Workbook

Sheet LS_RPRO
A1: Branch:
A2: 46296
A3: .
A4: DAYS | E4: Details of Discount | H4: NO. | K4: NO. OF STRING | M4: ENTERING | O4: CHARGE | P4: GIFT | Q4: OTHER COLLECTION | U4: CHECKS | V4: OTHER DISBURSEMENT | Z4: CASH DECLARED and DEPOSITED | AA4: CASH SALES | AB4: Calculated Cash Fr. Manual and OutSale | AC4: Cash Fr. Manual and OutSale | AD4: Over/(Short)
B5: GROSS | C5: DISCOUNT | D5: NET SALES | E5: ÀPPROVED DISC | F5: DISC W/O APPROVAL | G5: DEL. FEE | H5: CUSTOMER | I5: SHORTAGE | J5: OVERAGE | K5: TENNIS | L5: BADMIN2N | M5: CUSTOMER | O5: SALES | P5: CHECK | Q5: GC ISSUED-cash | R5: GC ISSUED-card | S5: DOWNPAYMENT | T5: ADV | V5: COD | W5: CASH ADVANCE | X5: (ADV) | Y5: CWT | AA5: AVAILABLE
A6: =A2+0 -> 46296 | B6: =102690.45+70551.9 -> 173242.35 | C6: 0 | D6: =+B6-C6 -> 173242.35 | F6: =+C6-E6 -> 0 | I6: =SUMIF(AB6,"<.01") -> 0 | J6: =SUMIF(AB6,">.01") -> 3 | K6: 0 | L6: 0 | M6: 359 | O6: =83892.7+53912.65 -> 137805.35 | X6: =4636 -> 4636 | Z6: =18800+12004 -> 30804 | AA6: =D6-O6-P6+Q6+S6+T6-U6-V6-W6-X6-Y6 -> 30801 | AB6: =Z6-AA6 -> 3 | AC6: =[1]MANUAL!X6+[1]OUTSALE!X6 -> 0 | AD6: =AB6-AC6 -> 3 | AF6: =O6+P6+U6+V6+W6+X6+Y6-Q6-R6-S6-T6 -> 142441.35
A7: =A6+1 -> 46297 | B7: =95054.25+113718.25 -> 208772.5 | C7: =169.8 -> 169.8 | D7: =+B7-C7 -> 208602.7 | E7: 169.8 | F7: =+C7-E7 -> 0 | H7: =45+56 -> 101 | I7: =SUMIF(AB7,"<.01") -> 0 | J7: =SUMIF(AB7,">.01") -> 4.05 | K7: 0 | L7: 2 | M7: 446 | O7: =71488.5+100077.25+236 -> 171801.75 | T7: 4636 | W7: 2363 | Z7: =23400+15678 -> 39078 | AA7: =D7-O7-P7+Q7+S7+T7-U7-V7-W7-X7-Y7 -> 39073.95 | AB7: =Z7-AA7 -> 4.05 | AC7: =[1]MANUAL!X7+[1]OUTSALE!X7 -> 0 | AD7: =AB7-AC7 -> 4.05 | AF7: =O7+P7+U7+V7+W7+X7+Y7-Q7-R7-S7-T7 -> 169528.75
A8: =A7+1 -> 46298 | B8: =355395.97+400 -> 355795.97 | C8: =349.5+359.46 -> 708.96 | D8: =+B8-C8 -> 355087.01 | E8: 708.96 | F8: =+C8-E8 -> 0 | H8: 138 | I8: =SUMIF(AB8,"<.01") -> 0 | J8: =SUMIF(AB8,">.01") -> 5.74 | K8: 4 | L8: 5 | M8: 976 | O8: =279997.55+5583.2 -> 285580.75 | V8: 400 | Z8: =69112 -> 69112 | AA8: =D8-O8-P8+Q8+S8+T8-U8-V8-W8-X8-Y8 -> 69106.26 | AB8: =Z8-AA8 -> 5.74 | AC8: =[1]MANUAL!X8+[1]OUTSALE!X8 -> 0 | AD8: =AB8-AC8 -> 5.74 | AF8: =O8+P8+U8+V8+W8+X8+Y8-Q8-R8-S8-T8 -> 285980.75
A9: =A8+1 -> 46299 | B9: =117294.75+182731.95 -> 300026.7 | C9: =109+199+1074+669+129.5 -> 2180.5 | D9: =+B9-C9 -> 297846.2 | E9: 2180.5 | F9: =+C9-E9 -> 0 | H9: =58+72 -> 130 | I9: =SUMIF(AB9,"<.01") -> 0 | J9: =SUMIF(AB9,">.01") -> 4 | K9: 0 | L9: 17 | M9: 883 | O9: =97328.25+145749.45 -> 243077.7 | Q9: 3100 | X9: =3040+3040 -> 6080 | Z9: =19658.5+32134 -> 51792.5 | AA9: =D9-O9-P9+Q9+S9+T9-U9-V9-W9-X9-Y9 -> 51788.5 | AB9: =Z9-AA9 -> 4 | AC9: =[1]MANUAL!X9+[1]OUTSALE!X9 -> 0 | AD9: =AB9-AC9 -> 4 | AF9: =O9+P9+U9+V9+W9+X9+Y9-Q9-R9-S9-T9 -> 246057.7
A10: =A9+1 -> 46300 | B10: =99966+114263.95+400 -> 214629.95 | C10: =299.6+470.46+826 -> 1596.06 | D10: =+B10-C10 -> 213033.89 | E10: 1596.06 | F10: =+C10-E10 -> 0 | H10: =33+42 -> 75 | I10: =SUMIF(AB10,"<.01") -> -47.2 | J10: =SUMIF(AB10,">.01") -> 0 | K10: 5 | L10: 1 | M10: 687 | O10: =74414.5+94015.19 -> 168429.69 | X10: 5280 | Z10: =25554+13723 -> 39277 | AA10: =D10-O10-P10+Q10+S10+T10-U10-V10-W10-X10-Y10 -> 39324.2 | AB10: =Z10-AA10 -> -47.2 | AC10: =MANUAL!X10+OUTSALE!X10 -> 0 | AD10: =AB10-AC10 -> -47.2 | AF10: =O10+P10+U10+V10+W10+X10+Y10-Q10-R10-S10-T10 -> 173709.69
A11: =A10+1 -> 46301 | B11: =72673.5+79201 -> 151874.5 | C11: =222.5+106.25 -> 328.75 | D11: =+B11-C11 -> 151545.75 | E11: 328.75 | F11: =+C11-E11 -> 0 | H11: =33+39 -> 72 | I11: =SUMIF(AB11,"<.01") -> 0 | J11: =SUMIF(AB11,">.01") -> 0 | K11: 1 | L11: 1 | M11: 333 | O11: =65038.5+78559.25 -> 143597.75 | T11: 11360 | Z11: =7635+11673 -> 19308 | AA11: =D11-O11-P11+Q11+S11+T11-U11-V11-W11-X11-Y11 -> 19308 | AB11: =Z11-AA11 -> 0 | AC11: =MANUAL!X11+OUTSALE!X11 -> 0 | AD11: =AB11-AC11 -> 0 | AF11: =O11+P11+U11+V11+W11+X11+Y11-Q11-R11-S11-T11 -> 132237.75
A12: =A11+1 -> 46302 | B12: =40683+75860.95 -> 116543.95 | C12: =328+119+319.5+199.8 -> 966.3 | D12: =+B12-C12 -> 115577.65 | E12: 966.3 | F12: =+C12-E12 -> 0 | H12: =23+27 -> 50 | I12: =SUMIF(AB12,"<.01") -> 0 | J12: =SUMIF(AB12,">.01") -> 1 | K12: 0 | L12: 0 | M12: 316 | O12: =16052+7208+718+1493.5+56438.9 -> 81910.4 | Z12: =14446+19222.25 -> 33668.25 | AA12: =D12-O12-P12+Q12+S12+T12-U12-V12-W12-X12-Y12 -> 33667.25 | AB12: =Z12-AA12 -> 1 | AC12: =MANUAL!X12+OUTSALE!X12 -> 0 | AD12: =AB12-AC12 -> 1 | AF12: =O12+P12+U12+V12+W12+X12+Y12-Q12-R12-S12-T12 -> 81910.4
A13: =A12+1 -> 46303 | B13: =90672.5+56282 -> 146954.5 | C13: =749.25+519 -> 1268.25 | D13: =+B13-C13 -> 145686.25 | E13: 1268.25 | F13: =+C13-E13 -> 0 | H13: =31+36 -> 67 | I13: =SUMIF(AB13,"<.01") -> 0 | J13: =SUMIF(AB13,">.01") -> 3 | K13: 0 | L13: 0 | M13: 478 | O13: =83072.25+36993 -> 120065.25 | Z13: =6332+19292 -> 25624 | AA13: =D13-O13-P13+Q13+S13+T13-U13-V13-W13-X13-Y13 -> 25621 | AB13: =Z13-AA13 -> 3 | AC13: =MANUAL!X13+OUTSALE!X13 -> 0 | AD13: =AB13-AC13 -> 3 | AF13: =O13+P13+U13+V13+W13+X13+Y13-Q13-R13-S13-T13 -> 120065.25
A14: =A13+1 -> 46304 | B14: =92582+105796.74 -> 198378.74 | C14: =750+195+169.8+222.5 -> 1337.3 | D14: =+B14-C14 -> 197041.44 | E14: 1337.3 | F14: =+C14-E14 -> 0 | H14: =42+39 -> 81 | I14: =SUMIF(AB14,"<.01") -> 0 | J14: =SUMIF(AB14,">.01") -> 1.81 | K14: 1 | L14: 6 | M14: 531 | O14: =70675+98455.25 -> 169130.25 | Z14: =20963+6950 -> 27913 | AA14: =D14-O14-P14+Q14+S14+T14-U14-V14-W14-X14-Y14 -> 27911.19 | AB14: =Z14-AA14 -> 1.81 | AC14: =MANUAL!X14+OUTSALE!X14 -> 0 | AD14: =AB14-AC14 -> 1.81 | AF14: =O14+P14+U14+V14+W14+X14+Y14-Q14-R14-S14-T14 -> 169130.25
A15: =A14+1 -> 46305 | B15: =132154.54+184082.5 -> 316237.04 | C15: =124+599.25+169.11+169.8+2399+349.5+155.45 -> 3966.11 | D15: =+B15-C15 -> 312270.93 | E15: 3966.11 | F15: =+C15-E15 -> 0 | H15: =63+79 -> 142 | I15: =SUMIF(AB15,"<.01") -> 0 | J15: =SUMIF(AB15,">.01") -> 5.3 | K15: 5 | L15: 4 | M15: 887 | O15: =96791.23+3400.75+145931.75 -> 246123.73 | X15: =10849+1326.5+2395 -> 14570.5 | Z15: =18900+32682 -> 51582 | AA15: =D15-O15-P15+Q15+S15+T15-U15-V15-W15-X15-Y15 -> 51576.7 | AB15: =Z15-AA15 -> 5.3 | AC15: =MANUAL!X15+OUTSALE!X15 -> 0 | AD15: =AB15-AC15 -> 5.3 | AF15: =O15+P15+U15+V15+W15+X15+Y15-Q15-R15-S15-T15 -> 260694.23
A16: =A15+1 -> 46306 | B16: =108316.15+207018.25 -> 315334.4 | C16: =169.8+235+136+2748.75 -> 3289.55 | D16: =+B16-C16 -> 312044.85 | E16: 3289.55 | F16: =+C16-E16 -> 0 | H16: =46+87 -> 133 | I16: =SUMIF(AB16,"<.01") -> 0 | J16: =SUMIF(AB16,">.01") -> 11.85 | M16: 595 | O16: =82777.7+180376.5 -> 263154.2 | T16: =2395+10849+1326.5 -> 14570.5 | Z16: =21559+41914 -> 63473 | AA16: =D16-O16-P16+Q16+S16+T16-U16-V16-W16-X16-Y16 -> 63461.15 | AB16: =Z16-AA16 -> 11.85 | AC16: =MANUAL!X16+OUTSALE!X16 -> 0 | AD16: =AB16-AC16 -> 11.85 | AF16: =O16+P16+U16+V16+W16+X16+Y16-Q16-R16-S16-T16 -> 248583.7
A17: =A16+1 -> 46307 | B17: =70048+500+87562 -> 158110 | C17: =169.8+139+349.5 -> 658.3 | D17: =+B17-C17 -> 157451.7 | F17: =+C17-E17 -> 658.3 | H17: =24 -> 24 | I17: =SUMIF(AB17,"<.01") -> 0 | J17: =SUMIF(AB17,">.01") -> 2 | K17: 0 | L17: 2 | M17: 336 | O17: =58744.7+60859 -> 119603.7 | X17: =939.5+500 -> 1439.5 | Z17: =10555.5+25855 -> 36410.5 | AA17: =D17-O17-P17+Q17+S17+T17-U17-V17-W17-X17-Y17 -> 36408.5 | AB17: =Z17-AA17 -> 2 | AC17: =MANUAL!X17+OUTSALE!X17 -> 0 | AD17: =AB17-AC17 -> 2 | AF17: =O17+P17+U17+V17+W17+X17+Y17-Q17-R17-S17-T17 -> 121043.2
A18: =A17+1 -> 46308 | D18: =+B18-C18 -> 0 | F18: =+C18-E18 -> 0 | I18: =SUMIF(AB18,"<.01") -> 0 | J18: =SUMIF(AB18,">.01") -> 0 | AA18: =D18-O18-P18+Q18+S18+T18-U18-V18-W18-X18-Y18 -> 0 | AB18: =Z18-AA18 -> 0 | AC18: =MANUAL!X18+OUTSALE!X18 -> 0 | AD18: =AB18-AC18 -> 0 | AF18: =O18+P18+U18+V18+W18+X18+Y18-Q18-R18-S18-T18 -> 0
A19: =A18+1 -> 46309 | D19: =+B19-C19 -> 0 | F19: =+C19-E19 -> 0 | I19: =SUMIF(AB19,"<.01") -> 0 | J19: =SUMIF(AB19,">.01") -> 0 | AA19: =D19-O19-P19+Q19+S19+T19-U19-V19-W19-X19-Y19 -> 0 | AB19: =Z19-AA19 -> 0 | AC19: =MANUAL!X19+OUTSALE!X19 -> 0 | AD19: =AB19-AC19 -> 0 | AE19: dfx | AF19: =O19+P19+U19+V19+W19+X19+Y19-Q19-R19-S19-T19 -> 0
A20: =A19+1 -> 46310 | D20: =+B20-C20 -> 0 | F20: =+C20-E20 -> 0 | I20: =SUMIF(AB20,"<.01") -> 0 | J20: =SUMIF(AB20,">.01") -> 0 | AA20: =D20-O20-P20+Q20+S20+T20-U20-V20-W20-X20-Y20 -> 0 | AB20: =Z20-AA20 -> 0 | AC20: =MANUAL!X20+OUTSALE!X20 -> 0 | AD20: =AB20-AC20 -> 0 | AF20: =O20+P20+U20+V20+W20+X20+Y20-Q20-R20-S20-T20 -> 0
A21: Subtotal | B21: =SUM(B6:B20) -> 2655900.6 | C21: =SUM(C6:C20) -> 16469.88 | D21: =+B21-C21 -> 2639430.7 | E21: =SUM(E6:E20) -> 15811.58 | F21: =SUM(F6:F20) -> 658.3 | G21: =SUM(G6:G20) -> 0 | H21: =SUM(H6:H20) -> 1013 | I21: =SUM(I6:I20) -> -47.2 | J21: =SUM(J6:J20) -> 41.75 | K21: =SUM(K6:K20) -> 16 | L21: =SUM(L6:L20) -> 38 | M21: =SUM(M6:M20) -> 6827 | O21: =SUM(O6:O20) -> 2150280.5 | P21: =SUM(P6:P20) -> 0 | Q21: =SUM(Q6:Q20) -> 3100 | R21: =SUM(R6:R20) -> 0 | S21: =SUM(S6:S20) -> 0 | T21: =SUM(T6:T20) -> 30566.5 | U21: =SUM(U6:U20) -> 0 | V21: =SUM(V6:V20) -> 400 | ... AD21: =SUM(AD6:AD20) -> -5.45
A23: =A20+1 -> 46311 | D23: =+B23-C23 -> 0 | F23: =+C23-E23 -> 0 | I23: =SUMIF(AB23,"<.01") -> 0 | J23: =SUMIF(AB23,">.01") -> 0 | AA23: =D23-O23-P23+Q23+S23+T23-U23-V23-W23-X23-Y23 -> 0 | AB23: =Z23-AA23 -> 0 | AC23: =MANUAL!X23+OUTSALE!X23 -> 0 | AD23: =AB23-AC23 -> 0 | AF23: =O23+P23+U23+V23+W23+X23+Y23-Q23-R23-S23-T23 -> 0
A24: =A23+1 -> 46312 | D24: =+B24-C24 -> 0 | F24: =+C24-E24 -> 0 | I24: =SUMIF(AB24,"<.01") -> 0 | J24: =SUMIF(AB24,">.01") -> 0 | AA24: =D24-O24-P24+Q24+S24+T24-U24-V24-W24-X24-Y24 -> 0 | AB24: =Z24-AA24 -> 0 | AC24: =MANUAL!X24+OUTSALE!X24 -> 0 | AD24: =AB24-AC24 -> 0 | AF24: =O24+P24+U24+V24+W24+X24+Y24-Q24-R24-S24-T24 -> 0
A25: =A24+1 -> 46313 | D25: =+B25-C25 -> 0 | F25: =+C25-E25 -> 0 | I25: 0 | J25: =SUMIF(AB25,">.01") -> 0 | AA25: =D25-O25-P25+Q25+S25+T25-U25-V25-W25-X25-Y25 -> 0 | AB25: =Z25-AA25 -> 0 | AC25: =MANUAL!X25+OUTSALE!X25 -> 0 | AD25: =AB25-AC25 -> 0 | AF25: =O25+P25+U25+V25+W25+X25+Y25-Q25-R25-S25-T25 -> 0
A26: =A25+1 -> 46314 | D26: =+B26-C26 -> 0 | F26: =+C26-E26 -> 0 | I26: =SUMIF(AB26,"<.01") -> 0 | J26: =SUMIF(AB26,">.01") -> 0 | AA26: =D26-O26-P26+Q26+S26+T26-U26-V26-W26-X26-Y26 -> 0 | AB26: =Z26-AA26 -> 0 | AC26: =MANUAL!X26+OUTSALE!X26 -> 0 | AD26: =AB26-AC26 -> 0 | AF26: =O26+P26+U26+V26+W26+X26+Y26-Q26-R26-S26-T26 -> 0
A27: =A26+1 -> 46315 | D27: =+B27-C27 -> 0 | F27: =+C27-E27 -> 0 | I27: =SUMIF(AB27,"<.01") -> 0 | J27: =SUMIF(AB27,">.01") -> 0 | AA27: =D27-O27-P27+Q27+S27+T27-U27-V27-W27-X27-Y27 -> 0 | AB27: =Z27-AA27 -> 0 | AC27: =MANUAL!X27+OUTSALE!X27 -> 0 | AD27: =AB27-AC27 -> 0 | AF27: =O27+P27+U27+V27+W27+X27+Y27-Q27-R27-S27-T27 -> 0
A28: =A27+1 -> 46316 | D28: =+B28-C28 -> 0 | F28: =+C28-E28 -> 0 | I28: =SUMIF(AB28,"<.01") -> 0 | J28: =SUMIF(AB28,">.01") -> 0 | AA28: =D28-O28-P28+Q28+S28+T28-U28-V28-W28-X28-Y28 -> 0 | AB28: =Z28-AA28 -> 0 | AC28: =MANUAL!X28+OUTSALE!X28 -> 0 | AD28: =AB28-AC28 -> 0 | AF28: =O28+P28+U28+V28+W28+X28+Y28-Q28-R28-S28-T28 -> 0
A29: =A28+1 -> 46317 | D29: =+B29-C29 -> 0 | F29: =+C29-E29 -> 0 | I29: =SUMIF(AB29,"<.01") -> 0 | J29: =SUMIF(AB29,">.01") -> 0 | AA29: =D29-O29-P29+Q29+S29+T29-U29-V29-W29-X29-Y29 -> 0 | AB29: =Z29-AA29 -> 0 | AC29: =MANUAL!X29+OUTSALE!X29 -> 0 | AD29: =AB29-AC29 -> 0 | AF29: =O29+P29+U29+V29+W29+X29+Y29-Q29-R29-S29-T29 -> 0
A30: =A29+1 -> 46318 | D30: =+B30-C30 -> 0 | F30: =+C30-E30 -> 0 | I30: =SUMIF(AB30,"<.01") -> 0 | J30: =SUMIF(AB30,">.01") -> 0 | AA30: =D30-O30-P30+Q30+S30+T30-U30-V30-W30-X30-Y30 -> 0 | AB30: =Z30-AA30 -> 0 | AC30: =MANUAL!X30+OUTSALE!X30 -> 0 | AD30: =AB30-AC30 -> 0 | AF30: =O30+P30+U30+V30+W30+X30+Y30-Q30-R30-S30-T30 -> 0
A31: =A30+1 -> 46319 | D31: =+B31-C31 -> 0 | F31: =+C31-E31 -> 0 | I31: =SUMIF(AB31,"<.01") -> 0 | J31: =SUMIF(AB31,">.01") -> 0 | AA31: =D31-O31-P31+Q31+S31+T31-U31-V31-W31-X31-Y31 -> 0 | AB31: =Z31-AA31 -> 0 | AC31: =MANUAL!X31+OUTSALE!X31 -> 0 | AD31: =AB31-AC31 -> 0 | AF31: =O31+P31+U31+V31+W31+X31+Y31-Q31-R31-S31-T31 -> 0
A32: =A31+1 -> 46320 | D32: =+B32-C32 -> 0 | F32: =+C32-E32 -> 0 | I32: =SUMIF(AB32,"<.01") -> 0 | J32: =SUMIF(AB32,">.01") -> 0 | AA32: =D32-O32-P32+Q32+S32+T32-U32-V32-W32-X32-Y32 -> 0 | AB32: =Z32-AA32 -> 0 | AC32: =MANUAL!X32+OUTSALE!X32 -> 0 | AD32: =AB32-AC32 -> 0 | AF32: =O32+P32+U32+V32+W32+X32+Y32-Q32-R32-S32-T32 -> 0
A33: =A32+1 -> 46321 | D33: =+B33-C33 -> 0 | F33: =+C33-E33 -> 0 | I33: =SUMIF(AB33,"<.01") -> 0 | J33: =SUMIF(AB33,">.01") -> 0 | AA33: =D33-O33-P33+Q33+S33+T33-U33-V33-W33-X33-Y33 -> 0 | AB33: =Z33-AA33 -> 0 | AC33: =MANUAL!X33+OUTSALE!X33 -> 0 | AD33: =AB33-AC33 -> 0 | AF33: =O33+P33+U33+V33+W33+X33+Y33-Q33-R33-S33-T33 -> 0
A34: =A33+1 -> 46322 | D34: =+B34-C34 -> 0 | F34: =+C34-E34 -> 0 | I34: =SUMIF(AB34,"<.01") -> 0 | J34: =SUMIF(AB34,">.01") -> 0 | AA34: =D34-O34-P34+Q34+S34+T34-U34-V34-W34-X34-Y34 -> 0 | AB34: =Z34-AA34 -> 0 | AC34: =MANUAL!X34+OUTSALE!X34 -> 0 | AD34: =AB34-AC34 -> 0 | AF34: =O34+P34+U34+V34+W34+X34+Y34-Q34-R34-S34-T34 -> 0
A35: =A34+1 -> 46323 | D35: =+B35-C35 -> 0 | F35: =+C35-E35 -> 0 | I35: =SUMIF(AB35,"<.01") -> 0 | J35: =SUMIF(AB35,">.01") -> 0 | AA35: =D35-O35-P35+Q35+S35+T35-U35-V35-W35-X35-Y35 -> 0 | AB35: =Z35-AA35 -> 0 | AC35: =MANUAL!X35+OUTSALE!X35 -> 0 | AD35: =AB35-AC35 -> 0 | AF35: =O35+P35+U35+V35+W35+X35+Y35-Q35-R35-S35-T35 -> 0
A36: =A35+1 -> 46324 | D36: =+B36-C36 -> 0 | F36: =+C36-E36 -> 0 | I36: =SUMIF(AB36,"<.01") -> 0 | J36: =SUMIF(AB36,">.01") -> 0 | AA36: =D36-O36-P36+Q36+S36+T36-U36-V36-W36-X36-Y36 -> 0 | AB36: =Z36-AA36 -> 0 | AC36: =MANUAL!X36+OUTSALE!X36 -> 0 | AD36: =AB36-AC36 -> 0 | AF36: =O36+P36+U36+V36+W36+X36+Y36-Q36-R36-S36-T36 -> 0
A37: =A36+1 -> 46325 | D37: =+B37-C37 -> 0 | F37: =+C37-E37 -> 0 | I37: =SUMIF(AB37,"<.01") -> 0 | J37: =SUMIF(AB37,">.01") -> 0 | AA37: =D37-O37-P37+Q37+S37+T37-U37-V37-W37-X37-Y37 -> 0 | AB37: =Z37-AA37 -> 0 | AC37: =MANUAL!X37+OUTSALE!X37 -> 0 | AD37: =AB37-AC37 -> 0 | AF37: =O37+P37+U37+V37+W37+X37+Y37-Q37-R37-S37-T37 -> 0
A38: =A37+1 -> 46326 | D38: =+B38-C38 -> 0 | F38: =+C38-E38 -> 0 | I38: =SUMIF(AB38,"<.01") -> 0 | J38: =SUMIF(AB38,">.01") -> 0 | AA38: =D38-O38-P38+Q38+S38+T38-U38-V38-W38-X38-Y38 -> 0 | AB38: =Z38-AA38 -> 0 | AC38: =MANUAL!X38+OUTSALE!X38 -> 0 | AD38: =AB38-AC38 -> 0 | AF38: =O38+P38+U38+V38+W38+X38+Y38-Q38-R38-S38-T38 -> 0
A39: Subtotal | B39: =SUM(B23:B38) -> 0 | C39: =SUM(C23:C38) -> 0 | D39: =SUM(D23:D38) -> 0 | E39: =SUM(E23:E38) -> 0 | F39: =SUM(F23:F38) -> 0 | G39: =SUM(G23:G38) -> 0 | H39: =SUM(H23:H38) -> 0 | I39: =SUM(I23:I38) -> 0 | ... M39: =SUM(M23:M38) -> 0 | O39: =SUM(O23:O38) -> 0 | P39: =SUM(P23:P38) -> 0 | Q39: =SUM(Q23:Q38) -> 0 | R39: =SUM(R23:R38) -> 0 | S39: =SUM(S23:S38) -> 0 | T39: =SUM(T23:T38) -> 0 | U39: =SUM(U23:U38) -> 0 | V39: =SUM(V23:V38) -> 0 | ... AD39: =SUM(AD23:AD38) -> 0
A41: Total | B41: =+B21+B39 -> 2655900.6 | C41: =+C21+C39 -> 16469.88 | D41: =+B41-C41 -> 2639430.7 | E41: =+E21+E39 -> 15811.58 | F41: =+C41-E41 -> 658.3 | G41: =+G21+G39 -> 0 | H41: =+H21+H39 -> 1013 | I41: =+I21+I39 -> -47.2 | J41: =+J21+J39 -> 41.75 | K41: =+K21+K39 -> 16 | L41: =+L21+L39 -> 38 | M41: =+M21+M39 -> 6827 | O41: =+O21+O39 -> 2150280.5 | P41: =+P21+P39 -> 0 | Q41: =+Q21+Q39 -> 3100 | R41: =+R21+R39 -> 0 | S41: =+S21+S39 -> 0 | T41: =+T21+T39 -> 30566.5 | U41: =+U21+U39 -> 0 | V41: =+V21+V39 -> 400 | ... AD41: =+AD21+AD39 -> -5.45

Sheet MSI
A1: MANUALLY ADDED TRANSACTIONS
A2: DATE: APRIL 1-30, 2025
A3: Store Code:
A4: LEGEND: | B4: REASON(LS-POP UP)
A5: INF- | B5: ITEM NOT ON FILE
A6: WP- | B6: WRONG PRICE
P7: DISCOUNT | V7: CHARGE
A8: BRANCH | B8: DATE | C8: CSI No. | D8: Manual /OutSale | E8: SALES ORDER # | F8: Sales Shipment No. | G8: CON/ OUT | H8: ALU/UPC | I8: BRAND | J8: DESCRIPTION1 | K8: DESC2/ ARTICLE # | L8: SIZE/ COLOR | M8: QTY | N8: Unit Price | O8: SP | P8: % | Q8: DISC. AMOUNT | R8: NET PRICE | S8: CASH | T8: Check | U8: COD | V8: CREDIT CARD | W8: EMPLOYEES' CHARGE | X8: Other Charge | Y8: Customer Name for Charge transaction | Z8: CHARGE | AA8: GC/ OTHERS | AB8: CWT | AC8: REASON(LS-POP UP) | AD8: REMARKS | AE8: CASHIER NAME | AF8: SALES PERSON(SA) SALES AGENT | AG8: MIS-REMARKS
O9: =M9*N9 -> 0 | Q9: =O9*P9 -> 0 | R9: =O9-Q9 -> 0
O10: =M10*N10 -> 0 | Q10: =O10*P10 -> 0 | R10: =O10-Q10 -> 0
O11: =M11*N11 -> 0 | Q11: =O11*P11 -> 0 | R11: =O11-Q11 -> 0
O12: =M12*N12 -> 0 | Q12: =O12*P12 -> 0 | R12: =O12-Q12 -> 0
O13: =M13*N13 -> 0 | Q13: =O13*P13 -> 0 | R13: =O13-Q13 -> 0
O14: =M14*N14 -> 0 | Q14: =O14*P14 -> 0 | R14: =O14-Q14 -> 0
O15: =M15*N15 -> 0 | Q15: =O15*P15 -> 0 | R15: =O15-Q15 -> 0
O16: =M16*N16 -> 0 | Q16: =O16*P16 -> 0 | R16: =O16-Q16 -> 0
O17: =M17*N17 -> 0 | Q17: =O17*P17 -> 0 | R17: =O17-Q17 -> 0
O18: =M18*N18 -> 0 | Q18: =O18*P18 -> 0 | R18: =O18-Q18 -> 0
O19: =M19*N19 -> 0 | Q19: =O19*P19 -> 0 | R19: =O19-Q19 -> 0
O303: =SUBTOTAL(9,O10:O302) -> 0

Sheet MRet
A1: MANUAL RETURNS
A2: DATE: APRIL 1-30, 2025
A3: Store Code: | B3: =MSI!B3 -> 0
A4: LEGEND: | B4: REASON(LS-POP UP)
A5: INF- | B5: ITEM NOT ON FILE
A6: WP- | B6: WRONG PRICE
P7: DISCOUNT | V7: CHARGE
A8: BRANCH | B8: DATE | C8: RS# | D8: Manual/ OutSale | E8: SALES ORDER # | F8: Return Receipt No. | G8: CON/ OUT | H8: ALU/UPC | I8: BRAND | J8: DESCRIPTION1 | K8: DESC2/ARTICLE # | L8: SIZE/COLOR | M8: QTY | N8: Unit Price | O8: SP | P8: % | Q8: DISC. AMOUNT | R8: NET PRICE | S8: CASH | T8: Check | U8: COD | V8: CREDIT CARD | W8: EMPLOYEES' CHARGE | X8: Other Charge | Y8: Customer Name for Charge transaction | Z8: CHARGE | AA8: GC/ OTHERS | AB8: CWT | AC8: REASON(LS-POP UP) | AD8: REMARKS | AE8: CASHIER NAME | AF8: SALES PERSON(SA) SALES AGENT | AG8: MIS-REMARKS
A9: =B$3 -> 0 | O9: =M9*N9 -> 0 | Q9: =O9*P9 -> 0 | R9: =O9-Q9 -> 0 | Z9: =MRet[[#This Row],[CREDIT CARD]]+MRet[[#This Row],[EMPLOYEES'' CHARGE]]+MRet[[#This Row],[Other Charge]] -> 0
A10: =B$3 -> 0 | O10: =M10*N10 -> 0 | Q10: =O10*P10 -> 0 | R10: =O10-Q10 -> 0 | Z10: =MRet[[#This Row],[CREDIT CARD]]+MRet[[#This Row],[EMPLOYEES'' CHARGE]]+MRet[[#This Row],[Other Charge]] -> 0
A11: =B$3 -> 0 | O11: =M11*N11 -> 0 | Q11: =O11*P11 -> 0 | R11: =O11-Q11 -> 0 | Z11: =MRet[[#This Row],[CREDIT CARD]]+MRet[[#This Row],[EMPLOYEES'' CHARGE]]+MRet[[#This Row],[Other Charge]] -> 0
A12: =B$3 -> 0 | O12: =M12*N12 -> 0 | Q12: =O12*P12 -> 0 | R12: =O12-Q12 -> 0 | Z12: =MRet[[#This Row],[CREDIT CARD]]+MRet[[#This Row],[EMPLOYEES'' CHARGE]]+MRet[[#This Row],[Other Charge]] -> 0
A13: =B$3 -> 0 | O13: =M13*N13 -> 0 | Q13: =O13*P13 -> 0 | R13: =O13-Q13 -> 0 | Z13: =MRet[[#This Row],[CREDIT CARD]]+MRet[[#This Row],[EMPLOYEES'' CHARGE]]+MRet[[#This Row],[Other Charge]] -> 0
A14: =B$3 -> 0 | O14: =M14*N14 -> 0 | Q14: =O14*P14 -> 0 | R14: =O14-Q14 -> 0 | Z14: =MRet[[#This Row],[CREDIT CARD]]+MRet[[#This Row],[EMPLOYEES'' CHARGE]]+MRet[[#This Row],[Other Charge]] -> 0
A15: =B$3 -> 0 | O15: =M15*N15 -> 0 | Q15: =O15*P15 -> 0 | R15: =O15-Q15 -> 0 | Z15: =MRet[[#This Row],[CREDIT CARD]]+MRet[[#This Row],[EMPLOYEES'' CHARGE]]+MRet[[#This Row],[Other Charge]] -> 0
A16: =B$3 -> 0 | O16: =M16*N16 -> 0 | Q16: =O16*P16 -> 0 | R16: =O16-Q16 -> 0 | Z16: =MRet[[#This Row],[CREDIT CARD]]+MRet[[#This Row],[EMPLOYEES'' CHARGE]]+MRet[[#This Row],[Other Charge]] -> 0
O330: =SUBTOTAL(9,O10:O329) -> 0

Sheet MANUAL
A1: MANUAL
A2: =LS_RPRO!A2 -> 46296
E4: Details of Discount | H4: NO. | M4: CHARGE | N4: GIFT | O4: OTHER COLLECTION | S4: CHECKS | T4: OTHER DISBURSEMENT | X4: CASH | Y4: CASH SALES | Z4: Over/(short)
B5: GROSS | C5: DISCOUNT | D5: NET SALES | E5: ÀPPROVED DISC | F5: DISC W/O APPROVAL | G5: DEL. FEE | H5: CUSTOMER | I5: SHORTAGE | J5: OVERAGE | K5: INVOICES | M5: SALES | N5: CHECK | O5: GC ISSUED-cash | P5: GC ISSUED-card | Q5: DOWNPAYMENT | R5: ADV | T5: COD | U5: CASH ADVANCE | V5: (ADV) | W5: CWT | Y5: AVAILABLE
A6: =A2+0 -> 46296 | B6: =(SUMIFS(msi[[#All],[SP]],msi[[#All],[DATE]],$A6,msi[[#All],[Manual /OutSale]],"Manual"))-(SUMIFS(MRet[[#All],[SP]],MRet[[#All],[DATE]],$A6,MRet[[#All],[Manual/ OutSale]],"Manual")) -> 0 | C6: =(SUMIFS(msi[[#All],[DISC. AMOUNT]],msi[[#All],[DATE]],$A6,msi[[#All],[Manual /OutSale]],"Manual"))-(SUMIFS(MRet[[#All],[DISC. AMOUNT]],MRet[[#All],[DATE]],$A6,MRet[[#All],[Manual/ OutSale]],"Manual")) -> 0 | D6: =+B6-C6 -> 0 | F6: =+C6-E6 -> 0 | I6: =SUMIF(Z6,"<.01") -> 0 | J6: =SUMIF(Z6,">.01") -> 0 | M6: =(SUMIFS(msi[[#All],[CHARGE]],msi[[#All],[DATE]],$A6,msi[[#All],[Manual /OutSale]],"Manual"))-(SUMIFS(MRet[[#All],[CHARGE]],MRet[[#All],[DATE]],$A6,MRet[[#All],[Manual/ OutSale]],"Manual")) -> 0 | N6: =(SUMIFS(msi[[#All],[GC/ OTHERS]],msi[[#All],[DATE]],$A6,msi[[#All],[Manual /OutSale]],"Manual"))-(SUMIFS(MRet[[#All],[GC/ OTHERS]],MRet[[#All],[DATE]],$A6,MRet[[#All],[Manual/ OutSale]],"Manual")) -> 0 | S6: =(SUMIFS(msi[[#All],[Check]],msi[[#All],[DATE]],$A6,msi[[#All],[Manual /OutSale]],"Manual"))-(SUMIFS(MRet[[#All],[Check]],MRet[[#All],[DATE]],$A6,MRet[[#All],[Manual/ OutSale]],"Manual")) -> 0 | T6: =(SUMIFS(msi[[#All],[COD]],msi[[#All],[DATE]],$A6,msi[[#All],[Manual /OutSale]],"Manual"))-(SUMIFS(MRet[[#All],[COD]],MRet[[#All],[DATE]],$A6,MRet[[#All],[Manual/ OutSale]],"Manual")) -> 0 | U6: 0 | W6: =(SUMIFS(msi[[#All],[CWT]],msi[[#All],[DATE]],$A6,msi[[#All],[Manual /OutSale]],"Manual"))-(SUMIFS(MRet[[#All],[CWT]],MRet[[#All],[DATE]],$A6,MRet[[#All],[Manual/ OutSale]],"Manual")) -> 0 | X6: =(SUMIFS(msi[[#All],[CASH]],msi[[#All],[DATE]],$A6,msi[[#All],[Manual /OutSale]],"Manual"))-(SUMIFS(MRet[[#All],[CASH]],MRet[[#All],[DATE]],$A6,MRet[[#All],[Manual/ OutSale]],"Manual")) -> 0 | Y6: =D6-M6-N6+O6+Q6+R6-S6-T6-U6-V6-W6 -> 0 | Z6: =X6-Y6 -> 0
A7: =A6+1 -> 46297 | B7: =(SUMIFS(msi[[#All],[SP]],msi[[#All],[DATE]],$A7,msi[[#All],[Manual /OutSale]],"Manual"))-(SUMIFS(MRet[[#All],[SP]],MRet[[#All],[DATE]],$A7,MRet[[#All],[Manual/ OutSale]],"Manual")) -> 0 | C7: =(SUMIFS(msi[[#All],[DISC. AMOUNT]],msi[[#All],[DATE]],$A7,msi[[#All],[Manual /OutSale]],"Manual"))-(SUMIFS(MRet[[#All],[DISC. AMOUNT]],MRet[[#All],[DATE]],$A7,MRet[[#All],[Manual/ OutSale]],"Manual")) -> 0 | D7: =+B7-C7 -> 0 | F7: =+C7-E7 -> 0 | I7: =SUMIF(Z7,"<.01") -> 0 | J7: =SUMIF(Z7,">.01") -> 0 | M7: =(SUMIFS(msi[[#All],[CHARGE]],msi[[#All],[DATE]],$A7,msi[[#All],[Manual /OutSale]],"Manual"))-(SUMIFS(MRet[[#All],[CHARGE]],MRet[[#All],[DATE]],$A7,MRet[[#All],[Manual/ OutSale]],"Manual")) -> 0 | N7: =(SUMIFS(msi[[#All],[GC/ OTHERS]],msi[[#All],[DATE]],$A7,msi[[#All],[Manual /OutSale]],"Manual"))-(SUMIFS(MRet[[#All],[GC/ OTHERS]],MRet[[#All],[DATE]],$A7,MRet[[#All],[Manual/ OutSale]],"Manual")) -> 0 | S7: =(SUMIFS(msi[[#All],[Check]],msi[[#All],[DATE]],$A7,msi[[#All],[Manual /OutSale]],"Manual"))-(SUMIFS(MRet[[#All],[Check]],MRet[[#All],[DATE]],$A7,MRet[[#All],[Manual/ OutSale]],"Manual")) -> 0 | T7: =(SUMIFS(msi[[#All],[COD]],msi[[#All],[DATE]],$A7,msi[[#All],[Manual /OutSale]],"Manual"))-(SUMIFS(MRet[[#All],[COD]],MRet[[#All],[DATE]],$A7,MRet[[#All],[Manual/ OutSale]],"Manual")) -> 0 | U7: 0 | W7: =(SUMIFS(msi[[#All],[CWT]],msi[[#All],[DATE]],$A7,msi[[#All],[Manual /OutSale]],"Manual"))-(SUMIFS(MRet[[#All],[CWT]],MRet[[#All],[DATE]],$A7,MRet[[#All],[Manual/ OutSale]],"Manual")) -> 0 | X7: =(SUMIFS(msi[[#All],[CASH]],msi[[#All],[DATE]],$A7,msi[[#All],[Manual /OutSale]],"Manual"))-(SUMIFS(MRet[[#All],[CASH]],MRet[[#All],[DATE]],$A7,MRet[[#All],[Manual/ OutSale]],"Manual")) -> 0 | Y7: =D7-M7-N7+O7+Q7+R7-S7-T7-U7-V7-W7 -> 0 | Z7: =X7-Y7 -> 0
A8: =A7+1 -> 46298 | B8: =(SUMIFS(msi[[#All],[SP]],msi[[#All],[DATE]],$A8,msi[[#All],[Manual /OutSale]],"Manual"))-(SUMIFS(MRet[[#All],[SP]],MRet[[#All],[DATE]],$A8,MRet[[#All],[Manual/ OutSale]],"Manual")) -> 0 | C8: =(SUMIFS(msi[[#All],[DISC. AMOUNT]],msi[[#All],[DATE]],$A8,msi[[#All],[Manual /OutSale]],"Manual"))-(SUMIFS(MRet[[#All],[DISC. AMOUNT]],MRet[[#All],[DATE]],$A8,MRet[[#All],[Manual/ OutSale]],"Manual")) -> 0 | D8: =+B8-C8 -> 0 | F8: =+C8-E8 -> 0 | I8: =SUMIF(Z8,"<.01") -> 0 | J8: =SUMIF(Z8,">.01") -> 0 | M8: =(SUMIFS(msi[[#All],[CHARGE]],msi[[#All],[DATE]],$A8,msi[[#All],[Manual /OutSale]],"Manual"))-(SUMIFS(MRet[[#All],[CHARGE]],MRet[[#All],[DATE]],$A8,MRet[[#All],[Manual/ OutSale]],"Manual")) -> 0 | N8: =(SUMIFS(msi[[#All],[GC/ OTHERS]],msi[[#All],[DATE]],$A8,msi[[#All],[Manual /OutSale]],"Manual"))-(SUMIFS(MRet[[#All],[GC/ OTHERS]],MRet[[#All],[DATE]],$A8,MRet[[#All],[Manual/ OutSale]],"Manual")) -> 0 | S8: =(SUMIFS(msi[[#All],[Check]],msi[[#All],[DATE]],$A8,msi[[#All],[Manual /OutSale]],"Manual"))-(SUMIFS(MRet[[#All],[Check]],MRet[[#All],[DATE]],$A8,MRet[[#All],[Manual/ OutSale]],"Manual")) -> 0 | T8: =(SUMIFS(msi[[#All],[COD]],msi[[#All],[DATE]],$A8,msi[[#All],[Manual /OutSale]],"Manual"))-(SUMIFS(MRet[[#All],[COD]],MRet[[#All],[DATE]],$A8,MRet[[#All],[Manual/ OutSale]],"Manual")) -> 0 | U8: 0 | W8: =(SUMIFS(msi[[#All],[CWT]],msi[[#All],[DATE]],$A8,msi[[#All],[Manual /OutSale]],"Manual"))-(SUMIFS(MRet[[#All],[CWT]],MRet[[#All],[DATE]],$A8,MRet[[#All],[Manual/ OutSale]],"Manual")) -> 0 | X8: =(SUMIFS(msi[[#All],[CASH]],msi[[#All],[DATE]],$A8,msi[[#All],[Manual /OutSale]],"Manual"))-(SUMIFS(MRet[[#All],[CASH]],MRet[[#All],[DATE]],$A8,MRet[[#All],[Manual/ OutSale]],"Manual")) -> 0 | Y8: =D8-M8-N8+O8+Q8+R8-S8-T8-U8-V8-W8 -> 0 | Z8: =X8-Y8 -> 0
A9: =A8+1 -> 46299 | B9: =(SUMIFS(msi[[#All],[SP]],msi[[#All],[DATE]],$A9,msi[[#All],[Manual /OutSale]],"Manual"))-(SUMIFS(MRet[[#All],[SP]],MRet[[#All],[DATE]],$A9,MRet[[#All],[Manual/ OutSale]],"Manual")) -> 0 | C9: =(SUMIFS(msi[[#All],[DISC. AMOUNT]],msi[[#All],[DATE]],$A9,msi[[#All],[Manual /OutSale]],"Manual"))-(SUMIFS(MRet[[#All],[DISC. AMOUNT]],MRet[[#All],[DATE]],$A9,MRet[[#All],[Manual/ OutSale]],"Manual")) -> 0 | D9: =+B9-C9 -> 0 | F9: =+C9-E9 -> 0 | I9: =SUMIF(Z9,"<.01") -> 0 | J9: =SUMIF(Z9,">.01") -> 0 | M9: =(SUMIFS(msi[[#All],[CHARGE]],msi[[#All],[DATE]],$A9,msi[[#All],[Manual /OutSale]],"Manual"))-(SUMIFS(MRet[[#All],[CHARGE]],MRet[[#All],[DATE]],$A9,MRet[[#All],[Manual/ OutSale]],"Manual")) -> 0 | N9: =(SUMIFS(msi[[#All],[GC/ OTHERS]],msi[[#All],[DATE]],$A9,msi[[#All],[Manual /OutSale]],"Manual"))-(SUMIFS(MRet[[#All],[GC/ OTHERS]],MRet[[#All],[DATE]],$A9,MRet[[#All],[Manual/ OutSale]],"Manual")) -> 0 | S9: =(SUMIFS(msi[[#All],[Check]],msi[[#All],[DATE]],$A9,msi[[#All],[Manual /OutSale]],"Manual"))-(SUMIFS(MRet[[#All],[Check]],MRet[[#All],[DATE]],$A9,MRet[[#All],[Manual/ OutSale]],"Manual")) -> 0 | T9: =(SUMIFS(msi[[#All],[COD]],msi[[#All],[DATE]],$A9,msi[[#All],[Manual /OutSale]],"Manual"))-(SUMIFS(MRet[[#All],[COD]],MRet[[#All],[DATE]],$A9,MRet[[#All],[Manual/ OutSale]],"Manual")) -> 0 | U9: 0 | W9: =(SUMIFS(msi[[#All],[CWT]],msi[[#All],[DATE]],$A9,msi[[#All],[Manual /OutSale]],"Manual"))-(SUMIFS(MRet[[#All],[CWT]],MRet[[#All],[DATE]],$A9,MRet[[#All],[Manual/ OutSale]],"Manual")) -> 0 | X9: =(SUMIFS(msi[[#All],[CASH]],msi[[#All],[DATE]],$A9,msi[[#All],[Manual /OutSale]],"Manual"))-(SUMIFS(MRet[[#All],[CASH]],MRet[[#All],[DATE]],$A9,MRet[[#All],[Manual/ OutSale]],"Manual")) -> 0 | Y9: =D9-M9-N9+O9+Q9+R9-S9-T9-U9-V9-W9 -> 0 | Z9: =X9-Y9 -> 0
A10: =A9+1 -> 46300 | B10: =(SUMIFS(msi[[#All],[SP]],msi[[#All],[DATE]],$A10,msi[[#All],[Manual /OutSale]],"Manual"))-(SUMIFS(MRet[[#All],[SP]],MRet[[#All],[DATE]],$A10,MRet[[#All],[Manual/ OutSale]],"Manual")) -> 0 | C10: =(SUMIFS(msi[[#All],[DISC. AMOUNT]],msi[[#All],[DATE]],$A10,msi[[#All],[Manual /OutSale]],"Manual"))-(SUMIFS(MRet[[#All],[DISC. AMOUNT]],MRet[[#All],[DATE]],$A10,MRet[[#All],[Manual/ OutSale]],"Manual")) -> 0 | D10: =+B10-C10 -> 0 | F10: =+C10-E10 -> 0 | I10: =SUMIF(Z10,"<.01") -> 0 | J10: =SUMIF(Z10,">.01") -> 0 | M10: =(SUMIFS(msi[[#All],[CHARGE]],msi[[#All],[DATE]],$A10,msi[[#All],[Manual /OutSale]],"Manual"))-(SUMIFS(MRet[[#All],[CHARGE]],MRet[[#All],[DATE]],$A10,MRet[[#All],[Manual/ OutSale]],"Manual")) -> 0 | N10: =(SUMIFS(msi[[#All],[GC/ OTHERS]],msi[[#All],[DATE]],$A10,msi[[#All],[Manual /OutSale]],"Manual"))-(SUMIFS(MRet[[#All],[GC/ OTHERS]],MRet[[#All],[DATE]],$A10,MRet[[#All],[Manual/ OutSale]],"Manual")) -> 0 | S10: =(SUMIFS(msi[[#All],[Check]],msi[[#All],[DATE]],$A10,msi[[#All],[Manual /OutSale]],"Manual"))-(SUMIFS(MRet[[#All],[Check]],MRet[[#All],[DATE]],$A10,MRet[[#All],[Manual/ OutSale]],"Manual")) -> 0 | T10: =(SUMIFS(msi[[#All],[COD]],msi[[#All],[DATE]],$A10,msi[[#All],[Manual /OutSale]],"Manual"))-(SUMIFS(MRet[[#All],[COD]],MRet[[#All],[DATE]],$A10,MRet[[#All],[Manual/ OutSale]],"Manual")) -> 0 | U10: 0 | W10: =(SUMIFS(msi[[#All],[CWT]],msi[[#All],[DATE]],$A10,msi[[#All],[Manual /OutSale]],"Manual"))-(SUMIFS(MRet[[#All],[CWT]],MRet[[#All],[DATE]],$A10,MRet[[#All],[Manual/ OutSale]],"Manual")) -> 0 | X10: =(SUMIFS(msi[[#All],[CASH]],msi[[#All],[DATE]],$A10,msi[[#All],[Manual /OutSale]],"Manual"))-(SUMIFS(MRet[[#All],[CASH]],MRet[[#All],[DATE]],$A10,MRet[[#All],[Manual/ OutSale]],"Manual")) -> 0 | Y10: =D10-M10-N10+O10+Q10+R10-S10-T10-U10-V10-W10 -> 0 | Z10: =X10-Y10 -> 0
A11: =A10+1 -> 46301 | B11: =(SUMIFS(msi[[#All],[SP]],msi[[#All],[DATE]],$A11,msi[[#All],[Manual /OutSale]],"Manual"))-(SUMIFS(MRet[[#All],[SP]],MRet[[#All],[DATE]],$A11,MRet[[#All],[Manual/ OutSale]],"Manual")) -> 0 | C11: =(SUMIFS(msi[[#All],[DISC. AMOUNT]],msi[[#All],[DATE]],$A11,msi[[#All],[Manual /OutSale]],"Manual"))-(SUMIFS(MRet[[#All],[DISC. AMOUNT]],MRet[[#All],[DATE]],$A11,MRet[[#All],[Manual/ OutSale]],"Manual")) -> 0 | D11: =+B11-C11 -> 0 | F11: =+C11-E11 -> 0 | I11: =SUMIF(Z11,"<.01") -> 0 | J11: =SUMIF(Z11,">.01") -> 0 | M11: =(SUMIFS(msi[[#All],[CHARGE]],msi[[#All],[DATE]],$A11,msi[[#All],[Manual /OutSale]],"Manual"))-(SUMIFS(MRet[[#All],[CHARGE]],MRet[[#All],[DATE]],$A11,MRet[[#All],[Manual/ OutSale]],"Manual")) -> 0 | N11: =(SUMIFS(msi[[#All],[GC/ OTHERS]],msi[[#All],[DATE]],$A11,msi[[#All],[Manual /OutSale]],"Manual"))-(SUMIFS(MRet[[#All],[GC/ OTHERS]],MRet[[#All],[DATE]],$A11,MRet[[#All],[Manual/ OutSale]],"Manual")) -> 0 | S11: =(SUMIFS(msi[[#All],[Check]],msi[[#All],[DATE]],$A11,msi[[#All],[Manual /OutSale]],"Manual"))-(SUMIFS(MRet[[#All],[Check]],MRet[[#All],[DATE]],$A11,MRet[[#All],[Manual/ OutSale]],"Manual")) -> 0 | T11: =(SUMIFS(msi[[#All],[COD]],msi[[#All],[DATE]],$A11,msi[[#All],[Manual /OutSale]],"Manual"))-(SUMIFS(MRet[[#All],[COD]],MRet[[#All],[DATE]],$A11,MRet[[#All],[Manual/ OutSale]],"Manual")) -> 0 | U11: 0 | W11: =(SUMIFS(msi[[#All],[CWT]],msi[[#All],[DATE]],$A11,msi[[#All],[Manual /OutSale]],"Manual"))-(SUMIFS(MRet[[#All],[CWT]],MRet[[#All],[DATE]],$A11,MRet[[#All],[Manual/ OutSale]],"Manual")) -> 0 | X11: =(SUMIFS(msi[[#All],[CASH]],msi[[#All],[DATE]],$A11,msi[[#All],[Manual /OutSale]],"Manual"))-(SUMIFS(MRet[[#All],[CASH]],MRet[[#All],[DATE]],$A11,MRet[[#All],[Manual/ OutSale]],"Manual")) -> 0 | Y11: =D11-M11-N11+O11+Q11+R11-S11-T11-U11-V11-W11 -> 0 | Z11: =X11-Y11 -> 0
A12: =A11+1 -> 46302 | B12: =(SUMIFS(msi[[#All],[SP]],msi[[#All],[DATE]],$A12,msi[[#All],[Manual /OutSale]],"Manual"))-(SUMIFS(MRet[[#All],[SP]],MRet[[#All],[DATE]],$A12,MRet[[#All],[Manual/ OutSale]],"Manual")) -> 0 | C12: =(SUMIFS(msi[[#All],[DISC. AMOUNT]],msi[[#All],[DATE]],$A12,msi[[#All],[Manual /OutSale]],"Manual"))-(SUMIFS(MRet[[#All],[DISC. AMOUNT]],MRet[[#All],[DATE]],$A12,MRet[[#All],[Manual/ OutSale]],"Manual")) -> 0 | D12: =+B12-C12 -> 0 | F12: =+C12-E12 -> 0 | I12: =SUMIF(Z12,"<.01") -> 0 | J12: =SUMIF(Z12,">.01") -> 0 | M12: =(SUMIFS(msi[[#All],[CHARGE]],msi[[#All],[DATE]],$A12,msi[[#All],[Manual /OutSale]],"Manual"))-(SUMIFS(MRet[[#All],[CHARGE]],MRet[[#All],[DATE]],$A12,MRet[[#All],[Manual/ OutSale]],"Manual")) -> 0 | N12: =(SUMIFS(msi[[#All],[GC/ OTHERS]],msi[[#All],[DATE]],$A12,msi[[#All],[Manual /OutSale]],"Manual"))-(SUMIFS(MRet[[#All],[GC/ OTHERS]],MRet[[#All],[DATE]],$A12,MRet[[#All],[Manual/ OutSale]],"Manual")) -> 0 | S12: =(SUMIFS(msi[[#All],[Check]],msi[[#All],[DATE]],$A12,msi[[#All],[Manual /OutSale]],"Manual"))-(SUMIFS(MRet[[#All],[Check]],MRet[[#All],[DATE]],$A12,MRet[[#All],[Manual/ OutSale]],"Manual")) -> 0 | T12: =(SUMIFS(msi[[#All],[COD]],msi[[#All],[DATE]],$A12,msi[[#All],[Manual /OutSale]],"Manual"))-(SUMIFS(MRet[[#All],[COD]],MRet[[#All],[DATE]],$A12,MRet[[#All],[Manual/ OutSale]],"Manual")) -> 0 | U12: 0 | W12: =(SUMIFS(msi[[#All],[CWT]],msi[[#All],[DATE]],$A12,msi[[#All],[Manual /OutSale]],"Manual"))-(SUMIFS(MRet[[#All],[CWT]],MRet[[#All],[DATE]],$A12,MRet[[#All],[Manual/ OutSale]],"Manual")) -> 0 | X12: =(SUMIFS(msi[[#All],[CASH]],msi[[#All],[DATE]],$A12,msi[[#All],[Manual /OutSale]],"Manual"))-(SUMIFS(MRet[[#All],[CASH]],MRet[[#All],[DATE]],$A12,MRet[[#All],[Manual/ OutSale]],"Manual")) -> 0 | Y12: =D12-M12-N12+O12+Q12+R12-S12-T12-U12-V12-W12 -> 0 | Z12: =X12-Y12 -> 0
A13: =A12+1 -> 46303 | B13: =(SUMIFS(msi[[#All],[SP]],msi[[#All],[DATE]],$A13,msi[[#All],[Manual /OutSale]],"Manual"))-(SUMIFS(MRet[[#All],[SP]],MRet[[#All],[DATE]],$A13,MRet[[#All],[Manual/ OutSale]],"Manual")) -> 0 | C13: =(SUMIFS(msi[[#All],[DISC. AMOUNT]],msi[[#All],[DATE]],$A13,msi[[#All],[Manual /OutSale]],"Manual"))-(SUMIFS(MRet[[#All],[DISC. AMOUNT]],MRet[[#All],[DATE]],$A13,MRet[[#All],[Manual/ OutSale]],"Manual")) -> 0 | D13: =+B13-C13 -> 0 | F13: =+C13-E13 -> 0 | I13: =SUMIF(Z13,"<.01") -> 0 | J13: =SUMIF(Z13,">.01") -> 0 | M13: =(SUMIFS(msi[[#All],[CHARGE]],msi[[#All],[DATE]],$A13,msi[[#All],[Manual /OutSale]],"Manual"))-(SUMIFS(MRet[[#All],[CHARGE]],MRet[[#All],[DATE]],$A13,MRet[[#All],[Manual/ OutSale]],"Manual")) -> 0 | N13: =(SUMIFS(msi[[#All],[GC/ OTHERS]],msi[[#All],[DATE]],$A13,msi[[#All],[Manual /OutSale]],"Manual"))-(SUMIFS(MRet[[#All],[GC/ OTHERS]],MRet[[#All],[DATE]],$A13,MRet[[#All],[Manual/ OutSale]],"Manual")) -> 0 | S13: =(SUMIFS(msi[[#All],[Check]],msi[[#All],[DATE]],$A13,msi[[#All],[Manual /OutSale]],"Manual"))-(SUMIFS(MRet[[#All],[Check]],MRet[[#All],[DATE]],$A13,MRet[[#All],[Manual/ OutSale]],"Manual")) -> 0 | T13: =(SUMIFS(msi[[#All],[COD]],msi[[#All],[DATE]],$A13,msi[[#All],[Manual /OutSale]],"Manual"))-(SUMIFS(MRet[[#All],[COD]],MRet[[#All],[DATE]],$A13,MRet[[#All],[Manual/ OutSale]],"Manual")) -> 0 | U13: 0 | W13: =(SUMIFS(msi[[#All],[CWT]],msi[[#All],[DATE]],$A13,msi[[#All],[Manual /OutSale]],"Manual"))-(SUMIFS(MRet[[#All],[CWT]],MRet[[#All],[DATE]],$A13,MRet[[#All],[Manual/ OutSale]],"Manual")) -> 0 | X13: =(SUMIFS(msi[[#All],[CASH]],msi[[#All],[DATE]],$A13,msi[[#All],[Manual /OutSale]],"Manual"))-(SUMIFS(MRet[[#All],[CASH]],MRet[[#All],[DATE]],$A13,MRet[[#All],[Manual/ OutSale]],"Manual")) -> 0 | Y13: =D13-M13-N13+O13+Q13+R13-S13-T13-U13-V13-W13 -> 0 | Z13: =X13-Y13 -> 0
A14: =A13+1 -> 46304 | B14: =(SUMIFS(msi[[#All],[SP]],msi[[#All],[DATE]],$A14,msi[[#All],[Manual /OutSale]],"Manual"))-(SUMIFS(MRet[[#All],[SP]],MRet[[#All],[DATE]],$A14,MRet[[#All],[Manual/ OutSale]],"Manual")) -> 0 | C14: =(SUMIFS(msi[[#All],[DISC. AMOUNT]],msi[[#All],[DATE]],$A14,msi[[#All],[Manual /OutSale]],"Manual"))-(SUMIFS(MRet[[#All],[DISC. AMOUNT]],MRet[[#All],[DATE]],$A14,MRet[[#All],[Manual/ OutSale]],"Manual")) -> 0 | D14: =+B14-C14 -> 0 | F14: =+C14-E14 -> 0 | I14: =SUMIF(Z14,"<.01") -> 0 | J14: =SUMIF(Z14,">.01") -> 0 | M14: =(SUMIFS(msi[[#All],[CHARGE]],msi[[#All],[DATE]],$A14,msi[[#All],[Manual /OutSale]],"Manual"))-(SUMIFS(MRet[[#All],[CHARGE]],MRet[[#All],[DATE]],$A14,MRet[[#All],[Manual/ OutSale]],"Manual")) -> 0 | N14: =(SUMIFS(msi[[#All],[GC/ OTHERS]],msi[[#All],[DATE]],$A14,msi[[#All],[Manual /OutSale]],"Manual"))-(SUMIFS(MRet[[#All],[GC/ OTHERS]],MRet[[#All],[DATE]],$A14,MRet[[#All],[Manual/ OutSale]],"Manual")) -> 0 | S14: =(SUMIFS(msi[[#All],[Check]],msi[[#All],[DATE]],$A14,msi[[#All],[Manual /OutSale]],"Manual"))-(SUMIFS(MRet[[#All],[Check]],MRet[[#All],[DATE]],$A14,MRet[[#All],[Manual/ OutSale]],"Manual")) -> 0 | T14: =(SUMIFS(msi[[#All],[COD]],msi[[#All],[DATE]],$A14,msi[[#All],[Manual /OutSale]],"Manual"))-(SUMIFS(MRet[[#All],[COD]],MRet[[#All],[DATE]],$A14,MRet[[#All],[Manual/ OutSale]],"Manual")) -> 0 | U14: 0 | W14: =(SUMIFS(msi[[#All],[CWT]],msi[[#All],[DATE]],$A14,msi[[#All],[Manual /OutSale]],"Manual"))-(SUMIFS(MRet[[#All],[CWT]],MRet[[#All],[DATE]],$A14,MRet[[#All],[Manual/ OutSale]],"Manual")) -> 0 | X14: =(SUMIFS(msi[[#All],[CASH]],msi[[#All],[DATE]],$A14,msi[[#All],[Manual /OutSale]],"Manual"))-(SUMIFS(MRet[[#All],[CASH]],MRet[[#All],[DATE]],$A14,MRet[[#All],[Manual/ OutSale]],"Manual")) -> 0 | Y14: =D14-M14-N14+O14+Q14+R14-S14-T14-U14-V14-W14 -> 0 | Z14: =X14-Y14 -> 0
A15: =A14+1 -> 46305 | B15: =(SUMIFS(msi[[#All],[SP]],msi[[#All],[DATE]],$A15,msi[[#All],[Manual /OutSale]],"Manual"))-(SUMIFS(MRet[[#All],[SP]],MRet[[#All],[DATE]],$A15,MRet[[#All],[Manual/ OutSale]],"Manual")) -> 0 | C15: =(SUMIFS(msi[[#All],[DISC. AMOUNT]],msi[[#All],[DATE]],$A15,msi[[#All],[Manual /OutSale]],"Manual"))-(SUMIFS(MRet[[#All],[DISC. AMOUNT]],MRet[[#All],[DATE]],$A15,MRet[[#All],[Manual/ OutSale]],"Manual")) -> 0 | D15: =+B15-C15 -> 0 | F15: =+C15-E15 -> 0 | I15: =SUMIF(Z15,"<.01") -> 0 | J15: =SUMIF(Z15,">.01") -> 0 | M15: =(SUMIFS(msi[[#All],[CHARGE]],msi[[#All],[DATE]],$A15,msi[[#All],[Manual /OutSale]],"Manual"))-(SUMIFS(MRet[[#All],[CHARGE]],MRet[[#All],[DATE]],$A15,MRet[[#All],[Manual/ OutSale]],"Manual")) -> 0 | N15: =(SUMIFS(msi[[#All],[GC/ OTHERS]],msi[[#All],[DATE]],$A15,msi[[#All],[Manual /OutSale]],"Manual"))-(SUMIFS(MRet[[#All],[GC/ OTHERS]],MRet[[#All],[DATE]],$A15,MRet[[#All],[Manual/ OutSale]],"Manual")) -> 0 | S15: =(SUMIFS(msi[[#All],[Check]],msi[[#All],[DATE]],$A15,msi[[#All],[Manual /OutSale]],"Manual"))-(SUMIFS(MRet[[#All],[Check]],MRet[[#All],[DATE]],$A15,MRet[[#All],[Manual/ OutSale]],"Manual")) -> 0 | T15: =(SUMIFS(msi[[#All],[COD]],msi[[#All],[DATE]],$A15,msi[[#All],[Manual /OutSale]],"Manual"))-(SUMIFS(MRet[[#All],[COD]],MRet[[#All],[DATE]],$A15,MRet[[#All],[Manual/ OutSale]],"Manual")) -> 0 | U15: 0 | W15: =(SUMIFS(msi[[#All],[CWT]],msi[[#All],[DATE]],$A15,msi[[#All],[Manual /OutSale]],"Manual"))-(SUMIFS(MRet[[#All],[CWT]],MRet[[#All],[DATE]],$A15,MRet[[#All],[Manual/ OutSale]],"Manual")) -> 0 | X15: =(SUMIFS(msi[[#All],[CASH]],msi[[#All],[DATE]],$A15,msi[[#All],[Manual /OutSale]],"Manual"))-(SUMIFS(MRet[[#All],[CASH]],MRet[[#All],[DATE]],$A15,MRet[[#All],[Manual/ OutSale]],"Manual")) -> 0 | Y15: =D15-M15-N15+O15+Q15+R15-S15-T15-U15-V15-W15 -> 0 | Z15: =X15-Y15 -> 0
A16: =A15+1 -> 46306 | B16: =(SUMIFS(msi[[#All],[SP]],msi[[#All],[DATE]],$A16,msi[[#All],[Manual /OutSale]],"Manual"))-(SUMIFS(MRet[[#All],[SP]],MRet[[#All],[DATE]],$A16,MRet[[#All],[Manual/ OutSale]],"Manual")) -> 0 | C16: =(SUMIFS(msi[[#All],[DISC. AMOUNT]],msi[[#All],[DATE]],$A16,msi[[#All],[Manual /OutSale]],"Manual"))-(SUMIFS(MRet[[#All],[DISC. AMOUNT]],MRet[[#All],[DATE]],$A16,MRet[[#All],[Manual/ OutSale]],"Manual")) -> 0 | D16: =+B16-C16 -> 0 | F16: =+C16-E16 -> 0 | I16: =SUMIF(Z16,"<.01") -> 0 | J16: =SUMIF(Z16,">.01") -> 0 | M16: =(SUMIFS(msi[[#All],[CHARGE]],msi[[#All],[DATE]],$A16,msi[[#All],[Manual /OutSale]],"Manual"))-(SUMIFS(MRet[[#All],[CHARGE]],MRet[[#All],[DATE]],$A16,MRet[[#All],[Manual/ OutSale]],"Manual")) -> 0 | N16: =(SUMIFS(msi[[#All],[GC/ OTHERS]],msi[[#All],[DATE]],$A16,msi[[#All],[Manual /OutSale]],"Manual"))-(SUMIFS(MRet[[#All],[GC/ OTHERS]],MRet[[#All],[DATE]],$A16,MRet[[#All],[Manual/ OutSale]],"Manual")) -> 0 | S16: =(SUMIFS(msi[[#All],[Check]],msi[[#All],[DATE]],$A16,msi[[#All],[Manual /OutSale]],"Manual"))-(SUMIFS(MRet[[#All],[Check]],MRet[[#All],[DATE]],$A16,MRet[[#All],[Manual/ OutSale]],"Manual")) -> 0 | T16: =(SUMIFS(msi[[#All],[COD]],msi[[#All],[DATE]],$A16,msi[[#All],[Manual /OutSale]],"Manual"))-(SUMIFS(MRet[[#All],[COD]],MRet[[#All],[DATE]],$A16,MRet[[#All],[Manual/ OutSale]],"Manual")) -> 0 | U16: 0 | W16: =(SUMIFS(msi[[#All],[CWT]],msi[[#All],[DATE]],$A16,msi[[#All],[Manual /OutSale]],"Manual"))-(SUMIFS(MRet[[#All],[CWT]],MRet[[#All],[DATE]],$A16,MRet[[#All],[Manual/ OutSale]],"Manual")) -> 0 | X16: =(SUMIFS(msi[[#All],[CASH]],msi[[#All],[DATE]],$A16,msi[[#All],[Manual /OutSale]],"Manual"))-(SUMIFS(MRet[[#All],[CASH]],MRet[[#All],[DATE]],$A16,MRet[[#All],[Manual/ OutSale]],"Manual")) -> 0 | Y16: =D16-M16-N16+O16+Q16+R16-S16-T16-U16-V16-W16 -> 0 | Z16: =X16-Y16 -> 0
A17: =A16+1 -> 46307 | B17: =(SUMIFS(msi[[#All],[SP]],msi[[#All],[DATE]],$A17,msi[[#All],[Manual /OutSale]],"Manual"))-(SUMIFS(MRet[[#All],[SP]],MRet[[#All],[DATE]],$A17,MRet[[#All],[Manual/ OutSale]],"Manual")) -> 0 | C17: =(SUMIFS(msi[[#All],[DISC. AMOUNT]],msi[[#All],[DATE]],$A17,msi[[#All],[Manual /OutSale]],"Manual"))-(SUMIFS(MRet[[#All],[DISC. AMOUNT]],MRet[[#All],[DATE]],$A17,MRet[[#All],[Manual/ OutSale]],"Manual")) -> 0 | D17: =+B17-C17 -> 0 | F17: =+C17-E17 -> 0 | I17: =SUMIF(Z17,"<.01") -> 0 | J17: =SUMIF(Z17,">.01") -> 0 | M17: =(SUMIFS(msi[[#All],[CHARGE]],msi[[#All],[DATE]],$A17,msi[[#All],[Manual /OutSale]],"Manual"))-(SUMIFS(MRet[[#All],[CHARGE]],MRet[[#All],[DATE]],$A17,MRet[[#All],[Manual/ OutSale]],"Manual")) -> 0 | N17: =(SUMIFS(msi[[#All],[GC/ OTHERS]],msi[[#All],[DATE]],$A17,msi[[#All],[Manual /OutSale]],"Manual"))-(SUMIFS(MRet[[#All],[GC/ OTHERS]],MRet[[#All],[DATE]],$A17,MRet[[#All],[Manual/ OutSale]],"Manual")) -> 0 | S17: =(SUMIFS(msi[[#All],[Check]],msi[[#All],[DATE]],$A17,msi[[#All],[Manual /OutSale]],"Manual"))-(SUMIFS(MRet[[#All],[Check]],MRet[[#All],[DATE]],$A17,MRet[[#All],[Manual/ OutSale]],"Manual")) -> 0 | T17: =(SUMIFS(msi[[#All],[COD]],msi[[#All],[DATE]],$A17,msi[[#All],[Manual /OutSale]],"Manual"))-(SUMIFS(MRet[[#All],[COD]],MRet[[#All],[DATE]],$A17,MRet[[#All],[Manual/ OutSale]],"Manual")) -> 0 | U17: 0 | W17: =(SUMIFS(msi[[#All],[CWT]],msi[[#All],[DATE]],$A17,msi[[#All],[Manual /OutSale]],"Manual"))-(SUMIFS(MRet[[#All],[CWT]],MRet[[#All],[DATE]],$A17,MRet[[#All],[Manual/ OutSale]],"Manual")) -> 0 | X17: =(SUMIFS(msi[[#All],[CASH]],msi[[#All],[DATE]],$A17,msi[[#All],[Manual /OutSale]],"Manual"))-(SUMIFS(MRet[[#All],[CASH]],MRet[[#All],[DATE]],$A17,MRet[[#All],[Manual/ OutSale]],"Manual")) -> 0 | Y17: =D17-M17-N17+O17+Q17+R17-S17-T17-U17-V17-W17 -> 0 | Z17: =X17-Y17 -> 0
A18: =A17+1 -> 46308 | B18: =(SUMIFS(msi[[#All],[SP]],msi[[#All],[DATE]],$A18,msi[[#All],[Manual /OutSale]],"Manual"))-(SUMIFS(MRet[[#All],[SP]],MRet[[#All],[DATE]],$A18,MRet[[#All],[Manual/ OutSale]],"Manual")) -> 0 | C18: =(SUMIFS(msi[[#All],[DISC. AMOUNT]],msi[[#All],[DATE]],$A18,msi[[#All],[Manual /OutSale]],"Manual"))-(SUMIFS(MRet[[#All],[DISC. AMOUNT]],MRet[[#All],[DATE]],$A18,MRet[[#All],[Manual/ OutSale]],"Manual")) -> 0 | D18: =+B18-C18 -> 0 | F18: =+C18-E18 -> 0 | I18: =SUMIF(Z18,"<.01") -> 0 | J18: =SUMIF(Z18,">.01") -> 0 | M18: =(SUMIFS(msi[[#All],[CHARGE]],msi[[#All],[DATE]],$A18,msi[[#All],[Manual /OutSale]],"Manual"))-(SUMIFS(MRet[[#All],[CHARGE]],MRet[[#All],[DATE]],$A18,MRet[[#All],[Manual/ OutSale]],"Manual")) -> 0 | N18: =(SUMIFS(msi[[#All],[GC/ OTHERS]],msi[[#All],[DATE]],$A18,msi[[#All],[Manual /OutSale]],"Manual"))-(SUMIFS(MRet[[#All],[GC/ OTHERS]],MRet[[#All],[DATE]],$A18,MRet[[#All],[Manual/ OutSale]],"Manual")) -> 0 | S18: =(SUMIFS(msi[[#All],[Check]],msi[[#All],[DATE]],$A18,msi[[#All],[Manual /OutSale]],"Manual"))-(SUMIFS(MRet[[#All],[Check]],MRet[[#All],[DATE]],$A18,MRet[[#All],[Manual/ OutSale]],"Manual")) -> 0 | T18: =(SUMIFS(msi[[#All],[COD]],msi[[#All],[DATE]],$A18,msi[[#All],[Manual /OutSale]],"Manual"))-(SUMIFS(MRet[[#All],[COD]],MRet[[#All],[DATE]],$A18,MRet[[#All],[Manual/ OutSale]],"Manual")) -> 0 | U18: 0 | W18: =(SUMIFS(msi[[#All],[CWT]],msi[[#All],[DATE]],$A18,msi[[#All],[Manual /OutSale]],"Manual"))-(SUMIFS(MRet[[#All],[CWT]],MRet[[#All],[DATE]],$A18,MRet[[#All],[Manual/ OutSale]],"Manual")) -> 0 | X18: =(SUMIFS(msi[[#All],[CASH]],msi[[#All],[DATE]],$A18,msi[[#All],[Manual /OutSale]],"Manual"))-(SUMIFS(MRet[[#All],[CASH]],MRet[[#All],[DATE]],$A18,MRet[[#All],[Manual/ OutSale]],"Manual")) -> 0 | Y18: =D18-M18-N18+O18+Q18+R18-S18-T18-U18-V18-W18 -> 0 | Z18: =X18-Y18 -> 0
... A20: =A19+1 -> 46310 | B20: =(SUMIFS(msi[[#All],[SP]],msi[[#All],[DATE]],$A20,msi[[#All],[Manual /OutSale]],"Manual"))-(SUMIFS(MRet[[#All],[SP]],MRet[[#All],[DATE]],$A20,MRet[[#All],[Manual/ OutSale]],"Manual")) -> 0 | C20: =(SUMIFS(msi[[#All],[DISC. AMOUNT]],msi[[#All],[DATE]],$A20,msi[[#All],[Manual /OutSale]],"Manual"))-(SUMIFS(MRet[[#All],[DISC. AMOUNT]],MRet[[#All],[DATE]],$A20,MRet[[#All],[Manual/ OutSale]],"Manual")) -> 0 | D20: =+B20-C20 -> 0 | F20: =+C20-E20 -> 0 | I20: =SUMIF(Z20,"<.01") -> 0 | J20: =SUMIF(Z20,">.01") -> 0 | M20: =(SUMIFS(msi[[#All],[CHARGE]],msi[[#All],[DATE]],$A20,msi[[#All],[Manual /OutSale]],"Manual"))-(SUMIFS(MRet[[#All],[CHARGE]],MRet[[#All],[DATE]],$A20,MRet[[#All],[Manual/ OutSale]],"Manual")) -> 0 | N20: =(SUMIFS(msi[[#All],[GC/ OTHERS]],msi[[#All],[DATE]],$A20,msi[[#All],[Manual /OutSale]],"Manual"))-(SUMIFS(MRet[[#All],[GC/ OTHERS]],MRet[[#All],[DATE]],$A20,MRet[[#All],[Manual/ OutSale]],"Manual")) -> 0 | S20: =(SUMIFS(msi[[#All],[Check]],msi[[#All],[DATE]],$A20,msi[[#All],[Manual /OutSale]],"Manual"))-(SUMIFS(MRet[[#All],[Check]],MRet[[#All],[DATE]],$A20,MRet[[#All],[Manual/ OutSale]],"Manual")) -> 0 | T20: =(SUMIFS(msi[[#All],[COD]],msi[[#All],[DATE]],$A20,msi[[#All],[Manual /OutSale]],"Manual"))-(SUMIFS(MRet[[#All],[COD]],MRet[[#All],[DATE]],$A20,MRet[[#All],[Manual/ OutSale]],"Manual")) -> 0 | U20: 0 | W20: =(SUMIFS(msi[[#All],[CWT]],msi[[#All],[DATE]],$A20,msi[[#All],[Manual /OutSale]],"Manual"))-(SUMIFS(MRet[[#All],[CWT]],MRet[[#All],[DATE]],$A20,MRet[[#All],[Manual/ OutSale]],"Manual")) -> 0 | X20: =(SUMIFS(msi[[#All],[CASH]],msi[[#All],[DATE]],$A20,msi[[#All],[Manual /OutSale]],"Manual"))-(SUMIFS(MRet[[#All],[CASH]],MRet[[#All],[DATE]],$A20,MRet[[#All],[Manual/ OutSale]],"Manual")) -> 0 | Y20: =D20-M20-N20+O20+Q20+R20-S20-T20-U20-V20-W20 -> 0 | Z20: =X20-Y20 -> 0
B21: =SUM(B6:B20) -> 0 | C21: =SUM(C6:C20) -> 0 | D21: =SUM(D6:D20) -> 0 | E21: =SUM(E6:E20) -> 0 | F21: =SUM(F6:F20) -> 0 | G21: =SUM(G6:G20) -> 0 | H21: =SUM(H6:H20) -> 0 | I21: =SUM(I6:I20) -> 0 | ... K21: =SUM(K6:K20) -> 0 | M21: =SUM(M6:M20) -> 0 | N21: =SUM(N6:N20) -> 0 | O21: =SUM(O6:O20) -> 0 | P21: =SUM(P6:P20) -> 0 | Q21: =SUM(Q6:Q20) -> 0 | R21: =SUM(R6:R20) -> 0 | S21: =SUM(S6:S20) -> 0 | T21: =SUM(T6:T20) -> 0 | ... Z21: =SUM(Z6:Z20) -> 0
A23: =A20+1 -> 46311 | B23: =(SUMIFS(msi[[#All],[SP]],msi[[#All],[DATE]],$A23,msi[[#All],[Manual /OutSale]],"Manual"))-(SUMIFS(MRet[[#All],[SP]],MRet[[#All],[DATE]],$A23,MRet[[#All],[Manual/ OutSale]],"Manual")) -> 0 | C23: =(SUMIFS(msi[[#All],[DISC. AMOUNT]],msi[[#All],[DATE]],$A23,msi[[#All],[Manual /OutSale]],"Manual"))-(SUMIFS(MRet[[#All],[DISC. AMOUNT]],MRet[[#All],[DATE]],$A23,MRet[[#All],[Manual/ OutSale]],"Manual")) -> 0 | D23: =+B23-C23 -> 0 | F23: =+C23-E23 -> 0 | I23: =SUMIF(Z23,"<.01") -> 0 | J23: =SUMIF(Z23,">.01") -> 0 | M23: =(SUMIFS(msi[[#All],[CHARGE]],msi[[#All],[DATE]],$A23,msi[[#All],[Manual /OutSale]],"Manual"))-(SUMIFS(MRet[[#All],[CHARGE]],MRet[[#All],[DATE]],$A23,MRet[[#All],[Manual/ OutSale]],"Manual")) -> 0 | N23: =(SUMIFS(msi[[#All],[GC/ OTHERS]],msi[[#All],[DATE]],$A23,msi[[#All],[Manual /OutSale]],"Manual"))-(SUMIFS(MRet[[#All],[GC/ OTHERS]],MRet[[#All],[DATE]],$A23,MRet[[#All],[Manual/ OutSale]],"Manual")) -> 0 | S23: =(SUMIFS(msi[[#All],[Check]],msi[[#All],[DATE]],$A23,msi[[#All],[Manual /OutSale]],"Manual"))-(SUMIFS(MRet[[#All],[Check]],MRet[[#All],[DATE]],$A23,MRet[[#All],[Manual/ OutSale]],"Manual")) -> 0 | T23: =(SUMIFS(msi[[#All],[COD]],msi[[#All],[DATE]],$A23,msi[[#All],[Manual /OutSale]],"Manual"))-(SUMIFS(MRet[[#All],[COD]],MRet[[#All],[DATE]],$A23,MRet[[#All],[Manual/ OutSale]],"Manual")) -> 0 | U23: 0 | W23: =(SUMIFS(msi[[#All],[CWT]],msi[[#All],[DATE]],$A23,msi[[#All],[Manual /OutSale]],"Manual"))-(SUMIFS(MRet[[#All],[CWT]],MRet[[#All],[DATE]],$A23,MRet[[#All],[Manual/ OutSale]],"Manual")) -> 0 | X23: =(SUMIFS(msi[[#All],[CASH]],msi[[#All],[DATE]],$A23,msi[[#All],[Manual /OutSale]],"Manual"))-(SUMIFS(MRet[[#All],[CASH]],MRet[[#All],[DATE]],$A23,MRet[[#All],[Manual/ OutSale]],"Manual")) -> 0 | Y23: =D23-M23-N23+O23+Q23+R23-S23-T23-U23-V23-W23 -> 0 | Z23: =X23-Y23 -> 0
A24: =A23+1 -> 46312 | B24: =(SUMIFS(msi[[#All],[SP]],msi[[#All],[DATE]],$A24,msi[[#All],[Manual /OutSale]],"Manual"))-(SUMIFS(MRet[[#All],[SP]],MRet[[#All],[DATE]],$A24,MRet[[#All],[Manual/ OutSale]],"Manual")) -> 0 | C24: =(SUMIFS(msi[[#All],[DISC. AMOUNT]],msi[[#All],[DATE]],$A24,msi[[#All],[Manual /OutSale]],"Manual"))-(SUMIFS(MRet[[#All],[DISC. AMOUNT]],MRet[[#All],[DATE]],$A24,MRet[[#All],[Manual/ OutSale]],"Manual")) -> 0 | D24: =+B24-C24 -> 0 | F24: =+C24-E24 -> 0 | I24: =SUMIF(Z24,"<.01") -> 0 | J24: =SUMIF(Z24,">.01") -> 0 | M24: =(SUMIFS(msi[[#All],[CHARGE]],msi[[#All],[DATE]],$A24,msi[[#All],[Manual /OutSale]],"Manual"))-(SUMIFS(MRet[[#All],[CHARGE]],MRet[[#All],[DATE]],$A24,MRet[[#All],[Manual/ OutSale]],"Manual")) -> 0 | N24: =(SUMIFS(msi[[#All],[GC/ OTHERS]],msi[[#All],[DATE]],$A24,msi[[#All],[Manual /OutSale]],"Manual"))-(SUMIFS(MRet[[#All],[GC/ OTHERS]],MRet[[#All],[DATE]],$A24,MRet[[#All],[Manual/ OutSale]],"Manual")) -> 0 | S24: =(SUMIFS(msi[[#All],[Check]],msi[[#All],[DATE]],$A24,msi[[#All],[Manual /OutSale]],"Manual"))-(SUMIFS(MRet[[#All],[Check]],MRet[[#All],[DATE]],$A24,MRet[[#All],[Manual/ OutSale]],"Manual")) -> 0 | T24: =(SUMIFS(msi[[#All],[COD]],msi[[#All],[DATE]],$A24,msi[[#All],[Manual /OutSale]],"Manual"))-(SUMIFS(MRet[[#All],[COD]],MRet[[#All],[DATE]],$A24,MRet[[#All],[Manual/ OutSale]],"Manual")) -> 0 | U24: 0 | W24: =(SUMIFS(msi[[#All],[CWT]],msi[[#All],[DATE]],$A24,msi[[#All],[Manual /OutSale]],"Manual"))-(SUMIFS(MRet[[#All],[CWT]],MRet[[#All],[DATE]],$A24,MRet[[#All],[Manual/ OutSale]],"Manual")) -> 0 | X24: =(SUMIFS(msi[[#All],[CASH]],msi[[#All],[DATE]],$A24,msi[[#All],[Manual /OutSale]],"Manual"))-(SUMIFS(MRet[[#All],[CASH]],MRet[[#All],[DATE]],$A24,MRet[[#All],[Manual/ OutSale]],"Manual")) -> 0 | Y24: =D24-M24-N24+O24+Q24+R24-S24-T24-U24-V24-W24 -> 0 | Z24: =X24-Y24 -> 0
A25: =A24+1 -> 46313 | B25: =(SUMIFS(msi[[#All],[SP]],msi[[#All],[DATE]],$A25,msi[[#All],[Manual /OutSale]],"Manual"))-(SUMIFS(MRet[[#All],[SP]],MRet[[#All],[DATE]],$A25,MRet[[#All],[Manual/ OutSale]],"Manual")) -> 0 | C25: =(SUMIFS(msi[[#All],[DISC. AMOUNT]],msi[[#All],[DATE]],$A25,msi[[#All],[Manual /OutSale]],"Manual"))-(SUMIFS(MRet[[#All],[DISC. AMOUNT]],MRet[[#All],[DATE]],$A25,MRet[[#All],[Manual/ OutSale]],"Manual")) -> 0 | D25: =+B25-C25 -> 0 | F25: =+C25-E25 -> 0 | I25: =SUMIF(Z25,"<.01") -> 0 | J25: =SUMIF(Z25,">.01") -> 0 | M25: =(SUMIFS(msi[[#All],[CHARGE]],msi[[#All],[DATE]],$A25,msi[[#All],[Manual /OutSale]],"Manual"))-(SUMIFS(MRet[[#All],[CHARGE]],MRet[[#All],[DATE]],$A25,MRet[[#All],[Manual/ OutSale]],"Manual")) -> 0 | N25: =(SUMIFS(msi[[#All],[GC/ OTHERS]],msi[[#All],[DATE]],$A25,msi[[#All],[Manual /OutSale]],"Manual"))-(SUMIFS(MRet[[#All],[GC/ OTHERS]],MRet[[#All],[DATE]],$A25,MRet[[#All],[Manual/ OutSale]],"Manual")) -> 0 | S25: =(SUMIFS(msi[[#All],[Check]],msi[[#All],[DATE]],$A25,msi[[#All],[Manual /OutSale]],"Manual"))-(SUMIFS(MRet[[#All],[Check]],MRet[[#All],[DATE]],$A25,MRet[[#All],[Manual/ OutSale]],"Manual")) -> 0 | T25: =(SUMIFS(msi[[#All],[COD]],msi[[#All],[DATE]],$A25,msi[[#All],[Manual /OutSale]],"Manual"))-(SUMIFS(MRet[[#All],[COD]],MRet[[#All],[DATE]],$A25,MRet[[#All],[Manual/ OutSale]],"Manual")) -> 0 | U25: 0 | W25: =(SUMIFS(msi[[#All],[CWT]],msi[[#All],[DATE]],$A25,msi[[#All],[Manual /OutSale]],"Manual"))-(SUMIFS(MRet[[#All],[CWT]],MRet[[#All],[DATE]],$A25,MRet[[#All],[Manual/ OutSale]],"Manual")) -> 0 | X25: =(SUMIFS(msi[[#All],[CASH]],msi[[#All],[DATE]],$A25,msi[[#All],[Manual /OutSale]],"Manual"))-(SUMIFS(MRet[[#All],[CASH]],MRet[[#All],[DATE]],$A25,MRet[[#All],[Manual/ OutSale]],"Manual")) -> 0 | Y25: =D25-M25-N25+O25+Q25+R25-S25-T25-U25-V25-W25 -> 0 | Z25: =X25-Y25 -> 0
A26: =A25+1 -> 46314 | B26: =(SUMIFS(msi[[#All],[SP]],msi[[#All],[DATE]],$A26,msi[[#All],[Manual /OutSale]],"Manual"))-(SUMIFS(MRet[[#All],[SP]],MRet[[#All],[DATE]],$A26,MRet[[#All],[Manual/ OutSale]],"Manual")) -> 0 | C26: =(SUMIFS(msi[[#All],[DISC. AMOUNT]],msi[[#All],[DATE]],$A26,msi[[#All],[Manual /OutSale]],"Manual"))-(SUMIFS(MRet[[#All],[DISC. AMOUNT]],MRet[[#All],[DATE]],$A26,MRet[[#All],[Manual/ OutSale]],"Manual")) -> 0 | D26: =+B26-C26 -> 0 | F26: =+C26-E26 -> 0 | I26: =SUMIF(Z26,"<.01") -> 0 | J26: =SUMIF(Z26,">.01") -> 0 | M26: =(SUMIFS(msi[[#All],[CHARGE]],msi[[#All],[DATE]],$A26,msi[[#All],[Manual /OutSale]],"Manual"))-(SUMIFS(MRet[[#All],[CHARGE]],MRet[[#All],[DATE]],$A26,MRet[[#All],[Manual/ OutSale]],"Manual")) -> 0 | N26: =(SUMIFS(msi[[#All],[GC/ OTHERS]],msi[[#All],[DATE]],$A26,msi[[#All],[Manual /OutSale]],"Manual"))-(SUMIFS(MRet[[#All],[GC/ OTHERS]],MRet[[#All],[DATE]],$A26,MRet[[#All],[Manual/ OutSale]],"Manual")) -> 0 | S26: =(SUMIFS(msi[[#All],[Check]],msi[[#All],[DATE]],$A26,msi[[#All],[Manual /OutSale]],"Manual"))-(SUMIFS(MRet[[#All],[Check]],MRet[[#All],[DATE]],$A26,MRet[[#All],[Manual/ OutSale]],"Manual")) -> 0 | T26: =(SUMIFS(msi[[#All],[COD]],msi[[#All],[DATE]],$A26,msi[[#All],[Manual /OutSale]],"Manual"))-(SUMIFS(MRet[[#All],[COD]],MRet[[#All],[DATE]],$A26,MRet[[#All],[Manual/ OutSale]],"Manual")) -> 0 | U26: 0 | W26: =(SUMIFS(msi[[#All],[CWT]],msi[[#All],[DATE]],$A26,msi[[#All],[Manual /OutSale]],"Manual"))-(SUMIFS(MRet[[#All],[CWT]],MRet[[#All],[DATE]],$A26,MRet[[#All],[Manual/ OutSale]],"Manual")) -> 0 | X26: =(SUMIFS(msi[[#All],[CASH]],msi[[#All],[DATE]],$A26,msi[[#All],[Manual /OutSale]],"Manual"))-(SUMIFS(MRet[[#All],[CASH]],MRet[[#All],[DATE]],$A26,MRet[[#All],[Manual/ OutSale]],"Manual")) -> 0 | Y26: =D26-M26-N26+O26+Q26+R26-S26-T26-U26-V26-W26 -> 0 | Z26: =X26-Y26 -> 0
A27: =A26+1 -> 46315 | B27: =(SUMIFS(msi[[#All],[SP]],msi[[#All],[DATE]],$A27,msi[[#All],[Manual /OutSale]],"Manual"))-(SUMIFS(MRet[[#All],[SP]],MRet[[#All],[DATE]],$A27,MRet[[#All],[Manual/ OutSale]],"Manual")) -> 0 | C27: =(SUMIFS(msi[[#All],[DISC. AMOUNT]],msi[[#All],[DATE]],$A27,msi[[#All],[Manual /OutSale]],"Manual"))-(SUMIFS(MRet[[#All],[DISC. AMOUNT]],MRet[[#All],[DATE]],$A27,MRet[[#All],[Manual/ OutSale]],"Manual")) -> 0 | D27: =+B27-C27 -> 0 | F27: =+C27-E27 -> 0 | I27: =SUMIF(Z27,"<.01") -> 0 | J27: =SUMIF(Z27,">.01") -> 0 | M27: =(SUMIFS(msi[[#All],[CHARGE]],msi[[#All],[DATE]],$A27,msi[[#All],[Manual /OutSale]],"Manual"))-(SUMIFS(MRet[[#All],[CHARGE]],MRet[[#All],[DATE]],$A27,MRet[[#All],[Manual/ OutSale]],"Manual")) -> 0 | N27: =(SUMIFS(msi[[#All],[GC/ OTHERS]],msi[[#All],[DATE]],$A27,msi[[#All],[Manual /OutSale]],"Manual"))-(SUMIFS(MRet[[#All],[GC/ OTHERS]],MRet[[#All],[DATE]],$A27,MRet[[#All],[Manual/ OutSale]],"Manual")) -> 0 | S27: =(SUMIFS(msi[[#All],[Check]],msi[[#All],[DATE]],$A27,msi[[#All],[Manual /OutSale]],"Manual"))-(SUMIFS(MRet[[#All],[Check]],MRet[[#All],[DATE]],$A27,MRet[[#All],[Manual/ OutSale]],"Manual")) -> 0 | T27: =(SUMIFS(msi[[#All],[COD]],msi[[#All],[DATE]],$A27,msi[[#All],[Manual /OutSale]],"Manual"))-(SUMIFS(MRet[[#All],[COD]],MRet[[#All],[DATE]],$A27,MRet[[#All],[Manual/ OutSale]],"Manual")) -> 0 | U27: 0 | W27: =(SUMIFS(msi[[#All],[CWT]],msi[[#All],[DATE]],$A27,msi[[#All],[Manual /OutSale]],"Manual"))-(SUMIFS(MRet[[#All],[CWT]],MRet[[#All],[DATE]],$A27,MRet[[#All],[Manual/ OutSale]],"Manual")) -> 0 | X27: =(SUMIFS(msi[[#All],[CASH]],msi[[#All],[DATE]],$A27,msi[[#All],[Manual /OutSale]],"Manual"))-(SUMIFS(MRet[[#All],[CASH]],MRet[[#All],[DATE]],$A27,MRet[[#All],[Manual/ OutSale]],"Manual")) -> 0 | Y27: =D27-M27-N27+O27+Q27+R27-S27-T27-U27-V27-W27 -> 0 | Z27: =X27-Y27 -> 0
A28: =A27+1 -> 46316 | B28: =(SUMIFS(msi[[#All],[SP]],msi[[#All],[DATE]],$A28,msi[[#All],[Manual /OutSale]],"Manual"))-(SUMIFS(MRet[[#All],[SP]],MRet[[#All],[DATE]],$A28,MRet[[#All],[Manual/ OutSale]],"Manual")) -> 0 | C28: =(SUMIFS(msi[[#All],[DISC. AMOUNT]],msi[[#All],[DATE]],$A28,msi[[#All],[Manual /OutSale]],"Manual"))-(SUMIFS(MRet[[#All],[DISC. AMOUNT]],MRet[[#All],[DATE]],$A28,MRet[[#All],[Manual/ OutSale]],"Manual")) -> 0 | D28: =+B28-C28 -> 0 | F28: =+C28-E28 -> 0 | I28: =SUMIF(Z28,"<.01") -> 0 | J28: =SUMIF(Z28,">.01") -> 0 | M28: =(SUMIFS(msi[[#All],[CHARGE]],msi[[#All],[DATE]],$A28,msi[[#All],[Manual /OutSale]],"Manual"))-(SUMIFS(MRet[[#All],[CHARGE]],MRet[[#All],[DATE]],$A28,MRet[[#All],[Manual/ OutSale]],"Manual")) -> 0 | N28: =(SUMIFS(msi[[#All],[GC/ OTHERS]],msi[[#All],[DATE]],$A28,msi[[#All],[Manual /OutSale]],"Manual"))-(SUMIFS(MRet[[#All],[GC/ OTHERS]],MRet[[#All],[DATE]],$A28,MRet[[#All],[Manual/ OutSale]],"Manual")) -> 0 | S28: =(SUMIFS(msi[[#All],[Check]],msi[[#All],[DATE]],$A28,msi[[#All],[Manual /OutSale]],"Manual"))-(SUMIFS(MRet[[#All],[Check]],MRet[[#All],[DATE]],$A28,MRet[[#All],[Manual/ OutSale]],"Manual")) -> 0 | T28: =(SUMIFS(msi[[#All],[COD]],msi[[#All],[DATE]],$A28,msi[[#All],[Manual /OutSale]],"Manual"))-(SUMIFS(MRet[[#All],[COD]],MRet[[#All],[DATE]],$A28,MRet[[#All],[Manual/ OutSale]],"Manual")) -> 0 | U28: 0 | W28: =(SUMIFS(msi[[#All],[CWT]],msi[[#All],[DATE]],$A28,msi[[#All],[Manual /OutSale]],"Manual"))-(SUMIFS(MRet[[#All],[CWT]],MRet[[#All],[DATE]],$A28,MRet[[#All],[Manual/ OutSale]],"Manual")) -> 0 | X28: =(SUMIFS(msi[[#All],[CASH]],msi[[#All],[DATE]],$A28,msi[[#All],[Manual /OutSale]],"Manual"))-(SUMIFS(MRet[[#All],[CASH]],MRet[[#All],[DATE]],$A28,MRet[[#All],[Manual/ OutSale]],"Manual")) -> 0 | Y28: =D28-M28-N28+O28+Q28+R28-S28-T28-U28-V28-W28 -> 0 | Z28: =X28-Y28 -> 0
A29: =A28+1 -> 46317 | B29: =(SUMIFS(msi[[#All],[SP]],msi[[#All],[DATE]],$A29,msi[[#All],[Manual /OutSale]],"Manual"))-(SUMIFS(MRet[[#All],[SP]],MRet[[#All],[DATE]],$A29,MRet[[#All],[Manual/ OutSale]],"Manual")) -> 0 | C29: =(SUMIFS(msi[[#All],[DISC. AMOUNT]],msi[[#All],[DATE]],$A29,msi[[#All],[Manual /OutSale]],"Manual"))-(SUMIFS(MRet[[#All],[DISC. AMOUNT]],MRet[[#All],[DATE]],$A29,MRet[[#All],[Manual/ OutSale]],"Manual")) -> 0 | D29: =+B29-C29 -> 0 | F29: =+C29-E29 -> 0 | I29: =SUMIF(Z29,"<.01") -> 0 | J29: =SUMIF(Z29,">.01") -> 0 | M29: =(SUMIFS(msi[[#All],[CHARGE]],msi[[#All],[DATE]],$A29,msi[[#All],[Manual /OutSale]],"Manual"))-(SUMIFS(MRet[[#All],[CHARGE]],MRet[[#All],[DATE]],$A29,MRet[[#All],[Manual/ OutSale]],"Manual")) -> 0 | N29: =(SUMIFS(msi[[#All],[GC/ OTHERS]],msi[[#All],[DATE]],$A29,msi[[#All],[Manual /OutSale]],"Manual"))-(SUMIFS(MRet[[#All],[GC/ OTHERS]],MRet[[#All],[DATE]],$A29,MRet[[#All],[Manual/ OutSale]],"Manual")) -> 0 | S29: =(SUMIFS(msi[[#All],[Check]],msi[[#All],[DATE]],$A29,msi[[#All],[Manual /OutSale]],"Manual"))-(SUMIFS(MRet[[#All],[Check]],MRet[[#All],[DATE]],$A29,MRet[[#All],[Manual/ OutSale]],"Manual")) -> 0 | T29: =(SUMIFS(msi[[#All],[COD]],msi[[#All],[DATE]],$A29,msi[[#All],[Manual /OutSale]],"Manual"))-(SUMIFS(MRet[[#All],[COD]],MRet[[#All],[DATE]],$A29,MRet[[#All],[Manual/ OutSale]],"Manual")) -> 0 | U29: 0 | W29: =(SUMIFS(msi[[#All],[CWT]],msi[[#All],[DATE]],$A29,msi[[#All],[Manual /OutSale]],"Manual"))-(SUMIFS(MRet[[#All],[CWT]],MRet[[#All],[DATE]],$A29,MRet[[#All],[Manual/ OutSale]],"Manual")) -> 0 | X29: =(SUMIFS(msi[[#All],[CASH]],msi[[#All],[DATE]],$A29,msi[[#All],[Manual /OutSale]],"Manual"))-(SUMIFS(MRet[[#All],[CASH]],MRet[[#All],[DATE]],$A29,MRet[[#All],[Manual/ OutSale]],"Manual")) -> 0 | Y29: =D29-M29-N29+O29+Q29+R29-S29-T29-U29-V29-W29 -> 0 | Z29: =X29-Y29 -> 0
A30: =A29+1 -> 46318 | B30: =(SUMIFS(msi[[#All],[SP]],msi[[#All],[DATE]],$A30,msi[[#All],[Manual /OutSale]],"Manual"))-(SUMIFS(MRet[[#All],[SP]],MRet[[#All],[DATE]],$A30,MRet[[#All],[Manual/ OutSale]],"Manual")) -> 0 | C30: =(SUMIFS(msi[[#All],[DISC. AMOUNT]],msi[[#All],[DATE]],$A30,msi[[#All],[Manual /OutSale]],"Manual"))-(SUMIFS(MRet[[#All],[DISC. AMOUNT]],MRet[[#All],[DATE]],$A30,MRet[[#All],[Manual/ OutSale]],"Manual")) -> 0 | D30: =+B30-C30 -> 0 | F30: =+C30-E30 -> 0 | I30: =SUMIF(Z30,"<.01") -> 0 | J30: =SUMIF(Z30,">.01") -> 0 | M30: =(SUMIFS(msi[[#All],[CHARGE]],msi[[#All],[DATE]],$A30,msi[[#All],[Manual /OutSale]],"Manual"))-(SUMIFS(MRet[[#All],[CHARGE]],MRet[[#All],[DATE]],$A30,MRet[[#All],[Manual/ OutSale]],"Manual")) -> 0 | N30: =(SUMIFS(msi[[#All],[GC/ OTHERS]],msi[[#All],[DATE]],$A30,msi[[#All],[Manual /OutSale]],"Manual"))-(SUMIFS(MRet[[#All],[GC/ OTHERS]],MRet[[#All],[DATE]],$A30,MRet[[#All],[Manual/ OutSale]],"Manual")) -> 0 | S30: =(SUMIFS(msi[[#All],[Check]],msi[[#All],[DATE]],$A30,msi[[#All],[Manual /OutSale]],"Manual"))-(SUMIFS(MRet[[#All],[Check]],MRet[[#All],[DATE]],$A30,MRet[[#All],[Manual/ OutSale]],"Manual")) -> 0 | T30: =(SUMIFS(msi[[#All],[COD]],msi[[#All],[DATE]],$A30,msi[[#All],[Manual /OutSale]],"Manual"))-(SUMIFS(MRet[[#All],[COD]],MRet[[#All],[DATE]],$A30,MRet[[#All],[Manual/ OutSale]],"Manual")) -> 0 | U30: 0 | W30: =(SUMIFS(msi[[#All],[CWT]],msi[[#All],[DATE]],$A30,msi[[#All],[Manual /OutSale]],"Manual"))-(SUMIFS(MRet[[#All],[CWT]],MRet[[#All],[DATE]],$A30,MRet[[#All],[Manual/ OutSale]],"Manual")) -> 0 | X30: =(SUMIFS(msi[[#All],[CASH]],msi[[#All],[DATE]],$A30,msi[[#All],[Manual /OutSale]],"Manual"))-(SUMIFS(MRet[[#All],[CASH]],MRet[[#All],[DATE]],$A30,MRet[[#All],[Manual/ OutSale]],"Manual")) -> 0 | Y30: =D30-M30-N30+O30+Q30+R30-S30-T30-U30-V30-W30 -> 0 | Z30: =X30-Y30 -> 0
A31: =A30+1 -> 46319 | B31: =(SUMIFS(msi[[#All],[SP]],msi[[#All],[DATE]],$A31,msi[[#All],[Manual /OutSale]],"Manual"))-(SUMIFS(MRet[[#All],[SP]],MRet[[#All],[DATE]],$A31,MRet[[#All],[Manual/ OutSale]],"Manual")) -> 0 | C31: =(SUMIFS(msi[[#All],[DISC. AMOUNT]],msi[[#All],[DATE]],$A31,msi[[#All],[Manual /OutSale]],"Manual"))-(SUMIFS(MRet[[#All],[DISC. AMOUNT]],MRet[[#All],[DATE]],$A31,MRet[[#All],[Manual/ OutSale]],"Manual")) -> 0 | D31: =+B31-C31 -> 0 | F31: =+C31-E31 -> 0 | I31: =SUMIF(Z31,"<.01") -> 0 | J31: =SUMIF(Z31,">.01") -> 0 | M31: =(SUMIFS(msi[[#All],[CHARGE]],msi[[#All],[DATE]],$A31,msi[[#All],[Manual /OutSale]],"Manual"))-(SUMIFS(MRet[[#All],[CHARGE]],MRet[[#All],[DATE]],$A31,MRet[[#All],[Manual/ OutSale]],"Manual")) -> 0 | N31: =(SUMIFS(msi[[#All],[GC/ OTHERS]],msi[[#All],[DATE]],$A31,msi[[#All],[Manual /OutSale]],"Manual"))-(SUMIFS(MRet[[#All],[GC/ OTHERS]],MRet[[#All],[DATE]],$A31,MRet[[#All],[Manual/ OutSale]],"Manual")) -> 0 | S31: =(SUMIFS(msi[[#All],[Check]],msi[[#All],[DATE]],$A31,msi[[#All],[Manual /OutSale]],"Manual"))-(SUMIFS(MRet[[#All],[Check]],MRet[[#All],[DATE]],$A31,MRet[[#All],[Manual/ OutSale]],"Manual")) -> 0 | T31: =(SUMIFS(msi[[#All],[COD]],msi[[#All],[DATE]],$A31,msi[[#All],[Manual /OutSale]],"Manual"))-(SUMIFS(MRet[[#All],[COD]],MRet[[#All],[DATE]],$A31,MRet[[#All],[Manual/ OutSale]],"Manual")) -> 0 | U31: 0 | W31: =(SUMIFS(msi[[#All],[CWT]],msi[[#All],[DATE]],$A31,msi[[#All],[Manual /OutSale]],"Manual"))-(SUMIFS(MRet[[#All],[CWT]],MRet[[#All],[DATE]],$A31,MRet[[#All],[Manual/ OutSale]],"Manual")) -> 0 | X31: =(SUMIFS(msi[[#All],[CASH]],msi[[#All],[DATE]],$A31,msi[[#All],[Manual /OutSale]],"Manual"))-(SUMIFS(MRet[[#All],[CASH]],MRet[[#All],[DATE]],$A31,MRet[[#All],[Manual/ OutSale]],"Manual")) -> 0 | Y31: =D31-M31-N31+O31+Q31+R31-S31-T31-U31-V31-W31 -> 0 | Z31: =X31-Y31 -> 0
A32: =A31+1 -> 46320 | B32: =(SUMIFS(msi[[#All],[SP]],msi[[#All],[DATE]],$A32,msi[[#All],[Manual /OutSale]],"Manual"))-(SUMIFS(MRet[[#All],[SP]],MRet[[#All],[DATE]],$A32,MRet[[#All],[Manual/ OutSale]],"Manual")) -> 0 | C32: =(SUMIFS(msi[[#All],[DISC. AMOUNT]],msi[[#All],[DATE]],$A32,msi[[#All],[Manual /OutSale]],"Manual"))-(SUMIFS(MRet[[#All],[DISC. AMOUNT]],MRet[[#All],[DATE]],$A32,MRet[[#All],[Manual/ OutSale]],"Manual")) -> 0 | D32: =+B32-C32 -> 0 | F32: =+C32-E32 -> 0 | I32: =SUMIF(Z32,"<.01") -> 0 | J32: =SUMIF(Z32,">.01") -> 0 | M32: =(SUMIFS(msi[[#All],[CHARGE]],msi[[#All],[DATE]],$A32,msi[[#All],[Manual /OutSale]],"Manual"))-(SUMIFS(MRet[[#All],[CHARGE]],MRet[[#All],[DATE]],$A32,MRet[[#All],[Manual/ OutSale]],"Manual")) -> 0 | N32: =(SUMIFS(msi[[#All],[GC/ OTHERS]],msi[[#All],[DATE]],$A32,msi[[#All],[Manual /OutSale]],"Manual"))-(SUMIFS(MRet[[#All],[GC/ OTHERS]],MRet[[#All],[DATE]],$A32,MRet[[#All],[Manual/ OutSale]],"Manual")) -> 0 | S32: =(SUMIFS(msi[[#All],[Check]],msi[[#All],[DATE]],$A32,msi[[#All],[Manual /OutSale]],"Manual"))-(SUMIFS(MRet[[#All],[Check]],MRet[[#All],[DATE]],$A32,MRet[[#All],[Manual/ OutSale]],"Manual")) -> 0 | T32: =(SUMIFS(msi[[#All],[COD]],msi[[#All],[DATE]],$A32,msi[[#All],[Manual /OutSale]],"Manual"))-(SUMIFS(MRet[[#All],[COD]],MRet[[#All],[DATE]],$A32,MRet[[#All],[Manual/ OutSale]],"Manual")) -> 0 | U32: 0 | W32: =(SUMIFS(msi[[#All],[CWT]],msi[[#All],[DATE]],$A32,msi[[#All],[Manual /OutSale]],"Manual"))-(SUMIFS(MRet[[#All],[CWT]],MRet[[#All],[DATE]],$A32,MRet[[#All],[Manual/ OutSale]],"Manual")) -> 0 | X32: =(SUMIFS(msi[[#All],[CASH]],msi[[#All],[DATE]],$A32,msi[[#All],[Manual /OutSale]],"Manual"))-(SUMIFS(MRet[[#All],[CASH]],MRet[[#All],[DATE]],$A32,MRet[[#All],[Manual/ OutSale]],"Manual")) -> 0 | Y32: =D32-M32-N32+O32+Q32+R32-S32-T32-U32-V32-W32 -> 0 | Z32: =X32-Y32 -> 0
A33: =A32+1 -> 46321 | B33: =(SUMIFS(msi[[#All],[SP]],msi[[#All],[DATE]],$A33,msi[[#All],[Manual /OutSale]],"Manual"))-(SUMIFS(MRet[[#All],[SP]],MRet[[#All],[DATE]],$A33,MRet[[#All],[Manual/ OutSale]],"Manual")) -> 0 | C33: =(SUMIFS(msi[[#All],[DISC. AMOUNT]],msi[[#All],[DATE]],$A33,msi[[#All],[Manual /OutSale]],"Manual"))-(SUMIFS(MRet[[#All],[DISC. AMOUNT]],MRet[[#All],[DATE]],$A33,MRet[[#All],[Manual/ OutSale]],"Manual")) -> 0 | D33: =+B33-C33 -> 0 | F33: =+C33-E33 -> 0 | I33: =SUMIF(Z33,"<.01") -> 0 | J33: =SUMIF(Z33,">.01") -> 0 | M33: =(SUMIFS(msi[[#All],[CHARGE]],msi[[#All],[DATE]],$A33,msi[[#All],[Manual /OutSale]],"Manual"))-(SUMIFS(MRet[[#All],[CHARGE]],MRet[[#All],[DATE]],$A33,MRet[[#All],[Manual/ OutSale]],"Manual")) -> 0 | N33: =(SUMIFS(msi[[#All],[GC/ OTHERS]],msi[[#All],[DATE]],$A33,msi[[#All],[Manual /OutSale]],"Manual"))-(SUMIFS(MRet[[#All],[GC/ OTHERS]],MRet[[#All],[DATE]],$A33,MRet[[#All],[Manual/ OutSale]],"Manual")) -> 0 | S33: =(SUMIFS(msi[[#All],[Check]],msi[[#All],[DATE]],$A33,msi[[#All],[Manual /OutSale]],"Manual"))-(SUMIFS(MRet[[#All],[Check]],MRet[[#All],[DATE]],$A33,MRet[[#All],[Manual/ OutSale]],"Manual")) -> 0 | T33: =(SUMIFS(msi[[#All],[COD]],msi[[#All],[DATE]],$A33,msi[[#All],[Manual /OutSale]],"Manual"))-(SUMIFS(MRet[[#All],[COD]],MRet[[#All],[DATE]],$A33,MRet[[#All],[Manual/ OutSale]],"Manual")) -> 0 | U33: 0 | W33: =(SUMIFS(msi[[#All],[CWT]],msi[[#All],[DATE]],$A33,msi[[#All],[Manual /OutSale]],"Manual"))-(SUMIFS(MRet[[#All],[CWT]],MRet[[#All],[DATE]],$A33,MRet[[#All],[Manual/ OutSale]],"Manual")) -> 0 | X33: =(SUMIFS(msi[[#All],[CASH]],msi[[#All],[DATE]],$A33,msi[[#All],[Manual /OutSale]],"Manual"))-(SUMIFS(MRet[[#All],[CASH]],MRet[[#All],[DATE]],$A33,MRet[[#All],[Manual/ OutSale]],"Manual")) -> 0 | Y33: =D33-M33-N33+O33+Q33+R33-S33-T33-U33-V33-W33 -> 0 | Z33: =X33-Y33 -> 0
A34: =A33+1 -> 46322 | B34: =(SUMIFS(msi[[#All],[SP]],msi[[#All],[DATE]],$A34,msi[[#All],[Manual /OutSale]],"Manual"))-(SUMIFS(MRet[[#All],[SP]],MRet[[#All],[DATE]],$A34,MRet[[#All],[Manual/ OutSale]],"Manual")) -> 0 | C34: =(SUMIFS(msi[[#All],[DISC. AMOUNT]],msi[[#All],[DATE]],$A34,msi[[#All],[Manual /OutSale]],"Manual"))-(SUMIFS(MRet[[#All],[DISC. AMOUNT]],MRet[[#All],[DATE]],$A34,MRet[[#All],[Manual/ OutSale]],"Manual")) -> 0 | D34: =+B34-C34 -> 0 | F34: =+C34-E34 -> 0 | I34: =SUMIF(Z34,"<.01") -> 0 | J34: =SUMIF(Z34,">.01") -> 0 | M34: =(SUMIFS(msi[[#All],[CHARGE]],msi[[#All],[DATE]],$A34,msi[[#All],[Manual /OutSale]],"Manual"))-(SUMIFS(MRet[[#All],[CHARGE]],MRet[[#All],[DATE]],$A34,MRet[[#All],[Manual/ OutSale]],"Manual")) -> 0 | N34: =(SUMIFS(msi[[#All],[GC/ OTHERS]],msi[[#All],[DATE]],$A34,msi[[#All],[Manual /OutSale]],"Manual"))-(SUMIFS(MRet[[#All],[GC/ OTHERS]],MRet[[#All],[DATE]],$A34,MRet[[#All],[Manual/ OutSale]],"Manual")) -> 0 | S34: =(SUMIFS(msi[[#All],[Check]],msi[[#All],[DATE]],$A34,msi[[#All],[Manual /OutSale]],"Manual"))-(SUMIFS(MRet[[#All],[Check]],MRet[[#All],[DATE]],$A34,MRet[[#All],[Manual/ OutSale]],"Manual")) -> 0 | T34: =(SUMIFS(msi[[#All],[COD]],msi[[#All],[DATE]],$A34,msi[[#All],[Manual /OutSale]],"Manual"))-(SUMIFS(MRet[[#All],[COD]],MRet[[#All],[DATE]],$A34,MRet[[#All],[Manual/ OutSale]],"Manual")) -> 0 | U34: 0 | W34: =(SUMIFS(msi[[#All],[CWT]],msi[[#All],[DATE]],$A34,msi[[#All],[Manual /OutSale]],"Manual"))-(SUMIFS(MRet[[#All],[CWT]],MRet[[#All],[DATE]],$A34,MRet[[#All],[Manual/ OutSale]],"Manual")) -> 0 | X34: =(SUMIFS(msi[[#All],[CASH]],msi[[#All],[DATE]],$A34,msi[[#All],[Manual /OutSale]],"Manual"))-(SUMIFS(MRet[[#All],[CASH]],MRet[[#All],[DATE]],$A34,MRet[[#All],[Manual/ OutSale]],"Manual")) -> 0 | Y34: =D34-M34-N34+O34+Q34+R34-S34-T34-U34-V34-W34 -> 0 | Z34: =X34-Y34 -> 0
A35: =A34+1 -> 46323 | B35: =(SUMIFS(msi[[#All],[SP]],msi[[#All],[DATE]],$A35,msi[[#All],[Manual /OutSale]],"Manual"))-(SUMIFS(MRet[[#All],[SP]],MRet[[#All],[DATE]],$A35,MRet[[#All],[Manual/ OutSale]],"Manual")) -> 0 | C35: =(SUMIFS(msi[[#All],[DISC. AMOUNT]],msi[[#All],[DATE]],$A35,msi[[#All],[Manual /OutSale]],"Manual"))-(SUMIFS(MRet[[#All],[DISC. AMOUNT]],MRet[[#All],[DATE]],$A35,MRet[[#All],[Manual/ OutSale]],"Manual")) -> 0 | D35: =+B35-C35 -> 0 | F35: =+C35-E35 -> 0 | I35: =SUMIF(Z35,"<.01") -> 0 | J35: =SUMIF(Z35,">.01") -> 0 | M35: =(SUMIFS(msi[[#All],[CHARGE]],msi[[#All],[DATE]],$A35,msi[[#All],[Manual /OutSale]],"Manual"))-(SUMIFS(MRet[[#All],[CHARGE]],MRet[[#All],[DATE]],$A35,MRet[[#All],[Manual/ OutSale]],"Manual")) -> 0 | N35: =(SUMIFS(msi[[#All],[GC/ OTHERS]],msi[[#All],[DATE]],$A35,msi[[#All],[Manual /OutSale]],"Manual"))-(SUMIFS(MRet[[#All],[GC/ OTHERS]],MRet[[#All],[DATE]],$A35,MRet[[#All],[Manual/ OutSale]],"Manual")) -> 0 | S35: =(SUMIFS(msi[[#All],[Check]],msi[[#All],[DATE]],$A35,msi[[#All],[Manual /OutSale]],"Manual"))-(SUMIFS(MRet[[#All],[Check]],MRet[[#All],[DATE]],$A35,MRet[[#All],[Manual/ OutSale]],"Manual")) -> 0 | T35: =(SUMIFS(msi[[#All],[COD]],msi[[#All],[DATE]],$A35,msi[[#All],[Manual /OutSale]],"Manual"))-(SUMIFS(MRet[[#All],[COD]],MRet[[#All],[DATE]],$A35,MRet[[#All],[Manual/ OutSale]],"Manual")) -> 0 | U35: 0 | W35: =(SUMIFS(msi[[#All],[CWT]],msi[[#All],[DATE]],$A35,msi[[#All],[Manual /OutSale]],"Manual"))-(SUMIFS(MRet[[#All],[CWT]],MRet[[#All],[DATE]],$A35,MRet[[#All],[Manual/ OutSale]],"Manual")) -> 0 | X35: =(SUMIFS(msi[[#All],[CASH]],msi[[#All],[DATE]],$A35,msi[[#All],[Manual /OutSale]],"Manual"))-(SUMIFS(MRet[[#All],[CASH]],MRet[[#All],[DATE]],$A35,MRet[[#All],[Manual/ OutSale]],"Manual")) -> 0 | Y35: =D35-M35-N35+O35+Q35+R35-S35-T35-U35-V35-W35 -> 0 | Z35: =X35-Y35 -> 0
... A38: =A37+1 -> 46326 | B38: =(SUMIFS(msi[[#All],[SP]],msi[[#All],[DATE]],$A38,msi[[#All],[Manual /OutSale]],"Manual"))-(SUMIFS(MRet[[#All],[SP]],MRet[[#All],[DATE]],$A38,MRet[[#All],[Manual/ OutSale]],"Manual")) -> 0 | C38: =(SUMIFS(msi[[#All],[DISC. AMOUNT]],msi[[#All],[DATE]],$A38,msi[[#All],[Manual /OutSale]],"Manual"))-(SUMIFS(MRet[[#All],[DISC. AMOUNT]],MRet[[#All],[DATE]],$A38,MRet[[#All],[Manual/ OutSale]],"Manual")) -> 0 | D38: =+B38-C38 -> 0 | F38: =+C38-E38 -> 0 | I38: =SUMIF(Z38,"<.01") -> 0 | J38: =SUMIF(Z38,">.01") -> 0 | M38: =(SUMIFS(msi[[#All],[CHARGE]],msi[[#All],[DATE]],$A38,msi[[#All],[Manual /OutSale]],"Manual"))-(SUMIFS(MRet[[#All],[CHARGE]],MRet[[#All],[DATE]],$A38,MRet[[#All],[Manual/ OutSale]],"Manual")) -> 0 | N38: =(SUMIFS(msi[[#All],[GC/ OTHERS]],msi[[#All],[DATE]],$A38,msi[[#All],[Manual /OutSale]],"Manual"))-(SUMIFS(MRet[[#All],[GC/ OTHERS]],MRet[[#All],[DATE]],$A38,MRet[[#All],[Manual/ OutSale]],"Manual")) -> 0 | S38: =(SUMIFS(msi[[#All],[Check]],msi[[#All],[DATE]],$A38,msi[[#All],[Manual /OutSale]],"Manual"))-(SUMIFS(MRet[[#All],[Check]],MRet[[#All],[DATE]],$A38,MRet[[#All],[Manual/ OutSale]],"Manual")) -> 0 | T38: =(SUMIFS(msi[[#All],[COD]],msi[[#All],[DATE]],$A38,msi[[#All],[Manual /OutSale]],"Manual"))-(SUMIFS(MRet[[#All],[COD]],MRet[[#All],[DATE]],$A38,MRet[[#All],[Manual/ OutSale]],"Manual")) -> 0 | U38: 0 | W38: =(SUMIFS(msi[[#All],[CWT]],msi[[#All],[DATE]],$A38,msi[[#All],[Manual /OutSale]],"Manual"))-(SUMIFS(MRet[[#All],[CWT]],MRet[[#All],[DATE]],$A38,MRet[[#All],[Manual/ OutSale]],"Manual")) -> 0 | X38: =(SUMIFS(msi[[#All],[CASH]],msi[[#All],[DATE]],$A38,msi[[#All],[Manual /OutSale]],"Manual"))-(SUMIFS(MRet[[#All],[CASH]],MRet[[#All],[DATE]],$A38,MRet[[#All],[Manual/ OutSale]],"Manual")) -> 0 | Y38: =D38-M38-N38+O38+Q38+R38-S38-T38-U38-V38-W38 -> 0 | Z38: =X38-Y38 -> 0
B39: =SUM(B23:B38) -> 0 | C39: =SUM(C23:C38) -> 0 | D39: =SUM(D23:D38) -> 0 | E39: =SUM(E23:E38) -> 0 | F39: =SUM(F23:F38) -> 0 | G39: =SUM(G23:G38) -> 0 | H39: =SUM(H23:H38) -> 0 | I39: =SUM(I23:I38) -> 0 | ... K39: =SUM(K23:K38) -> 0 | M39: =SUM(M23:M38) -> 0 | N39: =SUM(N23:N38) -> 0 | O39: =SUM(O23:O38) -> 0 | P39: =SUM(P23:P38) -> 0 | Q39: =SUM(Q23:Q38) -> 0 | R39: =SUM(R23:R38) -> 0 | S39: =SUM(S23:S38) -> 0 | T39: =SUM(T23:T38) -> 0 | ... Z39: =SUM(Z23:Z38) -> 0
B41: =+B21+B39 -> 0 | C41: =+C21+C39 -> 0 | D41: =+D21+D39 -> 0 | E41: =+E21+E39 -> 0 | F41: =+F21+F39 -> 0 | G41: =+G21+G39 -> 0 | H41: =+H21+H39 -> 0 | I41: =+I21+I39 -> 0 | ... K41: =+K21+K39 -> 0 | M41: =+M21+M39 -> 0 | N41: =+N21+N39 -> 0 | O41: =+O21+O39 -> 0 | P41: =+P21+P39 -> 0 | Q41: =+Q21+Q39 -> 0 | R41: =+R21+R39 -> 0 | S41: =+S21+S39 -> 0 | T41: =+T21+T39 -> 0 | ... Z41: =+Z21+Z39 -> 0

Sheet OUTSALE
A1: OUTSALE
A2: =LS_RPRO!A2 -> 46296
E4: Details of Discount | H4: NO. | M4: CHARGE | N4: GIFT | O4: OTHER COLLECTION | S4: CHECKS | T4: OTHER DISBURSEMENT | X4: CASH DEPOSIT | Y4: CASH SALES | Z4: Over/(short)
B5: GROSS | C5: DISCOUNT | D5: NET SALES | E5: ÀPPROVED DISC | F5: DISC W/O APPROVAL | G5: DEL. FEE | H5: CUSTOMER | I5: SHORTAGE | J5: OVERAGE | K5: INVOICES | M5: SALES | N5: CHECK | O5: GC ISSUED-cash | P5: GC ISSUED-card | Q5: DOWNPAYMENT | R5: ADV | T5: COD | U5: CASH ADVANCE | V5: (ADV) | W5: CWT | Y5: AVAILABLE
A6: =A2+0 -> 46296 | B6: =(SUMIFS(msi[[#All],[SP]],msi[[#All],[DATE]],$A6,msi[[#All],[Manual /OutSale]],"OutSale"))-(SUMIFS(MRet[[#All],[SP]],MRet[[#All],[DATE]],$A6,MRet[[#All],[Manual/ OutSale]],"OutSale")) -> 0 | C6: =(SUMIFS(msi[[#All],[DISC. AMOUNT]],msi[[#All],[DATE]],$A6,msi[[#All],[Manual /OutSale]],"OutSale"))-(SUMIFS(MRet[[#All],[DISC. AMOUNT]],MRet[[#All],[DATE]],$A6,MRet[[#All],[Manual/ OutSale]],"OutSale")) -> 0 | D6: =+B6-C6 -> 0 | F6: =+C6-E6 -> 0 | I6: =SUMIF(Z6,"<.01") -> 0 | J6: =SUMIF(Z6,">.01") -> 0 | M6: =(SUMIFS(msi[[#All],[CHARGE]],msi[[#All],[DATE]],$A6,msi[[#All],[Manual /OutSale]],"OutSale"))-(SUMIFS(MRet[[#All],[CHARGE]],MRet[[#All],[DATE]],$A6,MRet[[#All],[Manual/ OutSale]],"OutSale")) -> 0 | N6: =(SUMIFS(msi[[#All],[GC/ OTHERS]],msi[[#All],[DATE]],$A6,msi[[#All],[Manual /OutSale]],"OutSale"))-(SUMIFS(MRet[[#All],[GC/ OTHERS]],MRet[[#All],[DATE]],$A6,MRet[[#All],[Manual/ OutSale]],"OutSale")) -> 0 | S6: =(SUMIFS(msi[[#All],[Check]],msi[[#All],[DATE]],$A6,msi[[#All],[Manual /OutSale]],"OutSale"))-(SUMIFS(MRet[[#All],[Check]],MRet[[#All],[DATE]],$A6,MRet[[#All],[Manual/ OutSale]],"OutSale")) -> 0 | T6: =(SUMIFS(msi[[#All],[COD]],msi[[#All],[DATE]],$A6,msi[[#All],[Manual /OutSale]],"OutSale"))-(SUMIFS(MRet[[#All],[COD]],MRet[[#All],[DATE]],$A6,MRet[[#All],[Manual/ OutSale]],"OutSale")) -> 0 | U6: 0 | W6: =(SUMIFS(msi[[#All],[CWT]],msi[[#All],[DATE]],$A6,msi[[#All],[Manual /OutSale]],"OutSale"))-(SUMIFS(MRet[[#All],[CWT]],MRet[[#All],[DATE]],$A6,MRet[[#All],[Manual/ OutSale]],"OutSale")) -> 0 | X6: =(SUMIFS(msi[[#All],[CASH]],msi[[#All],[DATE]],$A6,msi[[#All],[Manual /OutSale]],"OutSale"))-(SUMIFS(MRet[[#All],[CASH]],MRet[[#All],[DATE]],$A6,MRet[[#All],[Manual/ OutSale]],"OutSale")) -> 0 | Y6: =D6-M6-N6+O6+Q6+R6-S6-T6-U6-V6-W6 -> 0 | Z6: =X6-Y6 -> 0
A7: =A6+1 -> 46297 | B7: =(SUMIFS(msi[[#All],[SP]],msi[[#All],[DATE]],$A7,msi[[#All],[Manual /OutSale]],"OutSale"))-(SUMIFS(MRet[[#All],[SP]],MRet[[#All],[DATE]],$A7,MRet[[#All],[Manual/ OutSale]],"OutSale")) -> 0 | C7: =(SUMIFS(msi[[#All],[DISC. AMOUNT]],msi[[#All],[DATE]],$A7,msi[[#All],[Manual /OutSale]],"OutSale"))-(SUMIFS(MRet[[#All],[DISC. AMOUNT]],MRet[[#All],[DATE]],$A7,MRet[[#All],[Manual/ OutSale]],"OutSale")) -> 0 | D7: =+B7-C7 -> 0 | F7: =+C7-E7 -> 0 | I7: =SUMIF(Z7,"<.01") -> 0 | J7: =SUMIF(Z7,">.01") -> 0 | M7: =(SUMIFS(msi[[#All],[CHARGE]],msi[[#All],[DATE]],$A7,msi[[#All],[Manual /OutSale]],"OutSale"))-(SUMIFS(MRet[[#All],[CHARGE]],MRet[[#All],[DATE]],$A7,MRet[[#All],[Manual/ OutSale]],"OutSale")) -> 0 | N7: =(SUMIFS(msi[[#All],[GC/ OTHERS]],msi[[#All],[DATE]],$A7,msi[[#All],[Manual /OutSale]],"OutSale"))-(SUMIFS(MRet[[#All],[GC/ OTHERS]],MRet[[#All],[DATE]],$A7,MRet[[#All],[Manual/ OutSale]],"OutSale")) -> 0 | S7: =(SUMIFS(msi[[#All],[Check]],msi[[#All],[DATE]],$A7,msi[[#All],[Manual /OutSale]],"OutSale"))-(SUMIFS(MRet[[#All],[Check]],MRet[[#All],[DATE]],$A7,MRet[[#All],[Manual/ OutSale]],"OutSale")) -> 0 | T7: =(SUMIFS(msi[[#All],[COD]],msi[[#All],[DATE]],$A7,msi[[#All],[Manual /OutSale]],"OutSale"))-(SUMIFS(MRet[[#All],[COD]],MRet[[#All],[DATE]],$A7,MRet[[#All],[Manual/ OutSale]],"OutSale")) -> 0 | U7: 0 | W7: =(SUMIFS(msi[[#All],[CWT]],msi[[#All],[DATE]],$A7,msi[[#All],[Manual /OutSale]],"OutSale"))-(SUMIFS(MRet[[#All],[CWT]],MRet[[#All],[DATE]],$A7,MRet[[#All],[Manual/ OutSale]],"OutSale")) -> 0 | X7: =(SUMIFS(msi[[#All],[CASH]],msi[[#All],[DATE]],$A7,msi[[#All],[Manual /OutSale]],"OutSale"))-(SUMIFS(MRet[[#All],[CASH]],MRet[[#All],[DATE]],$A7,MRet[[#All],[Manual/ OutSale]],"OutSale")) -> 0 | Y7: =D7-M7-N7+O7+Q7+R7-S7-T7-U7-V7-W7 -> 0 | Z7: =X7-Y7 -> 0
A8: =A7+1 -> 46298 | B8: =(SUMIFS(msi[[#All],[SP]],msi[[#All],[DATE]],$A8,msi[[#All],[Manual /OutSale]],"OutSale"))-(SUMIFS(MRet[[#All],[SP]],MRet[[#All],[DATE]],$A8,MRet[[#All],[Manual/ OutSale]],"OutSale")) -> 0 | C8: =(SUMIFS(msi[[#All],[DISC. AMOUNT]],msi[[#All],[DATE]],$A8,msi[[#All],[Manual /OutSale]],"OutSale"))-(SUMIFS(MRet[[#All],[DISC. AMOUNT]],MRet[[#All],[DATE]],$A8,MRet[[#All],[Manual/ OutSale]],"OutSale")) -> 0 | D8: =+B8-C8 -> 0 | F8: =+C8-E8 -> 0 | I8: =SUMIF(Z8,"<.01") -> 0 | J8: =SUMIF(Z8,">.01") -> 0 | M8: =(SUMIFS(msi[[#All],[CHARGE]],msi[[#All],[DATE]],$A8,msi[[#All],[Manual /OutSale]],"OutSale"))-(SUMIFS(MRet[[#All],[CHARGE]],MRet[[#All],[DATE]],$A8,MRet[[#All],[Manual/ OutSale]],"OutSale")) -> 0 | N8: =(SUMIFS(msi[[#All],[GC/ OTHERS]],msi[[#All],[DATE]],$A8,msi[[#All],[Manual /OutSale]],"OutSale"))-(SUMIFS(MRet[[#All],[GC/ OTHERS]],MRet[[#All],[DATE]],$A8,MRet[[#All],[Manual/ OutSale]],"OutSale")) -> 0 | S8: =(SUMIFS(msi[[#All],[Check]],msi[[#All],[DATE]],$A8,msi[[#All],[Manual /OutSale]],"OutSale"))-(SUMIFS(MRet[[#All],[Check]],MRet[[#All],[DATE]],$A8,MRet[[#All],[Manual/ OutSale]],"OutSale")) -> 0 | T8: =(SUMIFS(msi[[#All],[COD]],msi[[#All],[DATE]],$A8,msi[[#All],[Manual /OutSale]],"OutSale"))-(SUMIFS(MRet[[#All],[COD]],MRet[[#All],[DATE]],$A8,MRet[[#All],[Manual/ OutSale]],"OutSale")) -> 0 | U8: 0 | W8: =(SUMIFS(msi[[#All],[CWT]],msi[[#All],[DATE]],$A8,msi[[#All],[Manual /OutSale]],"OutSale"))-(SUMIFS(MRet[[#All],[CWT]],MRet[[#All],[DATE]],$A8,MRet[[#All],[Manual/ OutSale]],"OutSale")) -> 0 | X8: =(SUMIFS(msi[[#All],[CASH]],msi[[#All],[DATE]],$A8,msi[[#All],[Manual /OutSale]],"OutSale"))-(SUMIFS(MRet[[#All],[CASH]],MRet[[#All],[DATE]],$A8,MRet[[#All],[Manual/ OutSale]],"OutSale")) -> 0 | Y8: =D8-M8-N8+O8+Q8+R8-S8-T8-U8-V8-W8 -> 0 | Z8: =X8-Y8 -> 0
A9: =A8+1 -> 46299 | B9: =(SUMIFS(msi[[#All],[SP]],msi[[#All],[DATE]],$A9,msi[[#All],[Manual /OutSale]],"OutSale"))-(SUMIFS(MRet[[#All],[SP]],MRet[[#All],[DATE]],$A9,MRet[[#All],[Manual/ OutSale]],"OutSale")) -> 0 | C9: =(SUMIFS(msi[[#All],[DISC. AMOUNT]],msi[[#All],[DATE]],$A9,msi[[#All],[Manual /OutSale]],"OutSale"))-(SUMIFS(MRet[[#All],[DISC. AMOUNT]],MRet[[#All],[DATE]],$A9,MRet[[#All],[Manual/ OutSale]],"OutSale")) -> 0 | D9: =+B9-C9 -> 0 | F9: =+C9-E9 -> 0 | I9: =SUMIF(Z9,"<.01") -> 0 | J9: =SUMIF(Z9,">.01") -> 0 | M9: =(SUMIFS(msi[[#All],[CHARGE]],msi[[#All],[DATE]],$A9,msi[[#All],[Manual /OutSale]],"OutSale"))-(SUMIFS(MRet[[#All],[CHARGE]],MRet[[#All],[DATE]],$A9,MRet[[#All],[Manual/ OutSale]],"OutSale")) -> 0 | N9: =(SUMIFS(msi[[#All],[GC/ OTHERS]],msi[[#All],[DATE]],$A9,msi[[#All],[Manual /OutSale]],"OutSale"))-(SUMIFS(MRet[[#All],[GC/ OTHERS]],MRet[[#All],[DATE]],$A9,MRet[[#All],[Manual/ OutSale]],"OutSale")) -> 0 | S9: =(SUMIFS(msi[[#All],[Check]],msi[[#All],[DATE]],$A9,msi[[#All],[Manual /OutSale]],"OutSale"))-(SUMIFS(MRet[[#All],[Check]],MRet[[#All],[DATE]],$A9,MRet[[#All],[Manual/ OutSale]],"OutSale")) -> 0 | T9: =(SUMIFS(msi[[#All],[COD]],msi[[#All],[DATE]],$A9,msi[[#All],[Manual /OutSale]],"OutSale"))-(SUMIFS(MRet[[#All],[COD]],MRet[[#All],[DATE]],$A9,MRet[[#All],[Manual/ OutSale]],"OutSale")) -> 0 | U9: 0 | W9: =(SUMIFS(msi[[#All],[CWT]],msi[[#All],[DATE]],$A9,msi[[#All],[Manual /OutSale]],"OutSale"))-(SUMIFS(MRet[[#All],[CWT]],MRet[[#All],[DATE]],$A9,MRet[[#All],[Manual/ OutSale]],"OutSale")) -> 0 | X9: =(SUMIFS(msi[[#All],[CASH]],msi[[#All],[DATE]],$A9,msi[[#All],[Manual /OutSale]],"OutSale"))-(SUMIFS(MRet[[#All],[CASH]],MRet[[#All],[DATE]],$A9,MRet[[#All],[Manual/ OutSale]],"OutSale")) -> 0 | Y9: =D9-M9-N9+O9+Q9+R9-S9-T9-U9-V9-W9 -> 0 | Z9: =X9-Y9 -> 0
A10: =A9+1 -> 46300 | B10: =(SUMIFS(msi[[#All],[SP]],msi[[#All],[DATE]],$A10,msi[[#All],[Manual /OutSale]],"OutSale"))-(SUMIFS(MRet[[#All],[SP]],MRet[[#All],[DATE]],$A10,MRet[[#All],[Manual/ OutSale]],"OutSale")) -> 0 | C10: =(SUMIFS(msi[[#All],[DISC. AMOUNT]],msi[[#All],[DATE]],$A10,msi[[#All],[Manual /OutSale]],"OutSale"))-(SUMIFS(MRet[[#All],[DISC. AMOUNT]],MRet[[#All],[DATE]],$A10,MRet[[#All],[Manual/ OutSale]],"OutSale")) -> 0 | D10: =+B10-C10 -> 0 | F10: =+C10-E10 -> 0 | I10: =SUMIF(Z10,"<.01") -> 0 | J10: =SUMIF(Z10,">.01") -> 0 | M10: =(SUMIFS(msi[[#All],[CHARGE]],msi[[#All],[DATE]],$A10,msi[[#All],[Manual /OutSale]],"OutSale"))-(SUMIFS(MRet[[#All],[CHARGE]],MRet[[#All],[DATE]],$A10,MRet[[#All],[Manual/ OutSale]],"OutSale")) -> 0 | N10: =(SUMIFS(msi[[#All],[GC/ OTHERS]],msi[[#All],[DATE]],$A10,msi[[#All],[Manual /OutSale]],"OutSale"))-(SUMIFS(MRet[[#All],[GC/ OTHERS]],MRet[[#All],[DATE]],$A10,MRet[[#All],[Manual/ OutSale]],"OutSale")) -> 0 | S10: =(SUMIFS(msi[[#All],[Check]],msi[[#All],[DATE]],$A10,msi[[#All],[Manual /OutSale]],"OutSale"))-(SUMIFS(MRet[[#All],[Check]],MRet[[#All],[DATE]],$A10,MRet[[#All],[Manual/ OutSale]],"OutSale")) -> 0 | T10: =(SUMIFS(msi[[#All],[COD]],msi[[#All],[DATE]],$A10,msi[[#All],[Manual /OutSale]],"OutSale"))-(SUMIFS(MRet[[#All],[COD]],MRet[[#All],[DATE]],$A10,MRet[[#All],[Manual/ OutSale]],"OutSale")) -> 0 | U10: 0 | W10: =(SUMIFS(msi[[#All],[CWT]],msi[[#All],[DATE]],$A10,msi[[#All],[Manual /OutSale]],"OutSale"))-(SUMIFS(MRet[[#All],[CWT]],MRet[[#All],[DATE]],$A10,MRet[[#All],[Manual/ OutSale]],"OutSale")) -> 0 | X10: =(SUMIFS(msi[[#All],[CASH]],msi[[#All],[DATE]],$A10,msi[[#All],[Manual /OutSale]],"OutSale"))-(SUMIFS(MRet[[#All],[CASH]],MRet[[#All],[DATE]],$A10,MRet[[#All],[Manual/ OutSale]],"OutSale")) -> 0 | Y10: =D10-M10-N10+O10+Q10+R10-S10-T10-U10-V10-W10 -> 0 | Z10: =X10-Y10 -> 0
A11: =A10+1 -> 46301 | B11: =(SUMIFS(msi[[#All],[SP]],msi[[#All],[DATE]],$A11,msi[[#All],[Manual /OutSale]],"OutSale"))-(SUMIFS(MRet[[#All],[SP]],MRet[[#All],[DATE]],$A11,MRet[[#All],[Manual/ OutSale]],"OutSale")) -> 0 | C11: =(SUMIFS(msi[[#All],[DISC. AMOUNT]],msi[[#All],[DATE]],$A11,msi[[#All],[Manual /OutSale]],"OutSale"))-(SUMIFS(MRet[[#All],[DISC. AMOUNT]],MRet[[#All],[DATE]],$A11,MRet[[#All],[Manual/ OutSale]],"OutSale")) -> 0 | D11: =+B11-C11 -> 0 | F11: =+C11-E11 -> 0 | I11: =SUMIF(Z11,"<.01") -> 0 | J11: =SUMIF(Z11,">.01") -> 0 | M11: =(SUMIFS(msi[[#All],[CHARGE]],msi[[#All],[DATE]],$A11,msi[[#All],[Manual /OutSale]],"OutSale"))-(SUMIFS(MRet[[#All],[CHARGE]],MRet[[#All],[DATE]],$A11,MRet[[#All],[Manual/ OutSale]],"OutSale")) -> 0 | N11: =(SUMIFS(msi[[#All],[GC/ OTHERS]],msi[[#All],[DATE]],$A11,msi[[#All],[Manual /OutSale]],"OutSale"))-(SUMIFS(MRet[[#All],[GC/ OTHERS]],MRet[[#All],[DATE]],$A11,MRet[[#All],[Manual/ OutSale]],"OutSale")) -> 0 | S11: =(SUMIFS(msi[[#All],[Check]],msi[[#All],[DATE]],$A11,msi[[#All],[Manual /OutSale]],"OutSale"))-(SUMIFS(MRet[[#All],[Check]],MRet[[#All],[DATE]],$A11,MRet[[#All],[Manual/ OutSale]],"OutSale")) -> 0 | T11: =(SUMIFS(msi[[#All],[COD]],msi[[#All],[DATE]],$A11,msi[[#All],[Manual /OutSale]],"OutSale"))-(SUMIFS(MRet[[#All],[COD]],MRet[[#All],[DATE]],$A11,MRet[[#All],[Manual/ OutSale]],"OutSale")) -> 0 | U11: 0 | W11: =(SUMIFS(msi[[#All],[CWT]],msi[[#All],[DATE]],$A11,msi[[#All],[Manual /OutSale]],"OutSale"))-(SUMIFS(MRet[[#All],[CWT]],MRet[[#All],[DATE]],$A11,MRet[[#All],[Manual/ OutSale]],"OutSale")) -> 0 | X11: =(SUMIFS(msi[[#All],[CASH]],msi[[#All],[DATE]],$A11,msi[[#All],[Manual /OutSale]],"OutSale"))-(SUMIFS(MRet[[#All],[CASH]],MRet[[#All],[DATE]],$A11,MRet[[#All],[Manual/ OutSale]],"OutSale")) -> 0 | Y11: =D11-M11-N11+O11+Q11+R11-S11-T11-U11-V11-W11 -> 0 | Z11: =X11-Y11 -> 0
A12: =A11+1 -> 46302 | B12: =(SUMIFS(msi[[#All],[SP]],msi[[#All],[DATE]],$A12,msi[[#All],[Manual /OutSale]],"OutSale"))-(SUMIFS(MRet[[#All],[SP]],MRet[[#All],[DATE]],$A12,MRet[[#All],[Manual/ OutSale]],"OutSale")) -> 0 | C12: =(SUMIFS(msi[[#All],[DISC. AMOUNT]],msi[[#All],[DATE]],$A12,msi[[#All],[Manual /OutSale]],"OutSale"))-(SUMIFS(MRet[[#All],[DISC. AMOUNT]],MRet[[#All],[DATE]],$A12,MRet[[#All],[Manual/ OutSale]],"OutSale")) -> 0 | D12: =+B12-C12 -> 0 | F12: =+C12-E12 -> 0 | I12: =SUMIF(Z12,"<.01") -> 0 | J12: =SUMIF(Z12,">.01") -> 0 | M12: =(SUMIFS(msi[[#All],[CHARGE]],msi[[#All],[DATE]],$A12,msi[[#All],[Manual /OutSale]],"OutSale"))-(SUMIFS(MRet[[#All],[CHARGE]],MRet[[#All],[DATE]],$A12,MRet[[#All],[Manual/ OutSale]],"OutSale")) -> 0 | N12: =(SUMIFS(msi[[#All],[GC/ OTHERS]],msi[[#All],[DATE]],$A12,msi[[#All],[Manual /OutSale]],"OutSale"))-(SUMIFS(MRet[[#All],[GC/ OTHERS]],MRet[[#All],[DATE]],$A12,MRet[[#All],[Manual/ OutSale]],"OutSale")) -> 0 | S12: =(SUMIFS(msi[[#All],[Check]],msi[[#All],[DATE]],$A12,msi[[#All],[Manual /OutSale]],"OutSale"))-(SUMIFS(MRet[[#All],[Check]],MRet[[#All],[DATE]],$A12,MRet[[#All],[Manual/ OutSale]],"OutSale")) -> 0 | T12: =(SUMIFS(msi[[#All],[COD]],msi[[#All],[DATE]],$A12,msi[[#All],[Manual /OutSale]],"OutSale"))-(SUMIFS(MRet[[#All],[COD]],MRet[[#All],[DATE]],$A12,MRet[[#All],[Manual/ OutSale]],"OutSale")) -> 0 | U12: 0 | W12: =(SUMIFS(msi[[#All],[CWT]],msi[[#All],[DATE]],$A12,msi[[#All],[Manual /OutSale]],"OutSale"))-(SUMIFS(MRet[[#All],[CWT]],MRet[[#All],[DATE]],$A12,MRet[[#All],[Manual/ OutSale]],"OutSale")) -> 0 | X12: =(SUMIFS(msi[[#All],[CASH]],msi[[#All],[DATE]],$A12,msi[[#All],[Manual /OutSale]],"OutSale"))-(SUMIFS(MRet[[#All],[CASH]],MRet[[#All],[DATE]],$A12,MRet[[#All],[Manual/ OutSale]],"OutSale")) -> 0 | Y12: =D12-M12-N12+O12+Q12+R12-S12-T12-U12-V12-W12 -> 0 | Z12: =X12-Y12 -> 0
A13: =A12+1 -> 46303 | B13: =(SUMIFS(msi[[#All],[SP]],msi[[#All],[DATE]],$A13,msi[[#All],[Manual /OutSale]],"OutSale"))-(SUMIFS(MRet[[#All],[SP]],MRet[[#All],[DATE]],$A13,MRet[[#All],[Manual/ OutSale]],"OutSale")) -> 0 | C13: =(SUMIFS(msi[[#All],[DISC. AMOUNT]],msi[[#All],[DATE]],$A13,msi[[#All],[Manual /OutSale]],"OutSale"))-(SUMIFS(MRet[[#All],[DISC. AMOUNT]],MRet[[#All],[DATE]],$A13,MRet[[#All],[Manual/ OutSale]],"OutSale")) -> 0 | D13: =+B13-C13 -> 0 | F13: =+C13-E13 -> 0 | I13: =SUMIF(Z13,"<.01") -> 0 | J13: =SUMIF(Z13,">.01") -> 0 | M13: =(SUMIFS(msi[[#All],[CHARGE]],msi[[#All],[DATE]],$A13,msi[[#All],[Manual /OutSale]],"OutSale"))-(SUMIFS(MRet[[#All],[CHARGE]],MRet[[#All],[DATE]],$A13,MRet[[#All],[Manual/ OutSale]],"OutSale")) -> 0 | N13: =(SUMIFS(msi[[#All],[GC/ OTHERS]],msi[[#All],[DATE]],$A13,msi[[#All],[Manual /OutSale]],"OutSale"))-(SUMIFS(MRet[[#All],[GC/ OTHERS]],MRet[[#All],[DATE]],$A13,MRet[[#All],[Manual/ OutSale]],"OutSale")) -> 0 | S13: =(SUMIFS(msi[[#All],[Check]],msi[[#All],[DATE]],$A13,msi[[#All],[Manual /OutSale]],"OutSale"))-(SUMIFS(MRet[[#All],[Check]],MRet[[#All],[DATE]],$A13,MRet[[#All],[Manual/ OutSale]],"OutSale")) -> 0 | T13: =(SUMIFS(msi[[#All],[COD]],msi[[#All],[DATE]],$A13,msi[[#All],[Manual /OutSale]],"OutSale"))-(SUMIFS(MRet[[#All],[COD]],MRet[[#All],[DATE]],$A13,MRet[[#All],[Manual/ OutSale]],"OutSale")) -> 0 | U13: 0 | W13: =(SUMIFS(msi[[#All],[CWT]],msi[[#All],[DATE]],$A13,msi[[#All],[Manual /OutSale]],"OutSale"))-(SUMIFS(MRet[[#All],[CWT]],MRet[[#All],[DATE]],$A13,MRet[[#All],[Manual/ OutSale]],"OutSale")) -> 0 | X13: =(SUMIFS(msi[[#All],[CASH]],msi[[#All],[DATE]],$A13,msi[[#All],[Manual /OutSale]],"OutSale"))-(SUMIFS(MRet[[#All],[CASH]],MRet[[#All],[DATE]],$A13,MRet[[#All],[Manual/ OutSale]],"OutSale")) -> 0 | Y13: =D13-M13-N13+O13+Q13+R13-S13-T13-U13-V13-W13 -> 0 | Z13: =X13-Y13 -> 0
A14: =A13+1 -> 46304 | B14: =(SUMIFS(msi[[#All],[SP]],msi[[#All],[DATE]],$A14,msi[[#All],[Manual /OutSale]],"OutSale"))-(SUMIFS(MRet[[#All],[SP]],MRet[[#All],[DATE]],$A14,MRet[[#All],[Manual/ OutSale]],"OutSale")) -> 0 | C14: =(SUMIFS(msi[[#All],[DISC. AMOUNT]],msi[[#All],[DATE]],$A14,msi[[#All],[Manual /OutSale]],"OutSale"))-(SUMIFS(MRet[[#All],[DISC. AMOUNT]],MRet[[#All],[DATE]],$A14,MRet[[#All],[Manual/ OutSale]],"OutSale")) -> 0 | D14: =+B14-C14 -> 0 | F14: =+C14-E14 -> 0 | I14: =SUMIF(Z14,"<.01") -> 0 | J14: =SUMIF(Z14,">.01") -> 0 | M14: =(SUMIFS(msi[[#All],[CHARGE]],msi[[#All],[DATE]],$A14,msi[[#All],[Manual /OutSale]],"OutSale"))-(SUMIFS(MRet[[#All],[CHARGE]],MRet[[#All],[DATE]],$A14,MRet[[#All],[Manual/ OutSale]],"OutSale")) -> 0 | N14: =(SUMIFS(msi[[#All],[GC/ OTHERS]],msi[[#All],[DATE]],$A14,msi[[#All],[Manual /OutSale]],"OutSale"))-(SUMIFS(MRet[[#All],[GC/ OTHERS]],MRet[[#All],[DATE]],$A14,MRet[[#All],[Manual/ OutSale]],"OutSale")) -> 0 | S14: =(SUMIFS(msi[[#All],[Check]],msi[[#All],[DATE]],$A14,msi[[#All],[Manual /OutSale]],"OutSale"))-(SUMIFS(MRet[[#All],[Check]],MRet[[#All],[DATE]],$A14,MRet[[#All],[Manual/ OutSale]],"OutSale")) -> 0 | T14: =(SUMIFS(msi[[#All],[COD]],msi[[#All],[DATE]],$A14,msi[[#All],[Manual /OutSale]],"OutSale"))-(SUMIFS(MRet[[#All],[COD]],MRet[[#All],[DATE]],$A14,MRet[[#All],[Manual/ OutSale]],"OutSale")) -> 0 | U14: 0 | W14: =(SUMIFS(msi[[#All],[CWT]],msi[[#All],[DATE]],$A14,msi[[#All],[Manual /OutSale]],"OutSale"))-(SUMIFS(MRet[[#All],[CWT]],MRet[[#All],[DATE]],$A14,MRet[[#All],[Manual/ OutSale]],"OutSale")) -> 0 | X14: =(SUMIFS(msi[[#All],[CASH]],msi[[#All],[DATE]],$A14,msi[[#All],[Manual /OutSale]],"OutSale"))-(SUMIFS(MRet[[#All],[CASH]],MRet[[#All],[DATE]],$A14,MRet[[#All],[Manual/ OutSale]],"OutSale")) -> 0 | Y14: =D14-M14-N14+O14+Q14+R14-S14-T14-U14-V14-W14 -> 0 | Z14: =X14-Y14 -> 0
A15: =A14+1 -> 46305 | B15: =(SUMIFS(msi[[#All],[SP]],msi[[#All],[DATE]],$A15,msi[[#All],[Manual /OutSale]],"OutSale"))-(SUMIFS(MRet[[#All],[SP]],MRet[[#All],[DATE]],$A15,MRet[[#All],[Manual/ OutSale]],"OutSale")) -> 0 | C15: =(SUMIFS(msi[[#All],[DISC. AMOUNT]],msi[[#All],[DATE]],$A15,msi[[#All],[Manual /OutSale]],"OutSale"))-(SUMIFS(MRet[[#All],[DISC. AMOUNT]],MRet[[#All],[DATE]],$A15,MRet[[#All],[Manual/ OutSale]],"OutSale")) -> 0 | D15: =+B15-C15 -> 0 | F15: =+C15-E15 -> 0 | I15: =SUMIF(Z15,"<.01") -> 0 | J15: =SUMIF(Z15,">.01") -> 0 | M15: =(SUMIFS(msi[[#All],[CHARGE]],msi[[#All],[DATE]],$A15,msi[[#All],[Manual /OutSale]],"OutSale"))-(SUMIFS(MRet[[#All],[CHARGE]],MRet[[#All],[DATE]],$A15,MRet[[#All],[Manual/ OutSale]],"OutSale")) -> 0 | N15: =(SUMIFS(msi[[#All],[GC/ OTHERS]],msi[[#All],[DATE]],$A15,msi[[#All],[Manual /OutSale]],"OutSale"))-(SUMIFS(MRet[[#All],[GC/ OTHERS]],MRet[[#All],[DATE]],$A15,MRet[[#All],[Manual/ OutSale]],"OutSale")) -> 0 | S15: =(SUMIFS(msi[[#All],[Check]],msi[[#All],[DATE]],$A15,msi[[#All],[Manual /OutSale]],"OutSale"))-(SUMIFS(MRet[[#All],[Check]],MRet[[#All],[DATE]],$A15,MRet[[#All],[Manual/ OutSale]],"OutSale")) -> 0 | T15: =(SUMIFS(msi[[#All],[COD]],msi[[#All],[DATE]],$A15,msi[[#All],[Manual /OutSale]],"OutSale"))-(SUMIFS(MRet[[#All],[COD]],MRet[[#All],[DATE]],$A15,MRet[[#All],[Manual/ OutSale]],"OutSale")) -> 0 | U15: 0 | W15: =(SUMIFS(msi[[#All],[CWT]],msi[[#All],[DATE]],$A15,msi[[#All],[Manual /OutSale]],"OutSale"))-(SUMIFS(MRet[[#All],[CWT]],MRet[[#All],[DATE]],$A15,MRet[[#All],[Manual/ OutSale]],"OutSale")) -> 0 | X15: =(SUMIFS(msi[[#All],[CASH]],msi[[#All],[DATE]],$A15,msi[[#All],[Manual /OutSale]],"OutSale"))-(SUMIFS(MRet[[#All],[CASH]],MRet[[#All],[DATE]],$A15,MRet[[#All],[Manual/ OutSale]],"OutSale")) -> 0 | Y15: =D15-M15-N15+O15+Q15+R15-S15-T15-U15-V15-W15 -> 0 | Z15: =X15-Y15 -> 0
A16: =A15+1 -> 46306 | B16: =(SUMIFS(msi[[#All],[SP]],msi[[#All],[DATE]],$A16,msi[[#All],[Manual /OutSale]],"OutSale"))-(SUMIFS(MRet[[#All],[SP]],MRet[[#All],[DATE]],$A16,MRet[[#All],[Manual/ OutSale]],"OutSale")) -> 0 | C16: =(SUMIFS(msi[[#All],[DISC. AMOUNT]],msi[[#All],[DATE]],$A16,msi[[#All],[Manual /OutSale]],"OutSale"))-(SUMIFS(MRet[[#All],[DISC. AMOUNT]],MRet[[#All],[DATE]],$A16,MRet[[#All],[Manual/ OutSale]],"OutSale")) -> 0 | D16: =+B16-C16 -> 0 | F16: =+C16-E16 -> 0 | I16: =SUMIF(Z16,"<.01") -> 0 | J16: =SUMIF(Z16,">.01") -> 0 | M16: =(SUMIFS(msi[[#All],[CHARGE]],msi[[#All],[DATE]],$A16,msi[[#All],[Manual /OutSale]],"OutSale"))-(SUMIFS(MRet[[#All],[CHARGE]],MRet[[#All],[DATE]],$A16,MRet[[#All],[Manual/ OutSale]],"OutSale")) -> 0 | N16: =(SUMIFS(msi[[#All],[GC/ OTHERS]],msi[[#All],[DATE]],$A16,msi[[#All],[Manual /OutSale]],"OutSale"))-(SUMIFS(MRet[[#All],[GC/ OTHERS]],MRet[[#All],[DATE]],$A16,MRet[[#All],[Manual/ OutSale]],"OutSale")) -> 0 | S16: =(SUMIFS(msi[[#All],[Check]],msi[[#All],[DATE]],$A16,msi[[#All],[Manual /OutSale]],"OutSale"))-(SUMIFS(MRet[[#All],[Check]],MRet[[#All],[DATE]],$A16,MRet[[#All],[Manual/ OutSale]],"OutSale")) -> 0 | T16: =(SUMIFS(msi[[#All],[COD]],msi[[#All],[DATE]],$A16,msi[[#All],[Manual /OutSale]],"OutSale"))-(SUMIFS(MRet[[#All],[COD]],MRet[[#All],[DATE]],$A16,MRet[[#All],[Manual/ OutSale]],"OutSale")) -> 0 | U16: 0 | W16: =(SUMIFS(msi[[#All],[CWT]],msi[[#All],[DATE]],$A16,msi[[#All],[Manual /OutSale]],"OutSale"))-(SUMIFS(MRet[[#All],[CWT]],MRet[[#All],[DATE]],$A16,MRet[[#All],[Manual/ OutSale]],"OutSale")) -> 0 | X16: =(SUMIFS(msi[[#All],[CASH]],msi[[#All],[DATE]],$A16,msi[[#All],[Manual /OutSale]],"OutSale"))-(SUMIFS(MRet[[#All],[CASH]],MRet[[#All],[DATE]],$A16,MRet[[#All],[Manual/ OutSale]],"OutSale")) -> 0 | Y16: =D16-M16-N16+O16+Q16+R16-S16-T16-U16-V16-W16 -> 0 | Z16: =X16-Y16 -> 0
A17: =A16+1 -> 46307 | B17: =(SUMIFS(msi[[#All],[SP]],msi[[#All],[DATE]],$A17,msi[[#All],[Manual /OutSale]],"OutSale"))-(SUMIFS(MRet[[#All],[SP]],MRet[[#All],[DATE]],$A17,MRet[[#All],[Manual/ OutSale]],"OutSale")) -> 0 | C17: =(SUMIFS(msi[[#All],[DISC. AMOUNT]],msi[[#All],[DATE]],$A17,msi[[#All],[Manual /OutSale]],"OutSale"))-(SUMIFS(MRet[[#All],[DISC. AMOUNT]],MRet[[#All],[DATE]],$A17,MRet[[#All],[Manual/ OutSale]],"OutSale")) -> 0 | D17: =+B17-C17 -> 0 | F17: =+C17-E17 -> 0 | I17: =SUMIF(Z17,"<.01") -> 0 | J17: =SUMIF(Z17,">.01") -> 0 | M17: =(SUMIFS(msi[[#All],[CHARGE]],msi[[#All],[DATE]],$A17,msi[[#All],[Manual /OutSale]],"OutSale"))-(SUMIFS(MRet[[#All],[CHARGE]],MRet[[#All],[DATE]],$A17,MRet[[#All],[Manual/ OutSale]],"OutSale")) -> 0 | N17: =(SUMIFS(msi[[#All],[GC/ OTHERS]],msi[[#All],[DATE]],$A17,msi[[#All],[Manual /OutSale]],"OutSale"))-(SUMIFS(MRet[[#All],[GC/ OTHERS]],MRet[[#All],[DATE]],$A17,MRet[[#All],[Manual/ OutSale]],"OutSale")) -> 0 | S17: =(SUMIFS(msi[[#All],[Check]],msi[[#All],[DATE]],$A17,msi[[#All],[Manual /OutSale]],"OutSale"))-(SUMIFS(MRet[[#All],[Check]],MRet[[#All],[DATE]],$A17,MRet[[#All],[Manual/ OutSale]],"OutSale")) -> 0 | T17: =(SUMIFS(msi[[#All],[COD]],msi[[#All],[DATE]],$A17,msi[[#All],[Manual /OutSale]],"OutSale"))-(SUMIFS(MRet[[#All],[COD]],MRet[[#All],[DATE]],$A17,MRet[[#All],[Manual/ OutSale]],"OutSale")) -> 0 | U17: 0 | W17: =(SUMIFS(msi[[#All],[CWT]],msi[[#All],[DATE]],$A17,msi[[#All],[Manual /OutSale]],"OutSale"))-(SUMIFS(MRet[[#All],[CWT]],MRet[[#All],[DATE]],$A17,MRet[[#All],[Manual/ OutSale]],"OutSale")) -> 0 | X17: =(SUMIFS(msi[[#All],[CASH]],msi[[#All],[DATE]],$A17,msi[[#All],[Manual /OutSale]],"OutSale"))-(SUMIFS(MRet[[#All],[CASH]],MRet[[#All],[DATE]],$A17,MRet[[#All],[Manual/ OutSale]],"OutSale")) -> 0 | Y17: =D17-M17-N17+O17+Q17+R17-S17-T17-U17-V17-W17 -> 0 | Z17: =X17-Y17 -> 0
A18: =A17+1 -> 46308 | B18: =(SUMIFS(msi[[#All],[SP]],msi[[#All],[DATE]],$A18,msi[[#All],[Manual /OutSale]],"OutSale"))-(SUMIFS(MRet[[#All],[SP]],MRet[[#All],[DATE]],$A18,MRet[[#All],[Manual/ OutSale]],"OutSale")) -> 0 | C18: =(SUMIFS(msi[[#All],[DISC. AMOUNT]],msi[[#All],[DATE]],$A18,msi[[#All],[Manual /OutSale]],"OutSale"))-(SUMIFS(MRet[[#All],[DISC. AMOUNT]],MRet[[#All],[DATE]],$A18,MRet[[#All],[Manual/ OutSale]],"OutSale")) -> 0 | D18: =+B18-C18 -> 0 | F18: =+C18-E18 -> 0 | I18: =SUMIF(Z18,"<.01") -> 0 | J18: =SUMIF(Z18,">.01") -> 0 | M18: =(SUMIFS(msi[[#All],[CHARGE]],msi[[#All],[DATE]],$A18,msi[[#All],[Manual /OutSale]],"OutSale"))-(SUMIFS(MRet[[#All],[CHARGE]],MRet[[#All],[DATE]],$A18,MRet[[#All],[Manual/ OutSale]],"OutSale")) -> 0 | N18: =(SUMIFS(msi[[#All],[GC/ OTHERS]],msi[[#All],[DATE]],$A18,msi[[#All],[Manual /OutSale]],"OutSale"))-(SUMIFS(MRet[[#All],[GC/ OTHERS]],MRet[[#All],[DATE]],$A18,MRet[[#All],[Manual/ OutSale]],"OutSale")) -> 0 | S18: =(SUMIFS(msi[[#All],[Check]],msi[[#All],[DATE]],$A18,msi[[#All],[Manual /OutSale]],"OutSale"))-(SUMIFS(MRet[[#All],[Check]],MRet[[#All],[DATE]],$A18,MRet[[#All],[Manual/ OutSale]],"OutSale")) -> 0 | T18: =(SUMIFS(msi[[#All],[COD]],msi[[#All],[DATE]],$A18,msi[[#All],[Manual /OutSale]],"OutSale"))-(SUMIFS(MRet[[#All],[COD]],MRet[[#All],[DATE]],$A18,MRet[[#All],[Manual/ OutSale]],"OutSale")) -> 0 | U18: 0 | W18: =(SUMIFS(msi[[#All],[CWT]],msi[[#All],[DATE]],$A18,msi[[#All],[Manual /OutSale]],"OutSale"))-(SUMIFS(MRet[[#All],[CWT]],MRet[[#All],[DATE]],$A18,MRet[[#All],[Manual/ OutSale]],"OutSale")) -> 0 | X18: =(SUMIFS(msi[[#All],[CASH]],msi[[#All],[DATE]],$A18,msi[[#All],[Manual /OutSale]],"OutSale"))-(SUMIFS(MRet[[#All],[CASH]],MRet[[#All],[DATE]],$A18,MRet[[#All],[Manual/ OutSale]],"OutSale")) -> 0 | Y18: =D18-M18-N18+O18+Q18+R18-S18-T18-U18-V18-W18 -> 0 | Z18: =X18-Y18 -> 0
... A20: =A19+1 -> 46310 | B20: =(SUMIFS(msi[[#All],[SP]],msi[[#All],[DATE]],$A20,msi[[#All],[Manual /OutSale]],"OutSale"))-(SUMIFS(MRet[[#All],[SP]],MRet[[#All],[DATE]],$A20,MRet[[#All],[Manual/ OutSale]],"OutSale")) -> 0 | C20: =(SUMIFS(msi[[#All],[DISC. AMOUNT]],msi[[#All],[DATE]],$A20,msi[[#All],[Manual /OutSale]],"OutSale"))-(SUMIFS(MRet[[#All],[DISC. AMOUNT]],MRet[[#All],[DATE]],$A20,MRet[[#All],[Manual/ OutSale]],"OutSale")) -> 0 | D20: =+B20-C20 -> 0 | F20: =+C20-E20 -> 0 | I20: =SUMIF(Z20,"<.01") -> 0 | J20: =SUMIF(Z20,">.01") -> 0 | M20: =(SUMIFS(msi[[#All],[CHARGE]],msi[[#All],[DATE]],$A20,msi[[#All],[Manual /OutSale]],"OutSale"))-(SUMIFS(MRet[[#All],[CHARGE]],MRet[[#All],[DATE]],$A20,MRet[[#All],[Manual/ OutSale]],"OutSale")) -> 0 | N20: =(SUMIFS(msi[[#All],[GC/ OTHERS]],msi[[#All],[DATE]],$A20,msi[[#All],[Manual /OutSale]],"OutSale"))-(SUMIFS(MRet[[#All],[GC/ OTHERS]],MRet[[#All],[DATE]],$A20,MRet[[#All],[Manual/ OutSale]],"OutSale")) -> 0 | S20: =(SUMIFS(msi[[#All],[Check]],msi[[#All],[DATE]],$A20,msi[[#All],[Manual /OutSale]],"OutSale"))-(SUMIFS(MRet[[#All],[Check]],MRet[[#All],[DATE]],$A20,MRet[[#All],[Manual/ OutSale]],"OutSale")) -> 0 | T20: =(SUMIFS(msi[[#All],[COD]],msi[[#All],[DATE]],$A20,msi[[#All],[Manual /OutSale]],"OutSale"))-(SUMIFS(MRet[[#All],[COD]],MRet[[#All],[DATE]],$A20,MRet[[#All],[Manual/ OutSale]],"OutSale")) -> 0 | U20: 0 | W20: =(SUMIFS(msi[[#All],[CWT]],msi[[#All],[DATE]],$A20,msi[[#All],[Manual /OutSale]],"OutSale"))-(SUMIFS(MRet[[#All],[CWT]],MRet[[#All],[DATE]],$A20,MRet[[#All],[Manual/ OutSale]],"OutSale")) -> 0 | X20: =(SUMIFS(msi[[#All],[CASH]],msi[[#All],[DATE]],$A20,msi[[#All],[Manual /OutSale]],"OutSale"))-(SUMIFS(MRet[[#All],[CASH]],MRet[[#All],[DATE]],$A20,MRet[[#All],[Manual/ OutSale]],"OutSale")) -> 0 | Y20: =D20-M20-N20+O20+Q20+R20-S20-T20-U20-V20-W20 -> 0 | Z20: =X20-Y20 -> 0
B21: =SUM(B6:B20) -> 0 | C21: =SUM(C6:C20) -> 0 | D21: =SUM(D6:D20) -> 0 | E21: =SUM(E6:E20) -> 0 | F21: =SUM(F6:F20) -> 0 | G21: =SUM(G6:G20) -> 0 | H21: =SUM(H6:H20) -> 0 | I21: =SUM(I6:I20) -> 0 | ... K21: =SUM(K6:K20) -> 0 | M21: =SUM(M6:M20) -> 0 | N21: =SUM(N6:N20) -> 0 | O21: =SUM(O6:O20) -> 0 | P21: =SUM(P6:P20) -> 0 | Q21: =SUM(Q6:Q20) -> 0 | R21: =SUM(R6:R20) -> 0 | S21: =SUM(S6:S20) -> 0 | T21: =SUM(T6:T20) -> 0 | ... Z21: =SUM(Z6:Z20) -> 0
A23: =A20+1 -> 46311 | B23: =(SUMIFS(msi[[#All],[SP]],msi[[#All],[DATE]],$A23,msi[[#All],[Manual /OutSale]],"OutSale"))-(SUMIFS(MRet[[#All],[SP]],MRet[[#All],[DATE]],$A23,MRet[[#All],[Manual/ OutSale]],"OutSale")) -> 0 | C23: =(SUMIFS(msi[[#All],[DISC. AMOUNT]],msi[[#All],[DATE]],$A23,msi[[#All],[Manual /OutSale]],"OutSale"))-(SUMIFS(MRet[[#All],[DISC. AMOUNT]],MRet[[#All],[DATE]],$A23,MRet[[#All],[Manual/ OutSale]],"OutSale")) -> 0 | D23: =+B23-C23 -> 0 | F23: =+C23-E23 -> 0 | I23: =SUMIF(Z23,"<.01") -> 0 | J23: =SUMIF(Z23,">.01") -> 0 | M23: =(SUMIFS(msi[[#All],[CHARGE]],msi[[#All],[DATE]],$A23,msi[[#All],[Manual /OutSale]],"OutSale"))-(SUMIFS(MRet[[#All],[CHARGE]],MRet[[#All],[DATE]],$A23,MRet[[#All],[Manual/ OutSale]],"OutSale")) -> 0 | N23: =(SUMIFS(msi[[#All],[GC/ OTHERS]],msi[[#All],[DATE]],$A23,msi[[#All],[Manual /OutSale]],"OutSale"))-(SUMIFS(MRet[[#All],[GC/ OTHERS]],MRet[[#All],[DATE]],$A23,MRet[[#All],[Manual/ OutSale]],"OutSale")) -> 0 | S23: =(SUMIFS(msi[[#All],[Check]],msi[[#All],[DATE]],$A23,msi[[#All],[Manual /OutSale]],"OutSale"))-(SUMIFS(MRet[[#All],[Check]],MRet[[#All],[DATE]],$A23,MRet[[#All],[Manual/ OutSale]],"OutSale")) -> 0 | T23: =(SUMIFS(msi[[#All],[COD]],msi[[#All],[DATE]],$A23,msi[[#All],[Manual /OutSale]],"OutSale"))-(SUMIFS(MRet[[#All],[COD]],MRet[[#All],[DATE]],$A23,MRet[[#All],[Manual/ OutSale]],"OutSale")) -> 0 | U23: 0 | W23: =(SUMIFS(msi[[#All],[CWT]],msi[[#All],[DATE]],$A23,msi[[#All],[Manual /OutSale]],"OutSale"))-(SUMIFS(MRet[[#All],[CWT]],MRet[[#All],[DATE]],$A23,MRet[[#All],[Manual/ OutSale]],"OutSale")) -> 0 | X23: =(SUMIFS(msi[[#All],[CASH]],msi[[#All],[DATE]],$A23,msi[[#All],[Manual /OutSale]],"OutSale"))-(SUMIFS(MRet[[#All],[CASH]],MRet[[#All],[DATE]],$A23,MRet[[#All],[Manual/ OutSale]],"OutSale")) -> 0 | Y23: =D23-M23-N23+O23+Q23+R23-S23-T23-U23-V23-W23 -> 0 | Z23: =X23-Y23 -> 0
A24: =A23+1 -> 46312 | B24: =(SUMIFS(msi[[#All],[SP]],msi[[#All],[DATE]],$A24,msi[[#All],[Manual /OutSale]],"OutSale"))-(SUMIFS(MRet[[#All],[SP]],MRet[[#All],[DATE]],$A24,MRet[[#All],[Manual/ OutSale]],"OutSale")) -> 0 | C24: =(SUMIFS(msi[[#All],[DISC. AMOUNT]],msi[[#All],[DATE]],$A24,msi[[#All],[Manual /OutSale]],"OutSale"))-(SUMIFS(MRet[[#All],[DISC. AMOUNT]],MRet[[#All],[DATE]],$A24,MRet[[#All],[Manual/ OutSale]],"OutSale")) -> 0 | D24: =+B24-C24 -> 0 | F24: =+C24-E24 -> 0 | I24: =SUMIF(Z24,"<.01") -> 0 | J24: =SUMIF(Z24,">.01") -> 0 | M24: =(SUMIFS(msi[[#All],[CHARGE]],msi[[#All],[DATE]],$A24,msi[[#All],[Manual /OutSale]],"OutSale"))-(SUMIFS(MRet[[#All],[CHARGE]],MRet[[#All],[DATE]],$A24,MRet[[#All],[Manual/ OutSale]],"OutSale")) -> 0 | N24: =(SUMIFS(msi[[#All],[GC/ OTHERS]],msi[[#All],[DATE]],$A24,msi[[#All],[Manual /OutSale]],"OutSale"))-(SUMIFS(MRet[[#All],[GC/ OTHERS]],MRet[[#All],[DATE]],$A24,MRet[[#All],[Manual/ OutSale]],"OutSale")) -> 0 | S24: =(SUMIFS(msi[[#All],[Check]],msi[[#All],[DATE]],$A24,msi[[#All],[Manual /OutSale]],"OutSale"))-(SUMIFS(MRet[[#All],[Check]],MRet[[#All],[DATE]],$A24,MRet[[#All],[Manual/ OutSale]],"OutSale")) -> 0 | T24: =(SUMIFS(msi[[#All],[COD]],msi[[#All],[DATE]],$A24,msi[[#All],[Manual /OutSale]],"OutSale"))-(SUMIFS(MRet[[#All],[COD]],MRet[[#All],[DATE]],$A24,MRet[[#All],[Manual/ OutSale]],"OutSale")) -> 0 | U24: 0 | W24: =(SUMIFS(msi[[#All],[CWT]],msi[[#All],[DATE]],$A24,msi[[#All],[Manual /OutSale]],"OutSale"))-(SUMIFS(MRet[[#All],[CWT]],MRet[[#All],[DATE]],$A24,MRet[[#All],[Manual/ OutSale]],"OutSale")) -> 0 | X24: =(SUMIFS(msi[[#All],[CASH]],msi[[#All],[DATE]],$A24,msi[[#All],[Manual /OutSale]],"OutSale"))-(SUMIFS(MRet[[#All],[CASH]],MRet[[#All],[DATE]],$A24,MRet[[#All],[Manual/ OutSale]],"OutSale")) -> 0 | Y24: =D24-M24-N24+O24+Q24+R24-S24-T24-U24-V24-W24 -> 0 | Z24: =X24-Y24 -> 0
A25: =A24+1 -> 46313 | B25: =(SUMIFS(msi[[#All],[SP]],msi[[#All],[DATE]],$A25,msi[[#All],[Manual /OutSale]],"OutSale"))-(SUMIFS(MRet[[#All],[SP]],MRet[[#All],[DATE]],$A25,MRet[[#All],[Manual/ OutSale]],"OutSale")) -> 0 | C25: =(SUMIFS(msi[[#All],[DISC. AMOUNT]],msi[[#All],[DATE]],$A25,msi[[#All],[Manual /OutSale]],"OutSale"))-(SUMIFS(MRet[[#All],[DISC. AMOUNT]],MRet[[#All],[DATE]],$A25,MRet[[#All],[Manual/ OutSale]],"OutSale")) -> 0 | D25: =+B25-C25 -> 0 | F25: =+C25-E25 -> 0 | I25: =SUMIF(Z25,"<.01") -> 0 | J25: =SUMIF(Z25,">.01") -> 0 | M25: =(SUMIFS(msi[[#All],[CHARGE]],msi[[#All],[DATE]],$A25,msi[[#All],[Manual /OutSale]],"OutSale"))-(SUMIFS(MRet[[#All],[CHARGE]],MRet[[#All],[DATE]],$A25,MRet[[#All],[Manual/ OutSale]],"OutSale")) -> 0 | N25: =(SUMIFS(msi[[#All],[GC/ OTHERS]],msi[[#All],[DATE]],$A25,msi[[#All],[Manual /OutSale]],"OutSale"))-(SUMIFS(MRet[[#All],[GC/ OTHERS]],MRet[[#All],[DATE]],$A25,MRet[[#All],[Manual/ OutSale]],"OutSale")) -> 0 | S25: =(SUMIFS(msi[[#All],[Check]],msi[[#All],[DATE]],$A25,msi[[#All],[Manual /OutSale]],"OutSale"))-(SUMIFS(MRet[[#All],[Check]],MRet[[#All],[DATE]],$A25,MRet[[#All],[Manual/ OutSale]],"OutSale")) -> 0 | T25: =(SUMIFS(msi[[#All],[COD]],msi[[#All],[DATE]],$A25,msi[[#All],[Manual /OutSale]],"OutSale"))-(SUMIFS(MRet[[#All],[COD]],MRet[[#All],[DATE]],$A25,MRet[[#All],[Manual/ OutSale]],"OutSale")) -> 0 | U25: 0 | W25: =(SUMIFS(msi[[#All],[CWT]],msi[[#All],[DATE]],$A25,msi[[#All],[Manual /OutSale]],"OutSale"))-(SUMIFS(MRet[[#All],[CWT]],MRet[[#All],[DATE]],$A25,MRet[[#All],[Manual/ OutSale]],"OutSale")) -> 0 | X25: =(SUMIFS(msi[[#All],[CASH]],msi[[#All],[DATE]],$A25,msi[[#All],[Manual /OutSale]],"OutSale"))-(SUMIFS(MRet[[#All],[CASH]],MRet[[#All],[DATE]],$A25,MRet[[#All],[Manual/ OutSale]],"OutSale")) -> 0 | Y25: =D25-M25-N25+O25+Q25+R25-S25-T25-U25-V25-W25 -> 0 | Z25: =X25-Y25 -> 0
A26: =A25+1 -> 46314 | B26: =(SUMIFS(msi[[#All],[SP]],msi[[#All],[DATE]],$A26,msi[[#All],[Manual /OutSale]],"OutSale"))-(SUMIFS(MRet[[#All],[SP]],MRet[[#All],[DATE]],$A26,MRet[[#All],[Manual/ OutSale]],"OutSale")) -> 0 | C26: =(SUMIFS(msi[[#All],[DISC. AMOUNT]],msi[[#All],[DATE]],$A26,msi[[#All],[Manual /OutSale]],"OutSale"))-(SUMIFS(MRet[[#All],[DISC. AMOUNT]],MRet[[#All],[DATE]],$A26,MRet[[#All],[Manual/ OutSale]],"OutSale")) -> 0 | D26: =+B26-C26 -> 0 | F26: =+C26-E26 -> 0 | I26: =SUMIF(Z26,"<.01") -> 0 | J26: =SUMIF(Z26,">.01") -> 0 | M26: =(SUMIFS(msi[[#All],[CHARGE]],msi[[#All],[DATE]],$A26,msi[[#All],[Manual /OutSale]],"OutSale"))-(SUMIFS(MRet[[#All],[CHARGE]],MRet[[#All],[DATE]],$A26,MRet[[#All],[Manual/ OutSale]],"OutSale")) -> 0 | N26: =(SUMIFS(msi[[#All],[GC/ OTHERS]],msi[[#All],[DATE]],$A26,msi[[#All],[Manual /OutSale]],"OutSale"))-(SUMIFS(MRet[[#All],[GC/ OTHERS]],MRet[[#All],[DATE]],$A26,MRet[[#All],[Manual/ OutSale]],"OutSale")) -> 0 | S26: =(SUMIFS(msi[[#All],[Check]],msi[[#All],[DATE]],$A26,msi[[#All],[Manual /OutSale]],"OutSale"))-(SUMIFS(MRet[[#All],[Check]],MRet[[#All],[DATE]],$A26,MRet[[#All],[Manual/ OutSale]],"OutSale")) -> 0 | T26: =(SUMIFS(msi[[#All],[COD]],msi[[#All],[DATE]],$A26,msi[[#All],[Manual /OutSale]],"OutSale"))-(SUMIFS(MRet[[#All],[COD]],MRet[[#All],[DATE]],$A26,MRet[[#All],[Manual/ OutSale]],"OutSale")) -> 0 | U26: 0 | W26: =(SUMIFS(msi[[#All],[CWT]],msi[[#All],[DATE]],$A26,msi[[#All],[Manual /OutSale]],"OutSale"))-(SUMIFS(MRet[[#All],[CWT]],MRet[[#All],[DATE]],$A26,MRet[[#All],[Manual/ OutSale]],"OutSale")) -> 0 | X26: =(SUMIFS(msi[[#All],[CASH]],msi[[#All],[DATE]],$A26,msi[[#All],[Manual /OutSale]],"OutSale"))-(SUMIFS(MRet[[#All],[CASH]],MRet[[#All],[DATE]],$A26,MRet[[#All],[Manual/ OutSale]],"OutSale")) -> 0 | Y26: =D26-M26-N26+O26+Q26+R26-S26-T26-U26-V26-W26 -> 0 | Z26: =X26-Y26 -> 0
A27: =A26+1 -> 46315 | B27: =(SUMIFS(msi[[#All],[SP]],msi[[#All],[DATE]],$A27,msi[[#All],[Manual /OutSale]],"OutSale"))-(SUMIFS(MRet[[#All],[SP]],MRet[[#All],[DATE]],$A27,MRet[[#All],[Manual/ OutSale]],"OutSale")) -> 0 | C27: =(SUMIFS(msi[[#All],[DISC. AMOUNT]],msi[[#All],[DATE]],$A27,msi[[#All],[Manual /OutSale]],"OutSale"))-(SUMIFS(MRet[[#All],[DISC. AMOUNT]],MRet[[#All],[DATE]],$A27,MRet[[#All],[Manual/ OutSale]],"OutSale")) -> 0 | D27: =+B27-C27 -> 0 | F27: =+C27-E27 -> 0 | I27: =SUMIF(Z27,"<.01") -> 0 | J27: =SUMIF(Z27,">.01") -> 0 | M27: =(SUMIFS(msi[[#All],[CHARGE]],msi[[#All],[DATE]],$A27,msi[[#All],[Manual /OutSale]],"OutSale"))-(SUMIFS(MRet[[#All],[CHARGE]],MRet[[#All],[DATE]],$A27,MRet[[#All],[Manual/ OutSale]],"OutSale")) -> 0 | N27: =(SUMIFS(msi[[#All],[GC/ OTHERS]],msi[[#All],[DATE]],$A27,msi[[#All],[Manual /OutSale]],"OutSale"))-(SUMIFS(MRet[[#All],[GC/ OTHERS]],MRet[[#All],[DATE]],$A27,MRet[[#All],[Manual/ OutSale]],"OutSale")) -> 0 | S27: =(SUMIFS(msi[[#All],[Check]],msi[[#All],[DATE]],$A27,msi[[#All],[Manual /OutSale]],"OutSale"))-(SUMIFS(MRet[[#All],[Check]],MRet[[#All],[DATE]],$A27,MRet[[#All],[Manual/ OutSale]],"OutSale")) -> 0 | T27: =(SUMIFS(msi[[#All],[COD]],msi[[#All],[DATE]],$A27,msi[[#All],[Manual /OutSale]],"OutSale"))-(SUMIFS(MRet[[#All],[COD]],MRet[[#All],[DATE]],$A27,MRet[[#All],[Manual/ OutSale]],"OutSale")) -> 0 | U27: 0 | W27: =(SUMIFS(msi[[#All],[CWT]],msi[[#All],[DATE]],$A27,msi[[#All],[Manual /OutSale]],"OutSale"))-(SUMIFS(MRet[[#All],[CWT]],MRet[[#All],[DATE]],$A27,MRet[[#All],[Manual/ OutSale]],"OutSale")) -> 0 | X27: =(SUMIFS(msi[[#All],[CASH]],msi[[#All],[DATE]],$A27,msi[[#All],[Manual /OutSale]],"OutSale"))-(SUMIFS(MRet[[#All],[CASH]],MRet[[#All],[DATE]],$A27,MRet[[#All],[Manual/ OutSale]],"OutSale")) -> 0 | Y27: =D27-M27-N27+O27+Q27+R27-S27-T27-U27-V27-W27 -> 0 | Z27: =X27-Y27 -> 0
A28: =A27+1 -> 46316 | B28: =(SUMIFS(msi[[#All],[SP]],msi[[#All],[DATE]],$A28,msi[[#All],[Manual /OutSale]],"OutSale"))-(SUMIFS(MRet[[#All],[SP]],MRet[[#All],[DATE]],$A28,MRet[[#All],[Manual/ OutSale]],"OutSale")) -> 0 | C28: =(SUMIFS(msi[[#All],[DISC. AMOUNT]],msi[[#All],[DATE]],$A28,msi[[#All],[Manual /OutSale]],"OutSale"))-(SUMIFS(MRet[[#All],[DISC. AMOUNT]],MRet[[#All],[DATE]],$A28,MRet[[#All],[Manual/ OutSale]],"OutSale")) -> 0 | D28: =+B28-C28 -> 0 | F28: =+C28-E28 -> 0 | I28: =SUMIF(Z28,"<.01") -> 0 | J28: =SUMIF(Z28,">.01") -> 0 | M28: =(SUMIFS(msi[[#All],[CHARGE]],msi[[#All],[DATE]],$A28,msi[[#All],[Manual /OutSale]],"OutSale"))-(SUMIFS(MRet[[#All],[CHARGE]],MRet[[#All],[DATE]],$A28,MRet[[#All],[Manual/ OutSale]],"OutSale")) -> 0 | N28: =(SUMIFS(msi[[#All],[GC/ OTHERS]],msi[[#All],[DATE]],$A28,msi[[#All],[Manual /OutSale]],"OutSale"))-(SUMIFS(MRet[[#All],[GC/ OTHERS]],MRet[[#All],[DATE]],$A28,MRet[[#All],[Manual/ OutSale]],"OutSale")) -> 0 | S28: =(SUMIFS(msi[[#All],[Check]],msi[[#All],[DATE]],$A28,msi[[#All],[Manual /OutSale]],"OutSale"))-(SUMIFS(MRet[[#All],[Check]],MRet[[#All],[DATE]],$A28,MRet[[#All],[Manual/ OutSale]],"OutSale")) -> 0 | T28: =(SUMIFS(msi[[#All],[COD]],msi[[#All],[DATE]],$A28,msi[[#All],[Manual /OutSale]],"OutSale"))-(SUMIFS(MRet[[#All],[COD]],MRet[[#All],[DATE]],$A28,MRet[[#All],[Manual/ OutSale]],"OutSale")) -> 0 | U28: 0 | W28: =(SUMIFS(msi[[#All],[CWT]],msi[[#All],[DATE]],$A28,msi[[#All],[Manual /OutSale]],"OutSale"))-(SUMIFS(MRet[[#All],[CWT]],MRet[[#All],[DATE]],$A28,MRet[[#All],[Manual/ OutSale]],"OutSale")) -> 0 | X28: =(SUMIFS(msi[[#All],[CASH]],msi[[#All],[DATE]],$A28,msi[[#All],[Manual /OutSale]],"OutSale"))-(SUMIFS(MRet[[#All],[CASH]],MRet[[#All],[DATE]],$A28,MRet[[#All],[Manual/ OutSale]],"OutSale")) -> 0 | Y28: =D28-M28-N28+O28+Q28+R28-S28-T28-U28-V28-W28 -> 0 | Z28: =X28-Y28 -> 0
A29: =A28+1 -> 46317 | B29: =(SUMIFS(msi[[#All],[SP]],msi[[#All],[DATE]],$A29,msi[[#All],[Manual /OutSale]],"OutSale"))-(SUMIFS(MRet[[#All],[SP]],MRet[[#All],[DATE]],$A29,MRet[[#All],[Manual/ OutSale]],"OutSale")) -> 0 | C29: =(SUMIFS(msi[[#All],[DISC. AMOUNT]],msi[[#All],[DATE]],$A29,msi[[#All],[Manual /OutSale]],"OutSale"))-(SUMIFS(MRet[[#All],[DISC. AMOUNT]],MRet[[#All],[DATE]],$A29,MRet[[#All],[Manual/ OutSale]],"OutSale")) -> 0 | D29: =+B29-C29 -> 0 | F29: =+C29-E29 -> 0 | I29: =SUMIF(Z29,"<.01") -> 0 | J29: =SUMIF(Z29,">.01") -> 0 | M29: =(SUMIFS(msi[[#All],[CHARGE]],msi[[#All],[DATE]],$A29,msi[[#All],[Manual /OutSale]],"OutSale"))-(SUMIFS(MRet[[#All],[CHARGE]],MRet[[#All],[DATE]],$A29,MRet[[#All],[Manual/ OutSale]],"OutSale")) -> 0 | N29: =(SUMIFS(msi[[#All],[GC/ OTHERS]],msi[[#All],[DATE]],$A29,msi[[#All],[Manual /OutSale]],"OutSale"))-(SUMIFS(MRet[[#All],[GC/ OTHERS]],MRet[[#All],[DATE]],$A29,MRet[[#All],[Manual/ OutSale]],"OutSale")) -> 0 | S29: =(SUMIFS(msi[[#All],[Check]],msi[[#All],[DATE]],$A29,msi[[#All],[Manual /OutSale]],"OutSale"))-(SUMIFS(MRet[[#All],[Check]],MRet[[#All],[DATE]],$A29,MRet[[#All],[Manual/ OutSale]],"OutSale")) -> 0 | T29: =(SUMIFS(msi[[#All],[COD]],msi[[#All],[DATE]],$A29,msi[[#All],[Manual /OutSale]],"OutSale"))-(SUMIFS(MRet[[#All],[COD]],MRet[[#All],[DATE]],$A29,MRet[[#All],[Manual/ OutSale]],"OutSale")) -> 0 | U29: 0 | W29: =(SUMIFS(msi[[#All],[CWT]],msi[[#All],[DATE]],$A29,msi[[#All],[Manual /OutSale]],"OutSale"))-(SUMIFS(MRet[[#All],[CWT]],MRet[[#All],[DATE]],$A29,MRet[[#All],[Manual/ OutSale]],"OutSale")) -> 0 | X29: =(SUMIFS(msi[[#All],[CASH]],msi[[#All],[DATE]],$A29,msi[[#All],[Manual /OutSale]],"OutSale"))-(SUMIFS(MRet[[#All],[CASH]],MRet[[#All],[DATE]],$A29,MRet[[#All],[Manual/ OutSale]],"OutSale")) -> 0 | Y29: =D29-M29-N29+O29+Q29+R29-S29-T29-U29-V29-W29 -> 0 | Z29: =X29-Y29 -> 0
A30: =A29+1 -> 46318 | B30: =(SUMIFS(msi[[#All],[SP]],msi[[#All],[DATE]],$A30,msi[[#All],[Manual /OutSale]],"OutSale"))-(SUMIFS(MRet[[#All],[SP]],MRet[[#All],[DATE]],$A30,MRet[[#All],[Manual/ OutSale]],"OutSale")) -> 0 | C30: =(SUMIFS(msi[[#All],[DISC. AMOUNT]],msi[[#All],[DATE]],$A30,msi[[#All],[Manual /OutSale]],"OutSale"))-(SUMIFS(MRet[[#All],[DISC. AMOUNT]],MRet[[#All],[DATE]],$A30,MRet[[#All],[Manual/ OutSale]],"OutSale")) -> 0 | D30: =+B30-C30 -> 0 | F30: =+C30-E30 -> 0 | I30: =SUMIF(Z30,"<.01") -> 0 | J30: =SUMIF(Z30,">.01") -> 0 | M30: =(SUMIFS(msi[[#All],[CHARGE]],msi[[#All],[DATE]],$A30,msi[[#All],[Manual /OutSale]],"OutSale"))-(SUMIFS(MRet[[#All],[CHARGE]],MRet[[#All],[DATE]],$A30,MRet[[#All],[Manual/ OutSale]],"OutSale")) -> 0 | N30: =(SUMIFS(msi[[#All],[GC/ OTHERS]],msi[[#All],[DATE]],$A30,msi[[#All],[Manual /OutSale]],"OutSale"))-(SUMIFS(MRet[[#All],[GC/ OTHERS]],MRet[[#All],[DATE]],$A30,MRet[[#All],[Manual/ OutSale]],"OutSale")) -> 0 | S30: =(SUMIFS(msi[[#All],[Check]],msi[[#All],[DATE]],$A30,msi[[#All],[Manual /OutSale]],"OutSale"))-(SUMIFS(MRet[[#All],[Check]],MRet[[#All],[DATE]],$A30,MRet[[#All],[Manual/ OutSale]],"OutSale")) -> 0 | T30: =(SUMIFS(msi[[#All],[COD]],msi[[#All],[DATE]],$A30,msi[[#All],[Manual /OutSale]],"OutSale"))-(SUMIFS(MRet[[#All],[COD]],MRet[[#All],[DATE]],$A30,MRet[[#All],[Manual/ OutSale]],"OutSale")) -> 0 | U30: 0 | W30: =(SUMIFS(msi[[#All],[CWT]],msi[[#All],[DATE]],$A30,msi[[#All],[Manual /OutSale]],"OutSale"))-(SUMIFS(MRet[[#All],[CWT]],MRet[[#All],[DATE]],$A30,MRet[[#All],[Manual/ OutSale]],"OutSale")) -> 0 | X30: =(SUMIFS(msi[[#All],[CASH]],msi[[#All],[DATE]],$A30,msi[[#All],[Manual /OutSale]],"OutSale"))-(SUMIFS(MRet[[#All],[CASH]],MRet[[#All],[DATE]],$A30,MRet[[#All],[Manual/ OutSale]],"OutSale")) -> 0 | Y30: =D30-M30-N30+O30+Q30+R30-S30-T30-U30-V30-W30 -> 0 | Z30: =X30-Y30 -> 0
A31: =A30+1 -> 46319 | B31: =(SUMIFS(msi[[#All],[SP]],msi[[#All],[DATE]],$A31,msi[[#All],[Manual /OutSale]],"OutSale"))-(SUMIFS(MRet[[#All],[SP]],MRet[[#All],[DATE]],$A31,MRet[[#All],[Manual/ OutSale]],"OutSale")) -> 0 | C31: =(SUMIFS(msi[[#All],[DISC. AMOUNT]],msi[[#All],[DATE]],$A31,msi[[#All],[Manual /OutSale]],"OutSale"))-(SUMIFS(MRet[[#All],[DISC. AMOUNT]],MRet[[#All],[DATE]],$A31,MRet[[#All],[Manual/ OutSale]],"OutSale")) -> 0 | D31: =+B31-C31 -> 0 | F31: =+C31-E31 -> 0 | I31: =SUMIF(Z31,"<.01") -> 0 | J31: =SUMIF(Z31,">.01") -> 0 | M31: =(SUMIFS(msi[[#All],[CHARGE]],msi[[#All],[DATE]],$A31,msi[[#All],[Manual /OutSale]],"OutSale"))-(SUMIFS(MRet[[#All],[CHARGE]],MRet[[#All],[DATE]],$A31,MRet[[#All],[Manual/ OutSale]],"OutSale")) -> 0 | N31: =(SUMIFS(msi[[#All],[GC/ OTHERS]],msi[[#All],[DATE]],$A31,msi[[#All],[Manual /OutSale]],"OutSale"))-(SUMIFS(MRet[[#All],[GC/ OTHERS]],MRet[[#All],[DATE]],$A31,MRet[[#All],[Manual/ OutSale]],"OutSale")) -> 0 | S31: =(SUMIFS(msi[[#All],[Check]],msi[[#All],[DATE]],$A31,msi[[#All],[Manual /OutSale]],"OutSale"))-(SUMIFS(MRet[[#All],[Check]],MRet[[#All],[DATE]],$A31,MRet[[#All],[Manual/ OutSale]],"OutSale")) -> 0 | T31: =(SUMIFS(msi[[#All],[COD]],msi[[#All],[DATE]],$A31,msi[[#All],[Manual /OutSale]],"OutSale"))-(SUMIFS(MRet[[#All],[COD]],MRet[[#All],[DATE]],$A31,MRet[[#All],[Manual/ OutSale]],"OutSale")) -> 0 | U31: 0 | W31: =(SUMIFS(msi[[#All],[CWT]],msi[[#All],[DATE]],$A31,msi[[#All],[Manual /OutSale]],"OutSale"))-(SUMIFS(MRet[[#All],[CWT]],MRet[[#All],[DATE]],$A31,MRet[[#All],[Manual/ OutSale]],"OutSale")) -> 0 | X31: =(SUMIFS(msi[[#All],[CASH]],msi[[#All],[DATE]],$A31,msi[[#All],[Manual /OutSale]],"OutSale"))-(SUMIFS(MRet[[#All],[CASH]],MRet[[#All],[DATE]],$A31,MRet[[#All],[Manual/ OutSale]],"OutSale")) -> 0 | Y31: =D31-M31-N31+O31+Q31+R31-S31-T31-U31-V31-W31 -> 0 | Z31: =X31-Y31 -> 0
A32: =A31+1 -> 46320 | B32: =(SUMIFS(msi[[#All],[SP]],msi[[#All],[DATE]],$A32,msi[[#All],[Manual /OutSale]],"OutSale"))-(SUMIFS(MRet[[#All],[SP]],MRet[[#All],[DATE]],$A32,MRet[[#All],[Manual/ OutSale]],"OutSale")) -> 0 | C32: =(SUMIFS(msi[[#All],[DISC. AMOUNT]],msi[[#All],[DATE]],$A32,msi[[#All],[Manual /OutSale]],"OutSale"))-(SUMIFS(MRet[[#All],[DISC. AMOUNT]],MRet[[#All],[DATE]],$A32,MRet[[#All],[Manual/ OutSale]],"OutSale")) -> 0 | D32: =+B32-C32 -> 0 | F32: =+C32-E32 -> 0 | I32: =SUMIF(Z32,"<.01") -> 0 | J32: =SUMIF(Z32,">.01") -> 0 | M32: =(SUMIFS(msi[[#All],[CHARGE]],msi[[#All],[DATE]],$A32,msi[[#All],[Manual /OutSale]],"OutSale"))-(SUMIFS(MRet[[#All],[CHARGE]],MRet[[#All],[DATE]],$A32,MRet[[#All],[Manual/ OutSale]],"OutSale")) -> 0 | N32: =(SUMIFS(msi[[#All],[GC/ OTHERS]],msi[[#All],[DATE]],$A32,msi[[#All],[Manual /OutSale]],"OutSale"))-(SUMIFS(MRet[[#All],[GC/ OTHERS]],MRet[[#All],[DATE]],$A32,MRet[[#All],[Manual/ OutSale]],"OutSale")) -> 0 | S32: =(SUMIFS(msi[[#All],[Check]],msi[[#All],[DATE]],$A32,msi[[#All],[Manual /OutSale]],"OutSale"))-(SUMIFS(MRet[[#All],[Check]],MRet[[#All],[DATE]],$A32,MRet[[#All],[Manual/ OutSale]],"OutSale")) -> 0 | T32: =(SUMIFS(msi[[#All],[COD]],msi[[#All],[DATE]],$A32,msi[[#All],[Manual /OutSale]],"OutSale"))-(SUMIFS(MRet[[#All],[COD]],MRet[[#All],[DATE]],$A32,MRet[[#All],[Manual/ OutSale]],"OutSale")) -> 0 | U32: 0 | W32: =(SUMIFS(msi[[#All],[CWT]],msi[[#All],[DATE]],$A32,msi[[#All],[Manual /OutSale]],"OutSale"))-(SUMIFS(MRet[[#All],[CWT]],MRet[[#All],[DATE]],$A32,MRet[[#All],[Manual/ OutSale]],"OutSale")) -> 0 | X32: =(SUMIFS(msi[[#All],[CASH]],msi[[#All],[DATE]],$A32,msi[[#All],[Manual /OutSale]],"OutSale"))-(SUMIFS(MRet[[#All],[CASH]],MRet[[#All],[DATE]],$A32,MRet[[#All],[Manual/ OutSale]],"OutSale")) -> 0 | Y32: =D32-M32-N32+O32+Q32+R32-S32-T32-U32-V32-W32 -> 0 | Z32: =X32-Y32 -> 0
A33: =A32+1 -> 46321 | B33: =(SUMIFS(msi[[#All],[SP]],msi[[#All],[DATE]],$A33,msi[[#All],[Manual /OutSale]],"OutSale"))-(SUMIFS(MRet[[#All],[SP]],MRet[[#All],[DATE]],$A33,MRet[[#All],[Manual/ OutSale]],"OutSale")) -> 0 | C33: =(SUMIFS(msi[[#All],[DISC. AMOUNT]],msi[[#All],[DATE]],$A33,msi[[#All],[Manual /OutSale]],"OutSale"))-(SUMIFS(MRet[[#All],[DISC. AMOUNT]],MRet[[#All],[DATE]],$A33,MRet[[#All],[Manual/ OutSale]],"OutSale")) -> 0 | D33: =+B33-C33 -> 0 | F33: =+C33-E33 -> 0 | I33: =SUMIF(Z33,"<.01") -> 0 | J33: =SUMIF(Z33,">.01") -> 0 | M33: =(SUMIFS(msi[[#All],[CHARGE]],msi[[#All],[DATE]],$A33,msi[[#All],[Manual /OutSale]],"OutSale"))-(SUMIFS(MRet[[#All],[CHARGE]],MRet[[#All],[DATE]],$A33,MRet[[#All],[Manual/ OutSale]],"OutSale")) -> 0 | N33: =(SUMIFS(msi[[#All],[GC/ OTHERS]],msi[[#All],[DATE]],$A33,msi[[#All],[Manual /OutSale]],"OutSale"))-(SUMIFS(MRet[[#All],[GC/ OTHERS]],MRet[[#All],[DATE]],$A33,MRet[[#All],[Manual/ OutSale]],"OutSale")) -> 0 | S33: =(SUMIFS(msi[[#All],[Check]],msi[[#All],[DATE]],$A33,msi[[#All],[Manual /OutSale]],"OutSale"))-(SUMIFS(MRet[[#All],[Check]],MRet[[#All],[DATE]],$A33,MRet[[#All],[Manual/ OutSale]],"OutSale")) -> 0 | T33: =(SUMIFS(msi[[#All],[COD]],msi[[#All],[DATE]],$A33,msi[[#All],[Manual /OutSale]],"OutSale"))-(SUMIFS(MRet[[#All],[COD]],MRet[[#All],[DATE]],$A33,MRet[[#All],[Manual/ OutSale]],"OutSale")) -> 0 | U33: 0 | W33: =(SUMIFS(msi[[#All],[CWT]],msi[[#All],[DATE]],$A33,msi[[#All],[Manual /OutSale]],"OutSale"))-(SUMIFS(MRet[[#All],[CWT]],MRet[[#All],[DATE]],$A33,MRet[[#All],[Manual/ OutSale]],"OutSale")) -> 0 | X33: =(SUMIFS(msi[[#All],[CASH]],msi[[#All],[DATE]],$A33,msi[[#All],[Manual /OutSale]],"OutSale"))-(SUMIFS(MRet[[#All],[CASH]],MRet[[#All],[DATE]],$A33,MRet[[#All],[Manual/ OutSale]],"OutSale")) -> 0 | Y33: =D33-M33-N33+O33+Q33+R33-S33-T33-U33-V33-W33 -> 0 | Z33: =X33-Y33 -> 0
A34: =A33+1 -> 46322 | B34: =(SUMIFS(msi[[#All],[SP]],msi[[#All],[DATE]],$A34,msi[[#All],[Manual /OutSale]],"OutSale"))-(SUMIFS(MRet[[#All],[SP]],MRet[[#All],[DATE]],$A34,MRet[[#All],[Manual/ OutSale]],"OutSale")) -> 0 | C34: =(SUMIFS(msi[[#All],[DISC. AMOUNT]],msi[[#All],[DATE]],$A34,msi[[#All],[Manual /OutSale]],"OutSale"))-(SUMIFS(MRet[[#All],[DISC. AMOUNT]],MRet[[#All],[DATE]],$A34,MRet[[#All],[Manual/ OutSale]],"OutSale")) -> 0 | D34: =+B34-C34 -> 0 | F34: =+C34-E34 -> 0 | I34: =SUMIF(Z34,"<.01") -> 0 | J34: =SUMIF(Z34,">.01") -> 0 | M34: =(SUMIFS(msi[[#All],[CHARGE]],msi[[#All],[DATE]],$A34,msi[[#All],[Manual /OutSale]],"OutSale"))-(SUMIFS(MRet[[#All],[CHARGE]],MRet[[#All],[DATE]],$A34,MRet[[#All],[Manual/ OutSale]],"OutSale")) -> 0 | N34: =(SUMIFS(msi[[#All],[GC/ OTHERS]],msi[[#All],[DATE]],$A34,msi[[#All],[Manual /OutSale]],"OutSale"))-(SUMIFS(MRet[[#All],[GC/ OTHERS]],MRet[[#All],[DATE]],$A34,MRet[[#All],[Manual/ OutSale]],"OutSale")) -> 0 | S34: =(SUMIFS(msi[[#All],[Check]],msi[[#All],[DATE]],$A34,msi[[#All],[Manual /OutSale]],"OutSale"))-(SUMIFS(MRet[[#All],[Check]],MRet[[#All],[DATE]],$A34,MRet[[#All],[Manual/ OutSale]],"OutSale")) -> 0 | T34: =(SUMIFS(msi[[#All],[COD]],msi[[#All],[DATE]],$A34,msi[[#All],[Manual /OutSale]],"OutSale"))-(SUMIFS(MRet[[#All],[COD]],MRet[[#All],[DATE]],$A34,MRet[[#All],[Manual/ OutSale]],"OutSale")) -> 0 | U34: 0 | W34: =(SUMIFS(msi[[#All],[CWT]],msi[[#All],[DATE]],$A34,msi[[#All],[Manual /OutSale]],"OutSale"))-(SUMIFS(MRet[[#All],[CWT]],MRet[[#All],[DATE]],$A34,MRet[[#All],[Manual/ OutSale]],"OutSale")) -> 0 | X34: =(SUMIFS(msi[[#All],[CASH]],msi[[#All],[DATE]],$A34,msi[[#All],[Manual /OutSale]],"OutSale"))-(SUMIFS(MRet[[#All],[CASH]],MRet[[#All],[DATE]],$A34,MRet[[#All],[Manual/ OutSale]],"OutSale")) -> 0 | Y34: =D34-M34-N34+O34+Q34+R34-S34-T34-U34-V34-W34 -> 0 | Z34: =X34-Y34 -> 0
A35: =A34+1 -> 46323 | B35: =(SUMIFS(msi[[#All],[SP]],msi[[#All],[DATE]],$A35,msi[[#All],[Manual /OutSale]],"OutSale"))-(SUMIFS(MRet[[#All],[SP]],MRet[[#All],[DATE]],$A35,MRet[[#All],[Manual/ OutSale]],"OutSale")) -> 0 | C35: =(SUMIFS(msi[[#All],[DISC. AMOUNT]],msi[[#All],[DATE]],$A35,msi[[#All],[Manual /OutSale]],"OutSale"))-(SUMIFS(MRet[[#All],[DISC. AMOUNT]],MRet[[#All],[DATE]],$A35,MRet[[#All],[Manual/ OutSale]],"OutSale")) -> 0 | D35: =+B35-C35 -> 0 | F35: =+C35-E35 -> 0 | I35: =SUMIF(Z35,"<.01") -> 0 | J35: =SUMIF(Z35,">.01") -> 0 | M35: =(SUMIFS(msi[[#All],[CHARGE]],msi[[#All],[DATE]],$A35,msi[[#All],[Manual /OutSale]],"OutSale"))-(SUMIFS(MRet[[#All],[CHARGE]],MRet[[#All],[DATE]],$A35,MRet[[#All],[Manual/ OutSale]],"OutSale")) -> 0 | N35: =(SUMIFS(msi[[#All],[GC/ OTHERS]],msi[[#All],[DATE]],$A35,msi[[#All],[Manual /OutSale]],"OutSale"))-(SUMIFS(MRet[[#All],[GC/ OTHERS]],MRet[[#All],[DATE]],$A35,MRet[[#All],[Manual/ OutSale]],"OutSale")) -> 0 | S35: =(SUMIFS(msi[[#All],[Check]],msi[[#All],[DATE]],$A35,msi[[#All],[Manual /OutSale]],"OutSale"))-(SUMIFS(MRet[[#All],[Check]],MRet[[#All],[DATE]],$A35,MRet[[#All],[Manual/ OutSale]],"OutSale")) -> 0 | T35: =(SUMIFS(msi[[#All],[COD]],msi[[#All],[DATE]],$A35,msi[[#All],[Manual /OutSale]],"OutSale"))-(SUMIFS(MRet[[#All],[COD]],MRet[[#All],[DATE]],$A35,MRet[[#All],[Manual/ OutSale]],"OutSale")) -> 0 | U35: 0 | W35: =(SUMIFS(msi[[#All],[CWT]],msi[[#All],[DATE]],$A35,msi[[#All],[Manual /OutSale]],"OutSale"))-(SUMIFS(MRet[[#All],[CWT]],MRet[[#All],[DATE]],$A35,MRet[[#All],[Manual/ OutSale]],"OutSale")) -> 0 | X35: =(SUMIFS(msi[[#All],[CASH]],msi[[#All],[DATE]],$A35,msi[[#All],[Manual /OutSale]],"OutSale"))-(SUMIFS(MRet[[#All],[CASH]],MRet[[#All],[DATE]],$A35,MRet[[#All],[Manual/ OutSale]],"OutSale")) -> 0 | Y35: =D35-M35-N35+O35+Q35+R35-S35-T35-U35-V35-W35 -> 0 | Z35: =X35-Y35 -> 0
... A38: =A37+1 -> 46326 | B38: =(SUMIFS(msi[[#All],[SP]],msi[[#All],[DATE]],$A38,msi[[#All],[Manual /OutSale]],"OutSale"))-(SUMIFS(MRet[[#All],[SP]],MRet[[#All],[DATE]],$A38,MRet[[#All],[Manual/ OutSale]],"OutSale")) -> 0 | C38: =(SUMIFS(msi[[#All],[DISC. AMOUNT]],msi[[#All],[DATE]],$A38,msi[[#All],[Manual /OutSale]],"OutSale"))-(SUMIFS(MRet[[#All],[DISC. AMOUNT]],MRet[[#All],[DATE]],$A38,MRet[[#All],[Manual/ OutSale]],"OutSale")) -> 0 | D38: =+B38-C38 -> 0 | F38: =+C38-E38 -> 0 | I38: =SUMIF(Z38,"<.01") -> 0 | J38: =SUMIF(Z38,">.01") -> 0 | M38: =(SUMIFS(msi[[#All],[CHARGE]],msi[[#All],[DATE]],$A38,msi[[#All],[Manual /OutSale]],"OutSale"))-(SUMIFS(MRet[[#All],[CHARGE]],MRet[[#All],[DATE]],$A38,MRet[[#All],[Manual/ OutSale]],"OutSale")) -> 0 | N38: =(SUMIFS(msi[[#All],[GC/ OTHERS]],msi[[#All],[DATE]],$A38,msi[[#All],[Manual /OutSale]],"OutSale"))-(SUMIFS(MRet[[#All],[GC/ OTHERS]],MRet[[#All],[DATE]],$A38,MRet[[#All],[Manual/ OutSale]],"OutSale")) -> 0 | S38: =(SUMIFS(msi[[#All],[Check]],msi[[#All],[DATE]],$A38,msi[[#All],[Manual /OutSale]],"OutSale"))-(SUMIFS(MRet[[#All],[Check]],MRet[[#All],[DATE]],$A38,MRet[[#All],[Manual/ OutSale]],"OutSale")) -> 0 | T38: =(SUMIFS(msi[[#All],[COD]],msi[[#All],[DATE]],$A38,msi[[#All],[Manual /OutSale]],"OutSale"))-(SUMIFS(MRet[[#All],[COD]],MRet[[#All],[DATE]],$A38,MRet[[#All],[Manual/ OutSale]],"OutSale")) -> 0 | U38: 0 | W38: =(SUMIFS(msi[[#All],[CWT]],msi[[#All],[DATE]],$A38,msi[[#All],[Manual /OutSale]],"OutSale"))-(SUMIFS(MRet[[#All],[CWT]],MRet[[#All],[DATE]],$A38,MRet[[#All],[Manual/ OutSale]],"OutSale")) -> 0 | X38: =(SUMIFS(msi[[#All],[CASH]],msi[[#All],[DATE]],$A38,msi[[#All],[Manual /OutSale]],"OutSale"))-(SUMIFS(MRet[[#All],[CASH]],MRet[[#All],[DATE]],$A38,MRet[[#All],[Manual/ OutSale]],"OutSale")) -> 0 | Y38: =D38-M38-N38+O38+Q38+R38-S38-T38-U38-V38-W38 -> 0 | Z38: =X38-Y38 -> 0
B39: =SUM(B23:B38) -> 0 | C39: =SUM(C23:C38) -> 0 | D39: =SUM(D23:D38) -> 0 | E39: =SUM(E23:E38) -> 0 | F39: =SUM(F23:F38) -> 0 | G39: =SUM(G23:G38) -> 0 | H39: =SUM(H23:H38) -> 0 | I39: =SUM(I23:I38) -> 0 | ... K39: =SUM(K23:K38) -> 0 | M39: =SUM(M23:M38) -> 0 | N39: =SUM(N23:N38) -> 0 | O39: =SUM(O23:O38) -> 0 | P39: =SUM(P23:P38) -> 0 | Q39: =SUM(Q23:Q38) -> 0 | R39: =SUM(R23:R38) -> 0 | S39: =SUM(S23:S38) -> 0 | T39: =SUM(T23:T38) -> 0 | ... Z39: =SUM(Z23:Z38) -> 0
B41: =+B21+B39 -> 0 | C41: =+C21+C39 -> 0 | D41: =+D21+D39 -> 0 | E41: =+E21+E39 -> 0 | F41: =+F21+F39 -> 0 | G41: =+G21+G39 -> 0 | H41: =+H21+H39 -> 0 | I41: =+I21+I39 -> 0 | ... K41: =+K21+K39 -> 0 | M41: =+M21+M39 -> 0 | N41: =+N21+N39 -> 0 | O41: =+O21+O39 -> 0 | P41: =+P21+P39 -> 0 | Q41: =+Q21+Q39 -> 0 | R41: =+R21+R39 -> 0 | S41: =+S21+S39 -> 0 | T41: =+T21+T39 -> 0 | ... Z41: =+Z21+Z39 -> 0

Sheet Seasonality Template
D1: DAILY SALES MONITORING REPORT
N2: Interpretation:
N3: *Current seasonality %age is 62% while Sales Achievement is @ 31%. The store is short by 31% on seasonality
N4: *Staright line is 58% while Sales Achievement is @ 31%. The store is short by 27% on straight line
N5: **Seasonality percentage shows sales trend last year thus it will be great if the store is at par with the seasonality %age
N6: **Straight line shows equal distribution of sales based on the no. Of days
D12: STORE: | E12: TOBYS MEGAMALL
D13: MONTH: | E13: OCTOBER 1-31, 2026
O14: RETAIL DRIVERS | P14: RUNNING LY | Q14: RUNNING 2025 | R14: % inc/dec | T14: RETAIL DRIVERS | U14: RUNNING LY | V14: RUNNING 2016 | W14: % inc/dec
D15: GROSS SALES TARGET | G15: 8700000 | H15: AVE. DAILY SALES | J15: =G16/J20 -> 241445.51 | K15: GROSS MARGIN TARGET | O15: Entering Customer | P15: =SUM(AI25:AI55) -> 17825 | Q15: =SUM(AJ25:AJ55) -> 6827 | R15: =Q15/P15-1 -> -0.6169986 | T15: Gait Request | U15: =SUM(BG25:BG55) -> 0 | V15: =BH56 -> 0 | W15: =V15/U15-1 -> #DIV/0!
D16: MONTH-TO-DATE (MTD) | G16: =K56 -> 2655900.6 | H16: TARGET GROWTH VS. LY | J16: =G15/G56-1 -> 0.081261794 | K16: MONTH-TO-DATE (MTD) | M16: =AB56 -> 796770.18 | O16: Buying Customer | P16: =SUM(AL25:AL55) -> 3435 | Q16: =SUM(AM25:AM55) -> 1013 | R16: =Q16/P16-1 -> -0.70509461 | T16: Gait w/ po | U16: =SUM(BJ25:BJ55) -> 0 | V16: =BK56 -> 0 | W16: =V16/U16-1 -> #DIV/0!
D17: TOTAL VARIANCE ON TARGET | G17: =G16-G15 -> -6044099.4 | H17: CURRENT SEASONALITY | J17: =SUM(H25:H35) -> 0.3316651 | K17: TOTAL VARIANCE ON TARGET | M17: =M16-M15 -> 796770.18 | O17: Average Purchase | P17: =G56/AL56 -> 2342.4032 | Q17: =G16/Q16 -> 2621.817 | R17: =Q17/P17-1 -> 0.11928509 | T17: Gait Conversion | U17: =U16/U15 -> #DIV/0! | V17: =V16/V15 -> #DIV/0! | W17: =V17-U17 -> #DIV/0!
D18: TOTAL VARIANCE ON EXPECTED SALES -DAILY | G18: =N35 -> -387695.76 | H18: STRAIGHT LINE | J18: =(100%/31)*J20 -> 0.35483871 | K18: GM ACHIEVEMENT | M18: =SUM(AC25:AC55) -> #DIV/0! | O18: Conversion Ratio | P18: =P16/P15 -> 0.19270687 | Q18: =Q16/Q15 -> 0.14838143 | R18: =Q18-P18 -> -0.044325446 | T18: Shoes Sold | U18: =BQ56 -> 0 | V18: =BR56 -> 0 | W18: =V18/U18-1 -> #DIV/0!
D19: AVE. SALES NEEDED- DAILY | G19: =G17/J21 -> -302204.97 | H19: SALES ACHIEVEMENT | J19: =SUM(M25:M55) -> 0.30527593 | K19: GM ACHIEVEMENT BASED ON GROSS SALES | M19: =M16/G16 -> 0.3 | O19: Raquet Stringing | P19: =SUM(AY25:AY55) -> 142 | Q19: =AZ56 -> 54 | R19: =Q19/P19-1 -> -0.61971831
D20: BEST EOM PESO VALUE | G20: =J15*J21+G16 -> 7484810.8 | H20: RUNNING DAY/S | J20: 11 | O20: Shoot-out | P20: =BC56 -> 0 | Q20: =BD56 -> 0 | R20: =Q20/P20-1 -> #DIV/0!
D21: BEST EOM % | G21: =G20/G15 -> 0.86032308 | H21: REMAINING DAY/S | J21: =31-J20 -> 20 | K21: =1-J19 -> 0.69472407 | L21: vs target | O21: *Note: Follow execution on the sales template
D22: MONTH-TO-DATE (MTD) LY | G22: =G56 -> 8046155 | H22: % LY | J22: =(K56-G22)/G22 -> -0.6699168 | T22: GROSS MARGIN COMPUTATION
D23: . | T23: CONCESSION | X23: OUTRIGHT | AB23: TOTAL GROSS MARGIN 2025 | AC23: % SEASONALITY OF ACTUAL GROSS MARGIN
D24: DATE | G24: ACTUAL 2025 | H24: % SEASONALITY | I24: TARGET SALES PER DAY | J24: DAYS | K24: ACTUAL 2026 | L24: VARIANCE ON DAILY SALES TARGET | M24: % SEASONALITY OF ACTUAL SALES | N24: Running Variance | O24: QTY. SOLD 2026 | P24: DISCOUNT 2025 | Q24: DISCOUNT 2026 | R24: % CHANGE | T24: CONCESSION SALES 2025 | U24: CONCESSION SALES 2026 | V24: % Inc/Dec | W24: CONCESSION GM 2025 | X24: OUTRIGHT SALES 2025 | Y24: OUTRIGHT SALES 2026 | Z24: % Inc/Dec | AA24: OUTRIGHT GM 2025 | AE24: CREDIT CARD SALES 2025 | AF24: CREDIT CARD SALES 2026 | AG24: % Inc/Dec | AI24: ENTERING CUSTOMER 2025 | AJ24: ENTERING CUSTOMER 2026 | AK24: % Inc/Dec | AL24: BUYING CUSTOMER 2024 | AM24: BUYING CUSTOMER 2025 | AN24: % Inc/Dec | AO24: BATTING AVE. 2024 | AP24: BATTING AVE. 2025 | AQ24: % Inc/Dec | AS24: TENNIS 2025 | AT24: TENNIS 2026 | AU24: % Inc/Dec | AV24: BADMINTON 2025 | AW24: BADMINTON 2026 | AX24: % Inc/Dec | AY24: TOTAL RACQUETS STRINGING 2024 | AZ24: TOTAL RACQUETS STRINGING 2025 | BA24: % CHANGE | BC24: SHOOT-OUT SALES 2024 | BD24: SHOOT-OUT SALES 2025 | BE24: % Inc/Dec | BG24: GAIT REQUEST 2024 | BH24: GAIT REQUEST 2025 | BI24: % Inc/Dec | BJ24: GAIT W/ PO 2024 | BK24: GAIT W/ PO 2025 | BL24: % Inc/Dec | BM24: GAIT CONVERSION 2024 | BN24: GAIT CONVERSION 2025 | BO24: % CHANGE | BQ24: SHOES SOLD 2025 | BR24: SHOES SOLD 2026 | BS24: % Inc/Dec
D25: 1 | E25: Thursday | G25: 196063.15 | H25: =K25/G$56 -> 0.021531073 | I25: =G$15*H25 -> 187320.33 | J25: Thursday | K25: =LS_RPRO!B6+MANUAL!B6+OUTSALE!B6 -> 173242.35 | L25: =K25-I25 -> -14077.984 | M25: =K25/G15 -> 0.019912914 | N25: =L25 -> -14077.984 | P25: 0 | Q25: =LS_RPRO!C6+MANUAL!C6+OUTSALE!C6 -> 0 | R25: =(Q25-P25)/P25 -> #DIV/0! | V25: =(U25-T25)/T25 -> #DIV/0! | W25: =U25*25% -> 0 | Y25: =K25-U25 -> 173242.35 | Z25: =(Y25-X25)/X25 -> #DIV/0! | AA25: =Y25*30% -> 51972.705 | AB25: =W25+AA25 -> 51972.705 | AC25: =AB25/$M$15 -> #DIV/0! | AE25: 120657.9 | AF25: =LS_RPRO!O6+MANUAL!M6+OUTSALE!M6 -> 137805.35 | AG25: =(AF25-AE25)/AE25 -> 0.14211626 | AI25: 327 | AJ25: =LS_RPRO!M6 -> 359 | AK25: =AJ25/AI25-1 -> 0.097859327 | AL25: 76 | AM25: =LS_RPRO!H6+MANUAL!H6+OUTSALE!H6 -> 0 | AN25: =AM25/AL25-1 -> -1 | AO25: =AL25/AI25 -> 0.2324159 | AP25: =AM25/AJ25 -> 0 | AQ25: =AP25-AO25 -> -0.2324159 | AS25: 0 | AT25: =LS_RPRO!K6 -> 0 | AU25: =(AT25-AS25)/AS25 -> #DIV/0! | AV25: 0 | AW25: =LS_RPRO!L6 -> 0 | AX25: =(AW25-AV25)/AV25 -> #DIV/0! | AY25: =AS25+AV25 -> 0 | AZ25: =AT25+AW25 -> 0 | BA25: =(AZ25-AY25)/AY25 -> #DIV/0! | BD25: 0 | BE25: =(BD25-BC25)/BC25 -> #DIV/0! | BI25: =(BH25-BG25)/BG25 -> #DIV/0! | BL25: =(BK25-BJ25)/BJ25 -> #DIV/0! | BM25: =BJ25/BG25 -> #DIV/0! | BN25: =BK25/BH25 -> #DIV/0! | BO25: =BN25-BM25 -> #DIV/0! | BS25: =(BR25-BQ25)/BQ25 -> #DIV/0!
D26: 2 | E26: Friday | G26: 168531.4 | H26: =G26/G$56 -> 0.020945582 | I26: =G$15*H26 -> 182226.56 | J26: Friday | K26: =LS_RPRO!B7+MANUAL!B7+OUTSALE!B7 -> 208772.5 | L26: =K26-I26 -> 26545.936 | M26: =K26/G15 -> 0.023996839 | N26: =N25+L26 -> 12467.952 | P26: 54.5 | Q26: =LS_RPRO!C7+MANUAL!C7+OUTSALE!C7 -> 169.8 | R26: =(Q26-P26)/P26 -> 2.1155963 | V26: =(U26-T26)/T26 -> #DIV/0! | W26: =U26*25% -> 0 | Y26: =K26-U26 -> 208772.5 | Z26: =(Y26-X26)/X26 -> #DIV/0! | AA26: =Y26*30% -> 62631.75 | AB26: =W26+AA26 -> 62631.75 | AC26: =AB26/$M$15 -> #DIV/0! | AE26: 126636.75 | AF26: =LS_RPRO!O7+MANUAL!M7+OUTSALE!M7 -> 171801.75 | AG26: =(AF26-AE26)/AE26 -> 0.35665002 | AI26: 408 | AJ26: =LS_RPRO!M7 -> 446 | AK26: =AJ26/AI26-1 -> 0.093137255 | AL26: 90 | AM26: =LS_RPRO!H7+MANUAL!H7+OUTSALE!H7 -> 101 | AN26: =AM26/AL26-1 -> 0.12222222 | AO26: =AL26/AI26 -> 0.22058824 | AP26: =AM26/AJ26 -> 0.2264574 | AQ26: =AP26-AO26 -> 0.0058691638 | AS26: 4 | AT26: =LS_RPRO!K7 -> 0 | AU26: =(AT26-AS26)/AS26 -> -1 | AV26: 4 | AW26: =LS_RPRO!L7 -> 2 | AX26: =(AW26-AV26)/AV26 -> -0.5 | AY26: =AS26+AV26 -> 8 | AZ26: =AT26+AW26 -> 2 | BA26: =(AZ26-AY26)/AY26 -> -0.75 | BD26: 0 | BE26: =(BD26-BC26)/BC26 -> #DIV/0! | BI26: =(BH26-BG26)/BG26 -> #DIV/0! | BL26: =(BK26-BJ26)/BJ26 -> #DIV/0! | BM26: =BJ26/BG26 -> #DIV/0! | BN26: =BK26/BH26 -> #DIV/0! | BO26: =BN26-BM26 -> #DIV/0! | BS26: =(BR26-BQ26)/BQ26 -> #DIV/0!
D27: 3 | E27: Saturday | G27: 168709 | H27: =G27/G$56 -> 0.020967655 | I27: =G$15*H27 -> 182418.6 | J27: Saturday | K27: =LS_RPRO!B8+MANUAL!B8+OUTSALE!B8 -> 355795.97 | L27: =K27-I27 -> 173377.37 | M27: =K27/G15 -> 0.040896089 | N27: =N26+L27 -> 185845.33 | P27: 605.63 | Q27: =LS_RPRO!C8+MANUAL!C8+OUTSALE!C8 -> 708.96 | R27: =(Q27-P27)/P27 -> 0.17061572 | V27: =(U27-T27)/T27 -> #DIV/0! | W27: =U27*25% -> 0 | Y27: =K27-U27 -> 355795.97 | Z27: =(Y27-X27)/X27 -> #DIV/0! | AA27: =Y27*30% -> 106738.79 | AB27: =W27+AA27 -> 106738.79 | AC27: =AB27/$M$15 -> #DIV/0! | AE27: 243724.1 | AF27: =LS_RPRO!O8+MANUAL!M8+OUTSALE!M8 -> 285580.75 | AG27: =(AF27-AE27)/AE27 -> 0.17173784 | AI27: 674 | AJ27: =LS_RPRO!M8 -> 976 | AK27: =AJ27/AI27-1 -> 0.44807122 | AL27: 165 | AM27: =LS_RPRO!H8+MANUAL!H8+OUTSALE!H8 -> 138 | AN27: =AM27/AL27-1 -> -0.16363636 | AO27: =AL27/AI27 -> 0.24480712 | AP27: =AM27/AJ27 -> 0.14139344 | AQ27: =AP27-AO27 -> -0.10341368 | AS27: 1 | AT27: =LS_RPRO!K8 -> 4 | AU27: =(AT27-AS27)/AS27 -> 3 | AV27: 6 | AW27: =LS_RPRO!L8 -> 5 | AX27: =(AW27-AV27)/AV27 -> -0.16666667 | AY27: =AS27+AV27 -> 7 | AZ27: =AT27+AW27 -> 9 | BA27: =(AZ27-AY27)/AY27 -> 0.28571429 | BD27: 0 | BE27: =(BD27-BC27)/BC27 -> #DIV/0! | BI27: =(BH27-BG27)/BG27 -> #DIV/0! | BL27: =(BK27-BJ27)/BJ27 -> #DIV/0! | BM27: =BJ27/BG27 -> #DIV/0! | BN27: =BK27/BH27 -> #DIV/0! | BO27: =BN27-BM27 -> #DIV/0! | BS27: =(BR27-BQ27)/BQ27 -> #DIV/0!
D28: 4 | E28: Sunday | G28: 373840.98 | H28: =G28/G$56 -> 0.046462065 | I28: =G$15*H28 -> 404219.97 | J28: Sunday | K28: =LS_RPRO!B9+MANUAL!B9+OUTSALE!B9 -> 300026.7 | L28: =K28-I28 -> -104193.27 | M28: =K28/G15 -> 0.034485828 | N28: =N27+L28 -> 81652.057 | P28: 1372.15 | Q28: =LS_RPRO!C9+MANUAL!C9+OUTSALE!C9 -> 2180.5 | R28: =(Q28-P28)/P28 -> 0.58911198 | V28: =(U28-T28)/T28 -> #DIV/0! | W28: =U28*25% -> 0 | Y28: =K28-U28 -> 300026.7 | Z28: =(Y28-X28)/X28 -> #DIV/0! | AA28: =Y28*30% -> 90008.01 | AB28: =W28+AA28 -> 90008.01 | AC28: =AB28/$M$15 -> #DIV/0! | AE28: 314059.82 | AF28: =LS_RPRO!O9+MANUAL!M9+OUTSALE!M9 -> 243077.7 | AG28: =(AF28-AE28)/AE28 -> -0.22601465 | AI28: 881 | AJ28: =LS_RPRO!M9 -> 883 | AK28: =AJ28/AI28-1 -> 0.0022701476 | AL28: 175 | AM28: =LS_RPRO!H9+MANUAL!H9+OUTSALE!H9 -> 130 | AN28: =AM28/AL28-1 -> -0.25714286 | AO28: =AL28/AI28 -> 0.19863791 | AP28: =AM28/AJ28 -> 0.14722537 | AQ28: =AP28-AO28 -> -0.051412543 | AS28: 2 | AT28: =LS_RPRO!K9 -> 0 | AU28: =(AT28-AS28)/AS28 -> -1 | AV28: 10 | AW28: =LS_RPRO!L9 -> 17 | AX28: =(AW28-AV28)/AV28 -> 0.7 | AY28: =AS28+AV28 -> 12 | AZ28: =AT28+AW28 -> 17 | BA28: =(AZ28-AY28)/AY28 -> 0.41666667 | BD28: 0 | BE28: =(BD28-BC28)/BC28 -> #DIV/0! | BI28: =(BH28-BG28)/BG28 -> #DIV/0! | BL28: =(BK28-BJ28)/BJ28 -> #DIV/0! | BM28: =BJ28/BG28 -> #DIV/0! | BN28: =BK28/BH28 -> #DIV/0! | BO28: =BN28-BM28 -> #DIV/0! | BS28: =(BR28-BQ28)/BQ28 -> #DIV/0!
D29: 5 | E29: Monday | G29: 445288.82 | H29: =G29/G$56 -> 0.055341815 | I29: =G$15*H29 -> 481473.79 | J29: Monday | K29: =LS_RPRO!B10+MANUAL!B10+OUTSALE!B10 -> 214629.95 | L29: =K29-I29 -> -266843.84 | M29: =K29/G15 -> 0.024670109 | N29: =N28+L29 -> -185191.78 | P29: 85 | Q29: =LS_RPRO!C10+MANUAL!C10+OUTSALE!C10 -> 1596.06 | R29: =(Q29-P29)/P29 -> 17.777176 | V29: =(U29-T29)/T29 -> #DIV/0! | W29: =U29*25% -> 0 | Y29: =K29-U29 -> 214629.95 | Z29: =(Y29-X29)/X29 -> #DIV/0! | AA29: =Y29*30% -> 64388.985 | AB29: =W29+AA29 -> 64388.985 | AC29: =AB29/$M$15 -> #DIV/0! | AE29: 133602.5 | AF29: =LS_RPRO!O10+MANUAL!M10+OUTSALE!M10 -> 168429.69 | AG29: =(AF29-AE29)/AE29 -> 0.26067768 | AI29: 590 | AJ29: =LS_RPRO!M10 -> 687 | AK29: =AJ29/AI29-1 -> 0.16440678 | AL29: 95 | AM29: =LS_RPRO!H10+MANUAL!H10+OUTSALE!H10 -> 75 | AN29: =AM29/AL29-1 -> -0.21052632 | AO29: =AL29/AI29 -> 0.16101695 | AP29: =AM29/AJ29 -> 0.10917031 | AQ29: =AP29-AO29 -> -0.051846643 | AS29: 1 | AT29: =LS_RPRO!K10 -> 5 | AU29: =(AT29-AS29)/AS29 -> 4 | AV29: 5 | AW29: =LS_RPRO!L10 -> 1 | AX29: =(AW29-AV29)/AV29 -> -0.8 | AY29: =AS29+AV29 -> 6 | AZ29: =AT29+AW29 -> 6 | BA29: =(AZ29-AY29)/AY29 -> 0 | BD29: 0 | BE29: =(BD29-BC29)/BC29 -> #DIV/0! | BI29: =(BH29-BG29)/BG29 -> #DIV/0! | BL29: =(BK29-BJ29)/BJ29 -> #DIV/0! | BM29: =BJ29/BG29 -> #DIV/0! | BN29: =BK29/BH29 -> #DIV/0! | BO29: =BN29-BM29 -> #DIV/0! | BS29: =(BR29-BQ29)/BQ29 -> #DIV/0!
D30: 6 | E30: Tuesday | G30: 191197.5 | H30: =G30/G$56 -> 0.023762592 | I30: =G$15*H30 -> 206734.55 | J30: Tuesday | K30: =LS_RPRO!B11+MANUAL!B11+OUTSALE!B11 -> 151874.5 | L30: =K30-I30 -> -54860.052 | M30: =K30/G15 -> 0.017456839 | N30: =N29+L30 -> -240051.83 | P30: 45 | Q30: =LS_RPRO!C11+MANUAL!C11+OUTSALE!C11 -> 328.75 | R30: =(Q30-P30)/P30 -> 6.3055556 | V30: =(U30-T30)/T30 -> #DIV/0! | W30: =U30*25% -> 0 | Y30: =K30-U30 -> 151874.5 | Z30: =(Y30-X30)/X30 -> #DIV/0! | AA30: =Y30*30% -> 45562.35 | AB30: =W30+AA30 -> 45562.35 | AC30: =AB30/$M$15 -> #DIV/0! | AE30: 162334.45 | AF30: =LS_RPRO!O11+MANUAL!M11+OUTSALE!M11 -> 143597.75 | AG30: =(AF30-AE30)/AE30 -> -0.11542036 | AI30: 596 | AJ30: =LS_RPRO!M11 -> 333 | AK30: =AJ30/AI30-1 -> -0.44127517 | AL30: 76 | AM30: =LS_RPRO!H11+MANUAL!H11+OUTSALE!H11 -> 72 | AN30: =AM30/AL30-1 -> -0.052631579 | AO30: =AL30/AI30 -> 0.12751678 | AP30: =AM30/AJ30 -> 0.21621622 | AQ30: =AP30-AO30 -> 0.088699438 | AS30: 0 | AT30: =LS_RPRO!K11 -> 1 | AU30: =(AT30-AS30)/AS30 -> #DIV/0! | AV30: 0 | AW30: =LS_RPRO!L11 -> 1 | AX30: =(AW30-AV30)/AV30 -> #DIV/0! | AY30: =AS30+AV30 -> 0 | AZ30: =AT30+AW30 -> 2 | BA30: =(AZ30-AY30)/AY30 -> #DIV/0! | BD30: 0 | BE30: =(BD30-BC30)/BC30 -> #DIV/0! | BI30: =(BH30-BG30)/BG30 -> #DIV/0! | BL30: =(BK30-BJ30)/BJ30 -> #DIV/0! | BM30: =BJ30/BG30 -> #DIV/0! | BN30: =BK30/BH30 -> #DIV/0! | BO30: =BN30-BM30 -> #DIV/0! | BS30: =(BR30-BQ30)/BQ30 -> #DIV/0!
D31: 7 | E31: Wednesday | G31: 206303.95 | H31: =G31/G$56 -> 0.025640067 | I31: =G$15*H31 -> 223068.58 | J31: Wednesday | K31: =LS_RPRO!B12+MANUAL!B12+OUTSALE!B12 -> 116543.95 | L31: =K31-I31 -> -106524.63 | M31: =K31/G15 -> 0.013395856 | N31: =N30+L31 -> -346576.46 | P31: 575 | Q31: =LS_RPRO!C12+MANUAL!C12+OUTSALE!C12 -> 966.3 | R31: =(Q31-P31)/P31 -> 0.68052174 | V31: =(U31-T31)/T31 -> #DIV/0! | W31: =U31*25% -> 0 | Y31: =K31-U31 -> 116543.95 | Z31: =(Y31-X31)/X31 -> #DIV/0! | AA31: =Y31*30% -> 34963.185 | AB31: =W31+AA31 -> 34963.185 | AC31: =AB31/$M$15 -> #DIV/0! | AE31: 135150.4 | AF31: =LS_RPRO!O12+MANUAL!M12+OUTSALE!M12 -> 81910.4 | AG31: =(AF31-AE31)/AE31 -> -0.3939315 | AI31: 516 | AJ31: =LS_RPRO!M12 -> 316 | AK31: =AJ31/AI31-1 -> -0.3875969 | AL31: 71 | AM31: =LS_RPRO!H12+MANUAL!H12+OUTSALE!H12 -> 50 | AN31: =AM31/AL31-1 -> -0.29577465 | AO31: =AL31/AI31 -> 0.1375969 | AP31: =AM31/AJ31 -> 0.15822785 | AQ31: =AP31-AO31 -> 0.020630949 | AS31: 0 | AT31: =LS_RPRO!K12 -> 0 | AU31: =(AT31-AS31)/AS31 -> #DIV/0! | AV31: 5 | AW31: =LS_RPRO!L12 -> 0 | AX31: =(AW31-AV31)/AV31 -> -1 | AY31: =AS31+AV31 -> 5 | AZ31: =AT31+AW31 -> 0 | BA31: =(AZ31-AY31)/AY31 -> -1 | BD31: 0 | BE31: =(BD31-BC31)/BC31 -> #DIV/0! | BI31: =(BH31-BG31)/BG31 -> #DIV/0! | BL31: =(BK31-BJ31)/BJ31 -> #DIV/0! | BM31: =BJ31/BG31 -> #DIV/0! | BN31: =BK31/BH31 -> #DIV/0! | BO31: =BN31-BM31 -> #DIV/0! | BS31: =(BR31-BQ31)/BQ31 -> #DIV/0!
D32: 8 | E32: Thursday | G32: 169083.9 | H32: =G32/G$56 -> 0.021014248 | I32: =G$15*H32 -> 182823.96 | J32: Thursday | K32: =LS_RPRO!B13+MANUAL!B13+OUTSALE!B13 -> 146954.5 | L32: =K32-I32 -> -35869.461 | M32: =K32/G15 -> 0.016891322 | N32: =N31+L32 -> -382445.92 | P32: 135.75 | Q32: =LS_RPRO!C13+MANUAL!C13+OUTSALE!C13 -> 1268.25 | R32: =(Q32-P32)/P32 -> 8.3425414 | V32: =(U32-T32)/T32 -> #DIV/0! | W32: =U32*25% -> 0 | Y32: =K32-U32 -> 146954.5 | Z32: =(Y32-X32)/X32 -> #DIV/0! | AA32: =Y32*30% -> 44086.35 | AB32: =W32+AA32 -> 44086.35 | AC32: =AB32/$M$15 -> #DIV/0! | AE32: 84825.25 | AF32: =LS_RPRO!O13+MANUAL!M13+OUTSALE!M13 -> 120065.25 | AG32: =(AF32-AE32)/AE32 -> 0.41544234 | AI32: 554 | AJ32: =LS_RPRO!M13 -> 478 | AK32: =AJ32/AI32-1 -> -0.13718412 | AL32: 82 | AM32: =LS_RPRO!H13+MANUAL!H13+OUTSALE!H13 -> 67 | AN32: =AM32/AL32-1 -> -0.18292683 | AO32: =AL32/AI32 -> 0.14801444 | AP32: =AM32/AJ32 -> 0.14016736 | AQ32: =AP32-AO32 -> -0.0078470764 | AS32: 0 | AT32: =LS_RPRO!K13 -> 0 | AU32: =(AT32-AS32)/AS32 -> #DIV/0! | AV32: 0 | AW32: =LS_RPRO!L13 -> 0 | AX32: =(AW32-AV32)/AV32 -> #DIV/0! | AY32: =AS32+AV32 -> 0 | AZ32: =AT32+AW32 -> 0 | BA32: =(AZ32-AY32)/AY32 -> #DIV/0! | BD32: 0 | BE32: =(BD32-BC32)/BC32 -> #DIV/0! | BI32: =(BH32-BG32)/BG32 -> #DIV/0! | BL32: =(BK32-BJ32)/BJ32 -> #DIV/0! | BM32: =BJ32/BG32 -> #DIV/0! | BN32: =BK32/BH32 -> #DIV/0! | BO32: =BN32-BM32 -> #DIV/0! | BS32: =(BR32-BQ32)/BQ32 -> #DIV/0!
D33: 9 | E33: Friday | G33: 173091.25 | H33: =G33/G$56 -> 0.021512294 | I33: =G$15*H33 -> 187156.96 | J33: Friday | K33: =LS_RPRO!B14+MANUAL!B14+OUTSALE!B14 -> 198378.74 | L33: =K33-I33 -> 11221.785 | M33: =K33/G15 -> 0.022802154 | N33: =N32+L33 -> -371224.14 | P33: 0 | Q33: =LS_RPRO!C14+MANUAL!C14+OUTSALE!C14 -> 1337.3 | R33: =(Q33-P33)/P33 -> #DIV/0! | V33: =(U33-T33)/T33 -> #DIV/0! | W33: =U33*25% -> 0 | Y33: =K33-U33 -> 198378.74 | Z33: =(Y33-X33)/X33 -> #DIV/0! | AA33: =Y33*30% -> 59513.622 | AB33: =W33+AA33 -> 59513.622 | AC33: =AB33/$M$15 -> #DIV/0! | AE33: 158053.25 | AF33: =LS_RPRO!O14+MANUAL!M14+OUTSALE!M14 -> 169130.25 | AG33: =(AF33-AE33)/AE33 -> 0.070083975 | AI33: 623 | AJ33: =LS_RPRO!M14 -> 531 | AK33: =AJ33/AI33-1 -> -0.14767255 | AL33: 107 | AM33: =LS_RPRO!H14+MANUAL!H14+OUTSALE!H14 -> 81 | AN33: =AM33/AL33-1 -> -0.24299065 | AO33: =AL33/AI33 -> 0.1717496 | AP33: =AM33/AJ33 -> 0.15254237 | AQ33: =AP33-AO33 -> -0.019207226 | AS33: 3 | AT33: =LS_RPRO!K14 -> 1 | AU33: =(AT33-AS33)/AS33 -> -0.66666667 | AV33: 6 | AW33: =LS_RPRO!L14 -> 6 | AX33: =(AW33-AV33)/AV33 -> 0 | AY33: =AS33+AV33 -> 9 | AZ33: =AT33+AW33 -> 7 | BA33: =(AZ33-AY33)/AY33 -> -0.22222222 | BD33: 0 | BE33: =(BD33-BC33)/BC33 -> #DIV/0! | BI33: =(BH33-BG33)/BG33 -> #DIV/0! | BL33: =(BK33-BJ33)/BJ33 -> #DIV/0! | BM33: =BJ33/BG33 -> #DIV/0! | BN33: =BK33/BH33 -> #DIV/0! | BO33: =BN33-BM33 -> #DIV/0! | BS33: =(BR33-BQ33)/BQ33 -> #DIV/0!
D34: 10 | E34: Saturday | G34: 197428.25 | H34: =G34/G$56 -> 0.024536968 | I34: =G$15*H34 -> 213471.62 | J34: Saturday | K34: =LS_RPRO!B15+MANUAL!B15+OUTSALE!B15 -> 316237.04 | L34: =K34-I34 -> 102765.42 | M34: =K34/G15 -> 0.036349085 | N34: =N33+L34 -> -268458.72 | P34: 131.25 | Q34: =LS_RPRO!C15+MANUAL!C15+OUTSALE!C15 -> 3966.11 | R34: =(Q34-P34)/P34 -> 29.217981 | V34: =(U34-T34)/T34 -> #DIV/0! | W34: =U34*25% -> 0 | Y34: =K34-U34 -> 316237.04 | Z34: =(Y34-X34)/X34 -> #DIV/0! | AA34: =Y34*30% -> 94871.112 | AB34: =W34+AA34 -> 94871.112 | AC34: =AB34/$M$15 -> #DIV/0! | AE34: 265334.25 | AF34: =LS_RPRO!O15+MANUAL!M15+OUTSALE!M15 -> 246123.73 | AG34: =(AF34-AE34)/AE34 -> -0.072401207 | AI34: 680 | AJ34: =LS_RPRO!M15 -> 887 | AK34: =AJ34/AI34-1 -> 0.30441176 | AL34: 163 | AM34: =LS_RPRO!H15+MANUAL!H15+OUTSALE!H15 -> 142 | AN34: =AM34/AL34-1 -> -0.12883436 | AO34: =AL34/AI34 -> 0.23970588 | AP34: =AM34/AJ34 -> 0.16009019 | AQ34: =AP34-AO34 -> -0.079615691 | AS34: 2 | AT34: =LS_RPRO!K15 -> 5 | AU34: =(AT34-AS34)/AS34 -> 1.5 | AV34: 3 | AW34: =LS_RPRO!L15 -> 4 | AX34: =(AW34-AV34)/AV34 -> 0.33333333 | AY34: =AS34+AV34 -> 5 | AZ34: =AT34+AW34 -> 9 | BA34: =(AZ34-AY34)/AY34 -> 0.8 | BD34: 0 | BE34: =(BD34-BC34)/BC34 -> #DIV/0! | BI34: =(BH34-BG34)/BG34 -> #DIV/0! | BL34: =(BK34-BJ34)/BJ34 -> #DIV/0! | BM34: =BJ34/BG34 -> #DIV/0! | BN34: =BK34/BH34 -> #DIV/0! | BO34: =BN34-BM34 -> #DIV/0! | BS34: =(BR34-BQ34)/BQ34 -> #DIV/0!
D35: 11 | E35: Sunday | G35: 401911.4 | H35: =G35/G$56 -> 0.04995074 | I35: =G$15*H35 -> 434571.44 | J35: Sunday | K35: =LS_RPRO!B16+MANUAL!B16+OUTSALE!B16 -> 315334.4 | L35: =K35-I35 -> -119237.04 | M35: =K35/G15 -> 0.036245333 | N35: =N34+L35 -> -387695.76 | P35: 1287.83 | Q35: =LS_RPRO!C16+MANUAL!C16+OUTSALE!C16 -> 3289.55 | R35: =(Q35-P35)/P35 -> 1.5543356 | V35: =(U35-T35)/T35 -> #DIV/0! | W35: =U35*25% -> 0 | Y35: =K35-U35 -> 315334.4 | Z35: =(Y35-X35)/X35 -> #DIV/0! | AA35: =Y35*30% -> 94600.32 | AB35: =W35+AA35 -> 94600.32 | AC35: =AB35/$M$15 -> #DIV/0! | AE35: 454749.6 | AF35: =LS_RPRO!O16+MANUAL!M16+OUTSALE!M16 -> 263154.2 | AG35: =(AF35-AE35)/AE35 -> -0.42132066 | AI35: 711 | AJ35: =LS_RPRO!M16 -> 595 | AK35: =AJ35/AI35-1 -> -0.16315049 | AL35: 178 | AM35: =LS_RPRO!H16+MANUAL!H16+OUTSALE!H16 -> 133 | AN35: =AM35/AL35-1 -> -0.25280899 | AO35: =AL35/AI35 -> 0.25035162 | AP35: =AM35/AJ35 -> 0.22352941 | AQ35: =AP35-AO35 -> -0.026822206 | AS35: 2 | AT35: =LS_RPRO!K16 -> 0 | AU35: =(AT35-AS35)/AS35 -> -1 | AV35: 13 | AW35: =LS_RPRO!L16 -> 0 | AX35: =(AW35-AV35)/AV35 -> -1 | AY35: =AS35+AV35 -> 15 | AZ35: =AT35+AW35 -> 0 | BA35: =(AZ35-AY35)/AY35 -> -1 | BD35: 0 | BE35: =(BD35-BC35)/BC35 -> #DIV/0! | BI35: =(BH35-BG35)/BG35 -> #DIV/0! | BL35: =(BK35-BJ35)/BJ35 -> #DIV/0! | BM35: =BJ35/BG35 -> #DIV/0! | BN35: =BK35/BH35 -> #DIV/0! | BO35: =BN35-BM35 -> #DIV/0! | BS35: =(BR35-BQ35)/BQ35 -> #DIV/0!
D36: 12 | E36: Monday | G36: 548017.05 | H36: =G36/G$56 -> 0.068109184 | I36: =G$15*H36 -> 592549.9 | J36: Monday | K36: =LS_RPRO!B17+MANUAL!B17+OUTSALE!B17 -> 158110 | L36: =K36-I36 -> -434439.9 | M36: =K36/G15 -> 0.018173563 | N36: =N35+L36 -> -822135.66 | P36: 33.5 | Q36: =LS_RPRO!C17+MANUAL!C17+OUTSALE!C17 -> 658.3 | R36: =(Q36-P36)/P36 -> 18.650746 | V36: =(U36-T36)/T36 -> #DIV/0! | W36: =U36*25% -> 0 | Y36: =K36-U36 -> 158110 | Z36: =(Y36-X36)/X36 -> #DIV/0! | AA36: =Y36*30% -> 47433 | AB36: =W36+AA36 -> 47433 | AC36: =AB36/$M$15 -> #DIV/0! | AE36: 122262.5 | AF36: =LS_RPRO!O17+MANUAL!M17+OUTSALE!M17 -> 119603.7 | AG36: =(AF36-AE36)/AE36 -> -0.021746652 | AI36: 605 | AJ36: =LS_RPRO!M17 -> 336 | AK36: =AJ36/AI36-1 -> -0.4446281 | AL36: 77 | AM36: =LS_RPRO!H17+MANUAL!H17+OUTSALE!H17 -> 24 | AN36: =AM36/AL36-1 -> -0.68831169 | AO36: =AL36/AI36 -> 0.12727273 | AP36: =AM36/AJ36 -> 0.071428571 | AQ36: =AP36-AO36 -> -0.055844156 | AS36: 2 | AT36: =LS_RPRO!K17 -> 0 | AU36: =(AT36-AS36)/AS36 -> -1 | AV36: 2 | AW36: =LS_RPRO!L17 -> 2 | AX36: =(AW36-AV36)/AV36 -> 0 | AY36: =AS36+AV36 -> 4 | AZ36: =AT36+AW36 -> 2 | BA36: =(AZ36-AY36)/AY36 -> -0.5 | BD36: 0 | BE36: =(BD36-BC36)/BC36 -> #DIV/0! | BI36: =(BH36-BG36)/BG36 -> #DIV/0! | BL36: =(BK36-BJ36)/BJ36 -> #DIV/0! | BM36: =BJ36/BG36 -> #DIV/0! | BN36: =BK36/BH36 -> #DIV/0! | BO36: =BN36-BM36 -> #DIV/0! | BS36: =(BR36-BQ36)/BQ36 -> #DIV/0!
D37: 13 | E37: Tuesday | G37: 162285.5 | H37: =G37/G$56 -> 0.020169323 | I37: =G$15*H37 -> 175473.11 | J37: Tuesday | K37: =LS_RPRO!B18+MANUAL!B18+OUTSALE!B18 -> 0 | L37: =K37-I37 -> -175473.11 | M37: =K37/G15 -> 0 | N37: =N36+L37 -> -997608.77 | P37: 479.5 | Q37: =LS_RPRO!C18+MANUAL!C18+OUTSALE!C18 -> 0 | R37: =(Q37-P37)/P37 -> -1 | V37: =(U37-T37)/T37 -> #DIV/0! | W37: =U37*25% -> 0 | Y37: =K37-U37 -> 0 | Z37: =(Y37-X37)/X37 -> #DIV/0! | AA37: =Y37*30% -> 0 | AB37: =W37+AA37 -> 0 | AC37: =AB37/$M$15 -> #DIV/0! | AE37: 129005.5 | AF37: =LS_RPRO!O18+MANUAL!M18+OUTSALE!M18 -> 0 | AG37: =(AF37-AE37)/AE37 -> -1 | AI37: 408 | AJ37: =LS_RPRO!M18 -> 0 | AK37: =AJ37/AI37-1 -> -1 | AL37: 99 | AM37: =LS_RPRO!H18+MANUAL!H18+OUTSALE!H18 -> 0 | AN37: =AM37/AL37-1 -> -1 | AO37: =AL37/AI37 -> 0.24264706 | AP37: =AM37/AJ37 -> #DIV/0! | AQ37: =AP37-AO37 -> #DIV/0! | AS37: 2 | AT37: =LS_RPRO!K18 -> 0 | AU37: =(AT37-AS37)/AS37 -> -1 | AV37: 1 | AW37: =LS_RPRO!L18 -> 0 | AX37: =(AW37-AV37)/AV37 -> -1 | AY37: =AS37+AV37 -> 3 | AZ37: =AT37+AW37 -> 0 | BA37: =(AZ37-AY37)/AY37 -> -1 | BD37: 0 | BE37: =(BD37-BC37)/BC37 -> #DIV/0! | BI37: =(BH37-BG37)/BG37 -> #DIV/0! | BL37: =(BK37-BJ37)/BJ37 -> #DIV/0! | BM37: =BJ37/BG37 -> #DIV/0! | BN37: =BK37/BH37 -> #DIV/0! | BO37: =BN37-BM37 -> #DIV/0! | BS37: =(BR37-BQ37)/BQ37 -> #DIV/0!
D38: 14 | E38: Wednesday | G38: 196776 | H38: =G38/G$56 -> 0.024455905 | I38: =G$15*H38 -> 212766.37 | J38: Wednesday | K38: =LS_RPRO!B19+MANUAL!B19+OUTSALE!B19 -> 0 | L38: =K38-I38 -> -212766.37 | M38: =K38/G15 -> 0 | N38: =N37+L38 -> -1210375.1 | P38: 4550.89 | Q38: =LS_RPRO!C19+MANUAL!C19+OUTSALE!C19 -> 0 | R38: =(Q38-P38)/P38 -> -1 | V38: =(U38-T38)/T38 -> #DIV/0! | W38: =U38*25% -> 0 | Y38: =K38-U38 -> 0 | Z38: =(Y38-X38)/X38 -> #DIV/0! | AA38: =Y38*30% -> 0 | AB38: =W38+AA38 -> 0 | AC38: =AB38/$M$15 -> #DIV/0! | AE38: 149294.51 | AF38: =LS_RPRO!O19+MANUAL!M19+OUTSALE!M19 -> 0 | AG38: =(AF38-AE38)/AE38 -> -1 | AI38: 556 | AJ38: =LS_RPRO!M19 -> 0 | AK38: =AJ38/AI38-1 -> -1 | AL38: 48 | AM38: =LS_RPRO!H19+MANUAL!H19+OUTSALE!H19 -> 0 | AN38: =AM38/AL38-1 -> -1 | AO38: =AL38/AI38 -> 0.086330935 | AP38: =AM38/AJ38 -> #DIV/0! | AQ38: =AP38-AO38 -> #DIV/0! | AS38: 0 | AT38: =LS_RPRO!K19 -> 0 | AU38: =(AT38-AS38)/AS38 -> #DIV/0! | AV38: 4 | AW38: =LS_RPRO!L19 -> 0 | AX38: =(AW38-AV38)/AV38 -> -1 | AY38: =AS38+AV38 -> 4 | AZ38: =AT38+AW38 -> 0 | BA38: =(AZ38-AY38)/AY38 -> -1 | BD38: 0 | BE38: =(BD38-BC38)/BC38 -> #DIV/0! | BI38: =(BH38-BG38)/BG38 -> #DIV/0! | BL38: =(BK38-BJ38)/BJ38 -> #DIV/0! | BM38: =BJ38/BG38 -> #DIV/0! | BN38: =BK38/BH38 -> #DIV/0! | BO38: =BN38-BM38 -> #DIV/0! | BS38: =(BR38-BQ38)/BQ38 -> #DIV/0!
D39: 15 | E39: Thursday | G39: 217199.4 | H39: =G39/G$56 -> 0.026994185 | I39: =G$15*H39 -> 234849.41 | J39: Thursday | K39: =LS_RPRO!B20+MANUAL!B20+OUTSALE!B20 -> 0 | L39: =K39-I39 -> -234849.41 | M39: =K39/G15 -> 0 | N39: =N38+L39 -> -1445224.6 | P39: 0 | Q39: =LS_RPRO!C20+MANUAL!C20+OUTSALE!C20 -> 0 | R39: =(Q39-P39)/P39 -> #DIV/0! | V39: =(U39-T39)/T39 -> #DIV/0! | W39: =U39*25% -> 0 | Y39: =K39-U39 -> 0 | Z39: =(Y39-X39)/X39 -> #DIV/0! | AA39: =Y39*30% -> 0 | AB39: =W39+AA39 -> 0 | AC39: =AB39/$M$15 -> #DIV/0! | AE39: 220023.25 | AF39: =LS_RPRO!O20+MANUAL!M20+OUTSALE!M20 -> 0 | AG39: =(AF39-AE39)/AE39 -> -1 | AI39: 650 | AJ39: =LS_RPRO!M20 -> 0 | AK39: =AJ39/AI39-1 -> -1 | AL39: 121 | AM39: =LS_RPRO!H20+MANUAL!H20+OUTSALE!H20 -> 0 | AN39: =AM39/AL39-1 -> -1 | AO39: =AL39/AI39 -> 0.18615385 | AP39: =AM39/AJ39 -> #DIV/0! | AQ39: =AP39-AO39 -> #DIV/0! | AS39: 0 | AT39: =LS_RPRO!K20 -> 0 | AU39: =(AT39-AS39)/AS39 -> #DIV/0! | AV39: 0 | AW39: =LS_RPRO!L20 -> 0 | AX39: =(AW39-AV39)/AV39 -> #DIV/0! | AY39: =AS39+AV39 -> 0 | AZ39: =AT39+AW39 -> 0 | BA39: =(AZ39-AY39)/AY39 -> #DIV/0! | BD39: 0 | BE39: =(BD39-BC39)/BC39 -> #DIV/0! | BI39: =(BH39-BG39)/BG39 -> #DIV/0! | BL39: =(BK39-BJ39)/BJ39 -> #DIV/0! | BM39: =BJ39/BG39 -> #DIV/0! | BN39: =BK39/BH39 -> #DIV/0! | BO39: =BN39-BM39 -> #DIV/0! | BS39: =(BR39-BQ39)/BQ39 -> #DIV/0!
D40: 16 | E40: Friday | G40: 258189.75 | H40: =G40/G$56 -> 0.032088588 | I40: =G$15*H40 -> 279170.71 | J40: Friday | K40: =LS_RPRO!B23+MANUAL!B23+OUTSALE!B23 -> 0 | L40: =K40-I40 -> -279170.71 | M40: =K40/G15 -> 0 | N40: =N39+L40 -> -1724395.3 | P40: 4249.56 | Q40: =LS_RPRO!C23+MANUAL!C23+OUTSALE!C23 -> 0 | R40: =(Q40-P40)/P40 -> -1 | V40: =(U40-T40)/T40 -> #DIV/0! | W40: =U40*25% -> 0 | Y40: =K40-U40 -> 0 | Z40: =(Y40-X40)/X40 -> #DIV/0! | AA40: =Y40*30% -> 0 | AB40: =W40+AA40 -> 0 | AC40: =AB40/$M$15 -> #DIV/0! | AE40: 295936.09 | AF40: =LS_RPRO!O23+MANUAL!M23+OUTSALE!M23 -> 0 | AG40: =(AF40-AE40)/AE40 -> -1 | AI40: 716 | AJ40: =LS_RPRO!M23 -> 0 | AK40: =AJ40/AI40-1 -> -1 | AL40: 160 | AM40: =MANUAL!H23+LS_RPRO!H23+OUTSALE!H23 -> 0 | AN40: =AM40/AL40-1 -> -1 | AO40: =AL40/AI40 -> 0.22346369 | AP40: =AM40/AJ40 -> #DIV/0! | AQ40: =AP40-AO40 -> #DIV/0! | AS40: 1 | AT40: =LS_RPRO!K23 -> 0 | AU40: =(AT40-AS40)/AS40 -> -1 | AV40: 5 | AW40: =LS_RPRO!L23 -> 0 | AX40: =(AW40-AV40)/AV40 -> -1 | AY40: =AS40+AV40 -> 6 | AZ40: =AT40+AW40 -> 0 | BA40: =(AZ40-AY40)/AY40 -> -1 | BD40: 0 | BE40: =(BD40-BC40)/BC40 -> #DIV/0! | BI40: =(BH40-BG40)/BG40 -> #DIV/0! | BL40: =(BK40-BJ40)/BJ40 -> #DIV/0! | BM40: =BJ40/BG40 -> #DIV/0! | BN40: =BK40/BH40 -> #DIV/0! | BO40: =BN40-BM40 -> #DIV/0! | BS40: =(BR40-BQ40)/BQ40 -> #DIV/0!
D41: 17 | E41: Saturday | G41: 378674.3 | H41: =G41/G$56 -> 0.047062765 | I41: =G$15*H41 -> 409446.05 | J41: Saturday | K41: =LS_RPRO!B24+MANUAL!B24+OUTSALE!B24 -> 0 | L41: =K41-I41 -> -409446.05 | M41: =K41/G15 -> 0 | N41: =N40+L41 -> -2133841.3 | P41: 3515.08 | Q41: =LS_RPRO!C24+MANUAL!C24+OUTSALE!C24 -> 0 | R41: =(Q41-P41)/P41 -> -1 | V41: =(U41-T41)/T41 -> #DIV/0! | W41: =U41*25% -> 0 | Y41: =K41-U41 -> 0 | Z41: =(Y41-X41)/X41 -> #DIV/0! | AA41: =Y41*30% -> 0 | AB41: =W41+AA41 -> 0 | AC41: =AB41/$M$15 -> #DIV/0! | AE41: 334574.3 | AF41: =LS_RPRO!O24+MANUAL!M24+OUTSALE!M24 -> 0 | AG41: =(AF41-AE41)/AE41 -> -1 | AI41: 981 | AJ41: =LS_RPRO!M24 -> 0 | AK41: =AJ41/AI41-1 -> -1 | AL41: 202 | AM41: =MANUAL!H24+LS_RPRO!H24+OUTSALE!H24 -> 0 | AN41: =AM41/AL41-1 -> -1 | AO41: =AL41/AI41 -> 0.20591233 | AP41: =AM41/AJ41 -> #DIV/0! | AQ41: =AP41-AO41 -> #DIV/0! | AS41: 1 | AT41: =LS_RPRO!K24 -> 0 | AU41: =(AT41-AS41)/AS41 -> -1 | AV41: 6 | AW41: =LS_RPRO!L24 -> 0 | AX41: =(AW41-AV41)/AV41 -> -1 | AY41: =AS41+AV41 -> 7 | AZ41: =AT41+AW41 -> 0 | BA41: =(AZ41-AY41)/AY41 -> -1 | BD41: 0 | BE41: =(BD41-BC41)/BC41 -> #DIV/0! | BI41: =(BH41-BG41)/BG41 -> #DIV/0! | BL41: =(BK41-BJ41)/BJ41 -> #DIV/0! | BM41: =BJ41/BG41 -> #DIV/0! | BN41: =BK41/BH41 -> #DIV/0! | BO41: =BN41-BM41 -> #DIV/0! | BS41: =(BR41-BQ41)/BQ41 -> #DIV/0!
D42: 18 | E42: Sunday | G42: 420168.9 | H42: =G42/G$56 -> 0.052219837 | I42: =G$15*H42 -> 454312.58 | J42: Sunday | K42: =LS_RPRO!B25+MANUAL!B25+OUTSALE!B25 -> 0 | L42: =K42-I42 -> -454312.58 | M42: =K42/G15 -> 0 | N42: =N41+L42 -> -2588153.9 | P42: 3450.43 | Q42: =LS_RPRO!C25+MANUAL!C25+OUTSALE!C25 -> 0 | R42: =(Q42-P42)/P42 -> -1 | V42: =(U42-T42)/T42 -> #DIV/0! | W42: =U42*25% -> 0 | Y42: =K42-U42 -> 0 | Z42: =(Y42-X42)/X42 -> #DIV/0! | AA42: =Y42*30% -> 0 | AB42: =W42+AA42 -> 0 | AC42: =AB42/$M$15 -> #DIV/0! | AE42: 304557.84 | AF42: =LS_RPRO!O25+MANUAL!M25+OUTSALE!M25 -> 0 | AG42: =(AF42-AE42)/AE42 -> -1 | AI42: 1020 | AJ42: =LS_RPRO!M25 -> 0 | AK42: =AJ42/AI42-1 -> -1 | AL42: 201 | AM42: =MANUAL!H25+LS_RPRO!H25+OUTSALE!H25 -> 0 | AN42: =AM42/AL42-1 -> -1 | AO42: =AL42/AI42 -> 0.19705882 | AP42: =AM42/AJ42 -> #DIV/0! | AQ42: =AP42-AO42 -> #DIV/0! | AS42: 0 | AT42: =LS_RPRO!K25 -> 0 | AU42: =(AT42-AS42)/AS42 -> #DIV/0! | AV42: 3 | AW42: =LS_RPRO!L25 -> 0 | AX42: =(AW42-AV42)/AV42 -> -1 | AY42: =AS42+AV42 -> 3 | AZ42: =AT42+AW42 -> 0 | BA42: =(AZ42-AY42)/AY42 -> -1 | BD42: 0 | BE42: =(BD42-BC42)/BC42 -> #DIV/0! | BI42: =(BH42-BG42)/BG42 -> #DIV/0! | BL42: =(BK42-BJ42)/BJ42 -> #DIV/0! | BM42: =BJ42/BG42 -> #DIV/0! | BN42: =BK42/BH42 -> #DIV/0! | BO42: =BN42-BM42 -> #DIV/0! | BS42: =(BR42-BQ42)/BQ42 -> #DIV/0!
D43: 19 | E43: Monday | G43: 420278.56 | H43: =G43/G$56 -> 0.052233465 | I43: =G$15*H43 -> 454431.15 | J43: Monday | K43: =LS_RPRO!B26+MANUAL!B26+OUTSALE!B26 -> 0 | L43: =K43-I43 -> -454431.15 | M43: =K43/G15 -> 0 | N43: =N42+L43 -> -3042585 | P43: 0 | Q43: =LS_RPRO!C26+MANUAL!C26+OUTSALE!C26 -> 0 | R43: =(Q43-P43)/P43 -> #DIV/0! | V43: =(U43-T43)/T43 -> #DIV/0! | W43: =U43*25% -> 0 | Y43: =K43-U43 -> 0 | Z43: =(Y43-X43)/X43 -> #DIV/0! | AA43: =Y43*30% -> 0 | AB43: =W43+AA43 -> 0 | AC43: =AB43/$M$15 -> #DIV/0! | AE43: 150434 | AF43: =LS_RPRO!O26+MANUAL!M26+OUTSALE!M26 -> 0 | AG43: =(AF43-AE43)/AE43 -> -1 | AI43: 464 | AJ43: =LS_RPRO!M26 -> 0 | AK43: =AJ43/AI43-1 -> -1 | AL43: 68 | AM43: =MANUAL!H26+LS_RPRO!H26+OUTSALE!H26 -> 0 | AN43: =AM43/AL43-1 -> -1 | AO43: =AL43/AI43 -> 0.14655172 | AP43: =AM43/AJ43 -> #DIV/0! | AQ43: =AP43-AO43 -> #DIV/0! | AS43: 3 | AT43: =LS_RPRO!K26 -> 0 | AU43: =(AT43-AS43)/AS43 -> -1 | AV43: 0 | AW43: =LS_RPRO!L26 -> 0 | AX43: =(AW43-AV43)/AV43 -> #DIV/0! | AY43: =AS43+AV43 -> 3 | AZ43: =AT43+AW43 -> 0 | BA43: =(AZ43-AY43)/AY43 -> -1 | BD43: 0 | BE43: =(BD43-BC43)/BC43 -> #DIV/0! | BI43: =(BH43-BG43)/BG43 -> #DIV/0! | BL43: =(BK43-BJ43)/BJ43 -> #DIV/0! | BM43: =BJ43/BG43 -> #DIV/0! | BN43: =BK43/BH43 -> #DIV/0! | BO43: =BN43-BM43 -> #DIV/0! | BS43: =(BR43-BQ43)/BQ43 -> #DIV/0!
D44: 20 | E44: Tuesday | G44: 179352.45 | H44: =G44/G$56 -> 0.022290454 | I44: =G$15*H44 -> 193926.95 | J44: Tuesday | K44: =LS_RPRO!B27+MANUAL!B27+OUTSALE!B27 -> 0 | L44: =K44-I44 -> -193926.95 | M44: =K44/G15 -> 0 | N44: =N43+L44 -> -3236512 | P44: 2300 | Q44: =LS_RPRO!C27+MANUAL!C27+OUTSALE!C27 -> 0 | R44: =(Q44-P44)/P44 -> -1 | V44: =(U44-T44)/T44 -> #DIV/0! | W44: =U44*25% -> 0 | Y44: =K44-U44 -> 0 | Z44: =(Y44-X44)/X44 -> #DIV/0! | AA44: =Y44*30% -> 0 | AB44: =W44+AA44 -> 0 | AC44: =AB44/$M$15 -> #DIV/0! | AE44: 138094.6 | AF44: =LS_RPRO!O27+MANUAL!M27+OUTSALE!M27 -> 0 | AG44: =(AF44-AE44)/AE44 -> -1 | AI44: 307 | AJ44: =LS_RPRO!M27 -> 0 | AK44: =AJ44/AI44-1 -> -1 | AL44: 75 | AM44: =MANUAL!H27+LS_RPRO!H27+OUTSALE!H27 -> 0 | AN44: =AM44/AL44-1 -> -1 | AO44: =AL44/AI44 -> 0.24429967 | AP44: =AM44/AJ44 -> #DIV/0! | AQ44: =AP44-AO44 -> #DIV/0! | AS44: 1 | AT44: =LS_RPRO!K27 -> 0 | AU44: =(AT44-AS44)/AS44 -> -1 | AV44: 2 | AW44: =LS_RPRO!L27 -> 0 | AX44: =(AW44-AV44)/AV44 -> -1 | AY44: =AS44+AV44 -> 3 | AZ44: =AT44+AW44 -> 0 | BA44: =(AZ44-AY44)/AY44 -> -1 | BD44: 0 | BE44: =(BD44-BC44)/BC44 -> #DIV/0! | BI44: =(BH44-BG44)/BG44 -> #DIV/0! | BL44: =(BK44-BJ44)/BJ44 -> #DIV/0! | BM44: =BJ44/BG44 -> #DIV/0! | BN44: =BK44/BH44 -> #DIV/0! | BO44: =BN44-BM44 -> #DIV/0! | BS44: =(BR44-BQ44)/BQ44 -> #DIV/0!
D45: 21 | E45: Wednesday | G45: 171150.6 | H45: =G45/G$56 -> 0.021271104 | I45: =G$15*H45 -> 185058.6 | J45: Wednesday | K45: =LS_RPRO!B28+MANUAL!B28+OUTSALE!B28 -> 0 | L45: =K45-I45 -> -185058.6 | M45: =K45/G15 -> 0 | N45: =N44+L45 -> -3421570.6 | P45: 90 | Q45: =LS_RPRO!C28+MANUAL!C28+OUTSALE!C28 -> 0 | R45: =(Q45-P45)/P45 -> -1 | V45: =(U45-T45)/T45 -> #DIV/0! | W45: =U45*25% -> 0 | Y45: =K45-U45 -> 0 | Z45: =(Y45-X45)/X45 -> #DIV/0! | AA45: =Y45*30% -> 0 | AB45: =W45+AA45 -> 0 | AC45: =AB45/$M$15 -> #DIV/0! | AE45: 113559 | AF45: =LS_RPRO!O28+MANUAL!M28+OUTSALE!M28 -> 0 | AG45: =(AF45-AE45)/AE45 -> -1 | AI45: 298 | AJ45: =LS_RPRO!M28 -> 0 | AK45: =AJ45/AI45-1 -> -1 | AL45: 76 | AM45: =MANUAL!H28+LS_RPRO!H28+OUTSALE!H28 -> 0 | AN45: =AM45/AL45-1 -> -1 | AO45: =AL45/AI45 -> 0.25503356 | AP45: =AM45/AJ45 -> #DIV/0! | AQ45: =AP45-AO45 -> #DIV/0! | AS45: 0 | AT45: =LS_RPRO!K28 -> 0 | AU45: =(AT45-AS45)/AS45 -> #DIV/0! | AV45: 5 | AW45: =LS_RPRO!L28 -> 0 | AX45: =(AW45-AV45)/AV45 -> -1 | AY45: =AS45+AV45 -> 5 | AZ45: =AT45+AW45 -> 0 | BA45: =(AZ45-AY45)/AY45 -> -1 | BD45: 0 | BE45: =(BD45-BC45)/BC45 -> #DIV/0! | BI45: =(BH45-BG45)/BG45 -> #DIV/0! | BL45: =(BK45-BJ45)/BJ45 -> #DIV/0! | BM45: =BJ45/BG45 -> #DIV/0! | BN45: =BK45/BH45 -> #DIV/0! | BO45: =BN45-BM45 -> #DIV/0! | BS45: =(BR45-BQ45)/BQ45 -> #DIV/0!
D46: 22 | E46: Thursday | G46: 152381.75 | H46: =G46/G$56 -> 0.018938456 | I46: =G$15*H46 -> 164764.56 | J46: Thursday | K46: =LS_RPRO!B29+MANUAL!B29+OUTSALE!B29 -> 0 | L46: =K46-I46 -> -164764.56 | M46: =K46/G15 -> 0 | N46: =N45+L46 -> -3586335.2 | P46: 639.12 | Q46: =LS_RPRO!C29+MANUAL!C29+OUTSALE!C29 -> 0 | R46: =(Q46-P46)/P46 -> -1 | V46: =(U46-T46)/T46 -> #DIV/0! | W46: =U46*25% -> 0 | Y46: =K46-U46 -> 0 | Z46: =(Y46-X46)/X46 -> #DIV/0! | AA46: =Y46*30% -> 0 | AB46: =W46+AA46 -> 0 | AC46: =AB46/$M$15 -> #DIV/0! | AE46: 156088.54 | AF46: =LS_RPRO!O29+MANUAL!M29+OUTSALE!M29 -> 0 | AG46: =(AF46-AE46)/AE46 -> -1 | AI46: 397 | AJ46: =LS_RPRO!M29 -> 0 | AK46: =AJ46/AI46-1 -> -1 | AL46: 104 | AM46: =MANUAL!H29+LS_RPRO!H29+OUTSALE!H29 -> 0 | AN46: =AM46/AL46-1 -> -1 | AO46: =AL46/AI46 -> 0.26196474 | AP46: =AM46/AJ46 -> #DIV/0! | AQ46: =AP46-AO46 -> #DIV/0! | AS46: 0 | AT46: =LS_RPRO!K29 -> 0 | AU46: =(AT46-AS46)/AS46 -> #DIV/0! | AV46: 0 | AW46: =LS_RPRO!L29 -> 0 | AX46: =(AW46-AV46)/AV46 -> #DIV/0! | AY46: =AS46+AV46 -> 0 | AZ46: =AT46+AW46 -> 0 | BA46: =(AZ46-AY46)/AY46 -> #DIV/0! | BD46: 0 | BE46: =(BD46-BC46)/BC46 -> #DIV/0! | BI46: =(BH46-BG46)/BG46 -> #DIV/0! | BL46: =(BK46-BJ46)/BJ46 -> #DIV/0! | BM46: =BJ46/BG46 -> #DIV/0! | BN46: =BK46/BH46 -> #DIV/0! | BO46: =BN46-BM46 -> #DIV/0! | BS46: =(BR46-BQ46)/BQ46 -> #DIV/0!
D47: 23 | E47: Friday | G47: 242351.48 | H47: =G47/G$56 -> 0.03012016 | I47: =G$15*H47 -> 262045.4 | J47: Friday | K47: =LS_RPRO!B30+MANUAL!B30+OUTSALE!B30 -> 0 | L47: =K47-I47 -> -262045.4 | M47: =K47/G15 -> 0 | N47: =N46+L47 -> -3848380.6 | P47: 86.25 | Q47: =LS_RPRO!C30+MANUAL!C30+OUTSALE!C30 -> 0 | R47: =(Q47-P47)/P47 -> -1 | V47: =(U47-T47)/T47 -> #DIV/0! | W47: =U47*25% -> 0 | Y47: =K47-U47 -> 0 | Z47: =(Y47-X47)/X47 -> #DIV/0! | AA47: =Y47*30% -> 0 | AB47: =W47+AA47 -> 0 | AC47: =AB47/$M$15 -> #DIV/0! | AE47: 85931.45 | AF47: =LS_RPRO!O30+MANUAL!M30+OUTSALE!M30 -> 0 | AG47: =(AF47-AE47)/AE47 -> -1 | AI47: 402 | AJ47: =LS_RPRO!M30 -> 0 | AK47: =AJ47/AI47-1 -> -1 | AL47: 97 | AM47: =MANUAL!H30+LS_RPRO!H30+OUTSALE!H30 -> 0 | AN47: =AM47/AL47-1 -> -1 | AO47: =AL47/AI47 -> 0.24129353 | AP47: =AM47/AJ47 -> #DIV/0! | AQ47: =AP47-AO47 -> #DIV/0! | AS47: 4 | AT47: =LS_RPRO!K30 -> 0 | AU47: =(AT47-AS47)/AS47 -> -1 | AV47: 2 | AW47: =LS_RPRO!L30 -> 0 | AX47: =(AW47-AV47)/AV47 -> -1 | AY47: =AS47+AV47 -> 6 | AZ47: =AT47+AW47 -> 0 | BA47: =(AZ47-AY47)/AY47 -> -1 | BD47: 0 | BE47: =(BD47-BC47)/BC47 -> #DIV/0! | BI47: =(BH47-BG47)/BG47 -> #DIV/0! | BL47: =(BK47-BJ47)/BJ47 -> #DIV/0! | BM47: =BJ47/BG47 -> #DIV/0! | BN47: =BK47/BH47 -> #DIV/0! | BO47: =BN47-BM47 -> #DIV/0! | BS47: =(BR47-BQ47)/BQ47 -> #DIV/0!
D48: 24 | E48: Saturday | G48: 156071.95 | H48: =G48/G$56 -> 0.019397085 | I48: =G$15*H48 -> 168754.64 | J48: Saturday | K48: =LS_RPRO!B31+MANUAL!B31+OUTSALE!B31 -> 0 | L48: =K48-I48 -> -168754.64 | M48: =K48/G15 -> 0 | N48: =N47+L48 -> -4017135.2 | P48: 447.5 | Q48: =LS_RPRO!C31+MANUAL!C31+OUTSALE!C31 -> 0 | R48: =(Q48-P48)/P48 -> -1 | V48: =(U48-T48)/T48 -> #DIV/0! | W48: =U48*25% -> 0 | Y48: =K48-U48 -> 0 | Z48: =(Y48-X48)/X48 -> #DIV/0! | AA48: =Y48*30% -> 0 | AB48: =W48+AA48 -> 0 | AC48: =AB48/$M$15 -> #DIV/0! | AE48: 232305.8 | AF48: =LS_RPRO!O31+MANUAL!M31+OUTSALE!M31 -> 0 | AG48: =(AF48-AE48)/AE48 -> -1 | AI48: 638 | AJ48: =LS_RPRO!M31 -> 0 | AK48: =AJ48/AI48-1 -> -1 | AL48: 176 | AM48: =MANUAL!H31+LS_RPRO!H31+OUTSALE!H31 -> 0 | AN48: =AM48/AL48-1 -> -1 | AO48: =AL48/AI48 -> 0.27586207 | AP48: =AM48/AJ48 -> #DIV/0! | AQ48: =AP48-AO48 -> #DIV/0! | AS48: 1 | AT48: =LS_RPRO!K31 -> 0 | AU48: =(AT48-AS48)/AS48 -> -1 | AV48: 6 | AW48: =LS_RPRO!L31 -> 0 | AX48: =(AW48-AV48)/AV48 -> -1 | AY48: =AS48+AV48 -> 7 | AZ48: =AT48+AW48 -> 0 | BA48: =(AZ48-AY48)/AY48 -> -1 | BD48: 0 | BE48: =(BD48-BC48)/BC48 -> #DIV/0! | BI48: =(BH48-BG48)/BG48 -> #DIV/0! | BL48: =(BK48-BJ48)/BJ48 -> #DIV/0! | BM48: =BJ48/BG48 -> #DIV/0! | BN48: =BK48/BH48 -> #DIV/0! | BO48: =BN48-BM48 -> #DIV/0! | BS48: =(BR48-BQ48)/BQ48 -> #DIV/0!
D49: 25 | E49: Sunday | G49: 341333.8 | H49: =G49/G$56 -> 0.042421977 | I49: =G$15*H49 -> 369071.2 | J49: Sunday | K49: =LS_RPRO!B32+MANUAL!B32+OUTSALE!B32 -> 0 | L49: =K49-I49 -> -369071.2 | M49: =K49/G15 -> 0 | N49: =N48+L49 -> -4386206.4 | P49: 1043.48 | Q49: =LS_RPRO!C32+MANUAL!C32+OUTSALE!C32 -> 0 | R49: =(Q49-P49)/P49 -> -1 | V49: =(U49-T49)/T49 -> #DIV/0! | W49: =U49*25% -> 0 | Y49: =K49-U49 -> 0 | Z49: =(Y49-X49)/X49 -> #DIV/0! | AA49: =Y49*30% -> 0 | AB49: =W49+AA49 -> 0 | AC49: =AB49/$M$15 -> #DIV/0! | AE49: 310398.95 | AF49: =LS_RPRO!O32+MANUAL!M32+OUTSALE!M32 -> 0 | AG49: =(AF49-AE49)/AE49 -> -1 | AI49: 880 | AJ49: =LS_RPRO!M32 -> 0 | AK49: =AJ49/AI49-1 -> -1 | AL49: 157 | AM49: =MANUAL!H32+LS_RPRO!H32+OUTSALE!H32 -> 0 | AN49: =AM49/AL49-1 -> -1 | AO49: =AL49/AI49 -> 0.17840909 | AP49: =AM49/AJ49 -> #DIV/0! | AQ49: =AP49-AO49 -> #DIV/0! | AS49: 0 | AT49: =LS_RPRO!K32 -> 0 | AU49: =(AT49-AS49)/AS49 -> #DIV/0! | AV49: 0 | AW49: =LS_RPRO!L32 -> 0 | AX49: =(AW49-AV49)/AV49 -> #DIV/0! | AY49: =AS49+AV49 -> 0 | AZ49: =AT49+AW49 -> 0 | BA49: =(AZ49-AY49)/AY49 -> #DIV/0! | BD49: 0 | BE49: =(BD49-BC49)/BC49 -> #DIV/0! | BI49: =(BH49-BG49)/BG49 -> #DIV/0! | BL49: =(BK49-BJ49)/BJ49 -> #DIV/0! | BM49: =BJ49/BG49 -> #DIV/0! | BN49: =BK49/BH49 -> #DIV/0! | BO49: =BN49-BM49 -> #DIV/0! | BS49: =(BR49-BQ49)/BQ49 -> #DIV/0!
D50: 26 | E50: Monday | G50: 387732.12 | H50: =G50/G$56 -> 0.048188497 | I50: =G$15*H50 -> 419239.93 | J50: Monday | K50: =LS_RPRO!B33+MANUAL!B33+OUTSALE!B33 -> 0 | L50: =K50-I50 -> -419239.93 | M50: =K50/G15 -> 0 | N50: =N49+L50 -> -4805446.3 | P50: 168.75 | Q50: =LS_RPRO!C33+MANUAL!C33+OUTSALE!C33 -> 0 | R50: =(Q50-P50)/P50 -> -1 | V50: =(U50-T50)/T50 -> #DIV/0! | W50: =U50*25% -> 0 | Y50: =K50-U50 -> 0 | Z50: =(Y50-X50)/X50 -> #DIV/0! | AA50: =Y50*30% -> 0 | AB50: =W50+AA50 -> 0 | AC50: =AB50/$M$15 -> #DIV/0! | AE50: 90373.25 | AF50: =LS_RPRO!O33+MANUAL!M33+OUTSALE!M33 -> 0 | AG50: =(AF50-AE50)/AE50 -> -1 | AI50: 307 | AJ50: =LS_RPRO!M33 -> 0 | AK50: =AJ50/AI50-1 -> -1 | AL50: 83 | AM50: =MANUAL!H33+LS_RPRO!H33+OUTSALE!H33 -> 0 | AN50: =AM50/AL50-1 -> -1 | AO50: =AL50/AI50 -> 0.27035831 | AP50: =AM50/AJ50 -> #DIV/0! | AQ50: =AP50-AO50 -> #DIV/0! | AS50: 0 | AT50: =LS_RPRO!K33 -> 0 | AU50: =(AT50-AS50)/AS50 -> #DIV/0! | AV50: 3 | AW50: =LS_RPRO!L33 -> 0 | AX50: =(AW50-AV50)/AV50 -> -1 | AY50: =AS50+AV50 -> 3 | AZ50: =AT50+AW50 -> 0 | BA50: =(AZ50-AY50)/AY50 -> -1 | BD50: 0 | BE50: =(BD50-BC50)/BC50 -> #DIV/0! | BI50: =(BH50-BG50)/BG50 -> #DIV/0! | BL50: =(BK50-BJ50)/BJ50 -> #DIV/0! | BM50: =BJ50/BG50 -> #DIV/0! | BN50: =BK50/BH50 -> #DIV/0! | BO50: =BN50-BM50 -> #DIV/0! | BS50: =(BR50-BQ50)/BQ50 -> #DIV/0!
D51: 27 | E51: Tuesday | G51: 154971.75 | H51: =G51/G$56 -> 0.019260349 | I51: =G$15*H51 -> 167565.03 | J51: Tuesday | K51: =LS_RPRO!B34+MANUAL!B34+OUTSALE!B34 -> 0 | L51: =K51-I51 -> -167565.03 | M51: =K51/G15 -> 0 | N51: =N50+L51 -> -4973011.4 | P51: 3550.1 | Q51: =LS_RPRO!C34+MANUAL!C34+OUTSALE!C34 -> 0 | R51: =(Q51-P51)/P51 -> -1 | V51: =(U51-T51)/T51 -> #DIV/0! | W51: =U51*25% -> 0 | Y51: =K51-U51 -> 0 | Z51: =(Y51-X51)/X51 -> #DIV/0! | AA51: =Y51*30% -> 0 | AB51: =W51+AA51 -> 0 | AC51: =AB51/$M$15 -> #DIV/0! | AE51: 155842.5 | AF51: =LS_RPRO!O34+MANUAL!M34+OUTSALE!M34 -> 0 | AG51: =(AF51-AE51)/AE51 -> -1 | AI51: 381 | AJ51: =LS_RPRO!M34 -> 0 | AK51: =AJ51/AI51-1 -> -1 | AL51: 85 | AM51: =MANUAL!H34+LS_RPRO!H34+OUTSALE!H34 -> 0 | AN51: =AM51/AL51-1 -> -1 | AO51: =AL51/AI51 -> 0.22309711 | AP51: =AM51/AJ51 -> #DIV/0! | AQ51: =AP51-AO51 -> #DIV/0! | AS51: 0 | AT51: =LS_RPRO!K34 -> 0 | AU51: =(AT51-AS51)/AS51 -> #DIV/0! | AV51: 6 | AW51: =LS_RPRO!L34 -> 0 | AX51: =(AW51-AV51)/AV51 -> -1 | AY51: =AS51+AV51 -> 6 | AZ51: =AT51+AW51 -> 0 | BA51: =(AZ51-AY51)/AY51 -> -1 | BD51: 0 | BE51: =(BD51-BC51)/BC51 -> #DIV/0! | BI51: =(BH51-BG51)/BG51 -> #DIV/0! | BL51: =(BK51-BJ51)/BJ51 -> #DIV/0! | BM51: =BJ51/BG51 -> #DIV/0! | BN51: =BK51/BH51 -> #DIV/0! | BO51: =BN51-BM51 -> #DIV/0! | BS51: =(BR51-BQ51)/BQ51 -> #DIV/0!
D52: 28 | E52: Wednesday | G52: 213757.6 | H52: =G52/G$56 -> 0.026566428 | I52: =G$15*H52 -> 231127.93 | J52: Wednesday | K52: =LS_RPRO!B35+MANUAL!B35+OUTSALE!B35 -> 0 | L52: =K52-I52 -> -231127.93 | M52: =K52/G15 -> 0 | N52: =N51+L52 -> -5204139.3 | P52: 316 | Q52: =LS_RPRO!C35+MANUAL!C35+OUTSALE!C35 -> 0 | R52: =(Q52-P52)/P52 -> -1 | V52: =(U52-T52)/T52 -> #DIV/0! | W52: =U52*25% -> 0 | Y52: =K52-U52 -> 0 | Z52: =(Y52-X52)/X52 -> #DIV/0! | AA52: =Y52*30% -> 0 | AB52: =W52+AA52 -> 0 | AC52: =AB52/$M$15 -> #DIV/0! | AE52: 174420.4 | AF52: =LS_RPRO!O35+MANUAL!M35+OUTSALE!M35 -> 0 | AG52: =(AF52-AE52)/AE52 -> -1 | AI52: 620 | AJ52: =LS_RPRO!M35 -> 0 | AK52: =AJ52/AI52-1 -> -1 | AL52: 110 | AM52: =MANUAL!H35+LS_RPRO!H35+OUTSALE!H35 -> 0 | AN52: =AM52/AL52-1 -> -1 | AO52: =AL52/AI52 -> 0.17741935 | AP52: =AM52/AJ52 -> #DIV/0! | AQ52: =AP52-AO52 -> #DIV/0! | AS52: 0 | AT52: =LS_RPRO!K35 -> 0 | AU52: =(AT52-AS52)/AS52 -> #DIV/0! | AV52: 3 | AW52: =LS_RPRO!L35 -> 0 | AX52: =(AW52-AV52)/AV52 -> -1 | AY52: =AS52+AV52 -> 3 | AZ52: =AT52+AW52 -> 0 | BA52: =(AZ52-AY52)/AY52 -> -1 | BD52: 0 | BE52: =(BD52-BC52)/BC52 -> #DIV/0! | BI52: =(BH52-BG52)/BG52 -> #DIV/0! | BL52: =(BK52-BJ52)/BJ52 -> #DIV/0! | BM52: =BJ52/BG52 -> #DIV/0! | BN52: =BK52/BH52 -> #DIV/0! | BO52: =BN52-BM52 -> #DIV/0! | BS52: =(BR52-BQ52)/BQ52 -> #DIV/0!
D53: 29 | E53: Thursday | G53: 231536.6 | H53: =G53/G$56 -> 0.028776055 | I53: =G$15*H53 -> 250351.68 | J53: Thursday | K53: =LS_RPRO!B36+MANUAL!B36+OUTSALE!B36 -> 0 | L53: =K53-I53 -> -250351.68 | M53: =K53/G15 -> 0 | N53: =N52+L53 -> -5454491 | P53: 239.7 | Q53: =LS_RPRO!C36+MANUAL!C36+OUTSALE!C36 -> 0 | R53: =(Q53-P53)/P53 -> -1 | V53: =(U53-T53)/T53 -> #DIV/0! | W53: =U53*25% -> 0 | Y53: =K53-U53 -> 0 | Z53: =(Y53-X53)/X53 -> #DIV/0! | AA53: =Y53*30% -> 0 | AB53: =W53+AA53 -> 0 | AC53: =AB53/$M$15 -> #DIV/0! | AE53: 164526.2 | AF53: =LS_RPRO!O36+MANUAL!M36+OUTSALE!M36 -> 0 | AG53: =(AF53-AE53)/AE53 -> -1 | AI53: 526 | AJ53: =LS_RPRO!M36 -> 0 | AK53: =AJ53/AI53-1 -> -1 | AL53: 39 | AM53: =MANUAL!H36+LS_RPRO!H36+OUTSALE!H36 -> 0 | AN53: =AM53/AL53-1 -> -1 | AO53: =AL53/AI53 -> 0.074144487 | AP53: =AM53/AJ53 -> #DIV/0! | AQ53: =AP53-AO53 -> #DIV/0! | AS53: 0 | AT53: =LS_RPRO!K36 -> 0 | AU53: =(AT53-AS53)/AS53 -> #DIV/0! | AV53: 0 | AW53: =LS_RPRO!L36 -> 0 | AX53: =(AW53-AV53)/AV53 -> #DIV/0! | AY53: =AS53+AV53 -> 0 | AZ53: =AT53+AW53 -> 0 | BA53: =(AZ53-AY53)/AY53 -> #DIV/0! | BD53: 0 | BE53: =(BD53-BC53)/BC53 -> #DIV/0! | BI53: =(BH53-BG53)/BG53 -> #DIV/0! | BL53: =(BK53-BJ53)/BJ53 -> #DIV/0! | BM53: =BJ53/BG53 -> #DIV/0! | BN53: =BK53/BH53 -> #DIV/0! | BO53: =BN53-BM53 -> #DIV/0! | BS53: =(BR53-BQ53)/BQ53 -> #DIV/0!
D54: 30 | E54: Friday | G54: 205966.4 | H54: =G54/G$56 -> 0.025598115 | I54: =G$15*H54 -> 222703.6 | J54: Friday | K54: =LS_RPRO!B37+MANUAL!B37+OUTSALE!B37 -> 0 | L54: =K54-I54 -> -222703.6 | M54: =K54/G15 -> 0 | N54: =N53+L54 -> -5677194.6 | P54: 2135.15 | Q54: =LS_RPRO!C37+MANUAL!C37+OUTSALE!C37 -> 0 | R54: =(Q54-P54)/P54 -> -1 | V54: =(U54-T54)/T54 -> #DIV/0! | W54: =U54*25% -> 0 | Y54: =K54-U54 -> 0 | Z54: =(Y54-X54)/X54 -> #DIV/0! | AA54: =Y54*30% -> 0 | AB54: =W54+AA54 -> 0 | AC54: =AB54/$M$15 -> #DIV/0! | AE54: 207701.25 | AF54: =LS_RPRO!O37+MANUAL!M37+OUTSALE!M37 -> 0 | AG54: =(AF54-AE54)/AE54 -> -1 | AI54: 853 | AJ54: =LS_RPRO!M37 -> 0 | AK54: =AJ54/AI54-1 -> -1 | AL54: 136 | AM54: =MANUAL!H37+LS_RPRO!H37+OUTSALE!H37 -> 0 | AN54: =AM54/AL54-1 -> -1 | AO54: =AL54/AI54 -> 0.15943728 | AP54: =AM54/AJ54 -> #DIV/0! | AQ54: =AP54-AO54 -> #DIV/0! | AS54: 1 | AT54: =LS_RPRO!K37 -> 0 | AU54: =(AT54-AS54)/AS54 -> -1 | AV54: 5 | AW54: =LS_RPRO!L37 -> 0 | AX54: =(AW54-AV54)/AV54 -> -1 | AY54: =AS54+AV54 -> 6 | AZ54: =AT54+AW54 -> 0 | BA54: =(AZ54-AY54)/AY54 -> -1 | BD54: 0 | BE54: =(BD54-BC54)/BC54 -> #DIV/0! | BI54: =(BH54-BG54)/BG54 -> #DIV/0! | BL54: =(BK54-BJ54)/BJ54 -> #DIV/0! | BM54: =BJ54/BG54 -> #DIV/0! | BN54: =BK54/BH54 -> #DIV/0! | BO54: =BN54-BM54 -> #DIV/0! | BS54: =(BR54-BQ54)/BQ54 -> #DIV/0!
D55: 31 | E55: Saturday | G55: 316509.45 | H55: =G55/G$56 -> 0.039336733 | I55: =G$15*H55 -> 342229.58 | J55: Saturday | K55: =LS_RPRO!B38+MANUAL!B38+OUTSALE!B38 -> 0 | L55: =K55-I55 -> -342229.58 | M55: =K55/G15 -> 0 | N55: =N54+L55 -> -6019424.1 | P55: 57.5 | Q55: =LS_RPRO!C38+MANUAL!C38+OUTSALE!C38 -> 0 | R55: =(Q55-P55)/P55 -> -1 | V55: =(U55-T55)/T55 -> #DIV/0! | W55: =U55*25% -> 0 | Y55: =K55-U55 -> 0 | Z55: =(Y55-X55)/X55 -> #DIV/0! | AA55: =Y55*30% -> 0 | AB55: =W55+AA55 -> 0 | AC55: =AB55/$M$15 -> #DIV/0! | AE55: 135674.65 | AF55: =LS_RPRO!O38+MANUAL!M38+OUTSALE!M38 -> 0 | AG55: =(AF55-AE55)/AE55 -> -1 | AI55: 256 | AJ55: =LS_RPRO!M38 -> 0 | AK55: =AJ55/AI55-1 -> -1 | AL55: 43 | AM55: =MANUAL!H38+LS_RPRO!H38+OUTSALE!H38 -> 0 | AN55: =AM55/AL55-1 -> -1 | AO55: =AL55/AI55 -> 0.16796875 | AP55: =AM55/AJ55 -> #DIV/0! | AQ55: =AP55-AO55 -> #DIV/0! | AS55: 5 | AT55: =LS_RPRO!K38 -> 0 | AU55: =(AT55-AS55)/AS55 -> -1 | AV55: 1 | AW55: =LS_RPRO!L38 -> 0 | AX55: =(AW55-AV55)/AV55 -> -1 | AY55: =AS55+AV55 -> 6 | AZ55: =AT55+AW55 -> 0 | BA55: =(AZ55-AY55)/AY55 -> -1 | BD55: 0 | BE55: =(BD55-BC55)/BC55 -> #DIV/0! | BI55: =(BH55-BG55)/BG55 -> #DIV/0! | BL55: =(BK55-BJ55)/BJ55 -> #DIV/0! | BM55: =BJ55/BG55 -> #DIV/0! | BN55: =BK55/BH55 -> #DIV/0! | BO55: =BN55-BM55 -> #DIV/0! | BS55: =(BR55-BQ55)/BQ55 -> #DIV/0!
D56: OVERALL TOTAL | G56: =SUM(G25:G55) -> 8046155 | H56: =SUM(H25:H55) -> 0.99716376 | I56: =SUM(I25:I55) -> 8675324.7 | K56: =SUM(K25:K55) -> 2655900.6 | L56: =SUM(L25:L55) -> -6019424.1 | M56: =K56/G15 -> 0.30527593 | N56: =SUM(N25:N55) -> -70509924 | O56: =SUM(O25:O55) -> 0 | P56: =SUM(P25:P55) -> 31644.62 | Q56: =SUM(Q25:Q55) -> 16469.88 | R56: =(Q56-P56)/P56 -> -0.47953617 | T56: =SUM(T25:T55) -> 0 | U56: =SUM(U25:U55) -> 0 | V56: =(U56-T56)/T56 -> #DIV/0! | W56: =SUM(W25:W55) -> 0 | X56: =SUM(X25:X55) -> 0 | Y56: =SUM(Y25:Y55) -> 2655900.6 | Z56: =(Y56-X56)/X56 -> #DIV/0! | AA56: =SUM(AA25:AA55) -> 796770.18 | AB56: =SUM(AB25:AB55) -> 796770.18 | AC56: =SUM(AC25:AC55) -> #DIV/0! | AE56: =SUM(AE25:AE55) -> 5870132.9 | AF56: =SUM(AF25:AF55) -> 2150280.5 | AG56: =(AF56-AE56)/AE56 -> -0.63369134 | AI56: =SUM(AI25:AI55) -> 17825 | AJ56: =SUM(AJ25:AJ55) -> 6827 | AK56: =AJ56/AI56-1 -> -0.6169986 | AL56: =SUM(AL25:AL55) -> 3435 | AM56: =SUM(AM25:AM55) -> 1013 | AN56: =AM56/AL56-1 -> -0.70509461 | AO56: =AL56/AI56 -> 0.19270687 | AP56: =AM56/AJ56 -> 0.14838143 | AQ56: =AP56-AO56 -> -0.044325446 | AS56: =SUM(AS25:AS55) -> 36 | AT56: =SUM(AT25:AT55) -> 16 | AU56: =(AT56-AS56)/AS56 -> -0.55555556 | AV56: =SUM(AV25:AV55) -> 106 | AW56: =SUM(AW25:AW55) -> 38 | AX56: =(AW56-AV56)/AV56 -> -0.64150943 | AY56: =SUM(AY25:AY55) -> 142 | AZ56: =SUM(AZ25:AZ55) -> 54 | BA56: =(AZ56-AY56)/AY56 -> -0.61971831 | BC56: =SUM(BC25:BC55) -> 0 | BD56: =SUM(BD25:BD55) -> 0 | BE56: =(BD56-BC56)/BC56 -> #DIV/0! | BG56: =SUM(BG25:BG55) -> 0 | BH56: =SUM(BH25:BH55) -> 0 | BI56: =(BH56-BG56)/BG56 -> #DIV/0! | BJ56: =SUM(BJ25:BJ55) -> 0 | BK56: =SUM(BK25:BK55) -> 0 | BL56: =(BK56-BJ56)/BJ56 -> #DIV/0! | BM56: =BJ56/BG56 -> #DIV/0! | BN56: =BK56/BH56 -> #DIV/0! | BO56: =BN56-BM56 -> #DIV/0! | BQ56: =SUM(BQ25:BQ55) -> 0 | BR56: =SUM(BR25:BR55) -> 0 | BS56: =(BR56-BQ56)/BQ56 -> #DIV/0!
D60: WEEKLY SALES REPORT
G61: 2026 | H61: 2025
D62: OCT 1-4 | G62: =SUM(K25:K28) -> 1037837.5 | H62: =SUM(G25:G28) -> 907144.53 | I62: =(G62-H62)/G62*1 -> 0.12592818
D63: OCT5-11 | G63: =SUM(K29:K35) -> 1459953.1 | H63: =SUM(G29:G35) -> 1784305.1 | I63: =(G63-H63)/G63*100% -> -0.22216604
D64: OCT 12-18 | G64: =SUM(K36:K42) -> 158110 | H64: =SUM(G36:G42) -> 2181310.9 | I64: =(G64-H64)/G64*100 -> -1279.616
D65: OCT 19-25 | G65: =SUM(K43:K49) -> 0 | H65: =SUM(G43:G49) -> 1662920.6 | I65: =(G65-H65)/G65*100 -> #DIV/0!
D66: OCT 26-31 | G66: =SUM(K50:K55) -> 0 | H66: =SUM(G50:G55) -> 1510473.9 | I66: =(G66-H66)/G66*100 -> #DIV/0!
G67: =K55 -> 0 | H67: =K56 -> 2655900.6 | I67: =(G67-H67)/G67*100 -> #DIV/0!
G69: =SUM(G62:G67) -> 2655900.6

Sheet SAME DAY COMPARISON
A1: SALES COMPARISON
A2: YEAR | B2: SALES | C2: % INC/DEC
A3: 2025 | B3: =SUM(B5:B18) -> 3239466.7 | C3: =(B4-B3)/B3 -> -0.18014263 | F3: =B4-B3 -> -583566.05
A4: 2026 | B4: =C38 -> 2655900.6
A6: DATE | B6: LY(2025) | C6: TY(2026) | D6: % INC/DEC
A7: 46296 | B7: 196063.15 | C7: ='Seasonality Template'!K25 -> 173242.35 | D7: =(C7-B7)/C7 -> -0.13172761
A8: =A7+1 -> 46297 | B8: 168531.4 | C8: ='Seasonality Template'!K26 -> 208772.5 | D8: =(C8-B8)/C8 -> 0.19275096
A9: =A8+1 -> 46298 | B9: 168709 | C9: ='Seasonality Template'!K27 -> 355795.97 | D9: =(C9-B9)/C9 -> 0.52582656
A10: =A9+1 -> 46299 | B10: 373840.98 | C10: ='Seasonality Template'!K28 -> 300026.7 | D10: =(C10-B10)/B10 -> -0.19744834
A11: =A10+1 -> 46300 | B11: 445288.82 | C11: ='Seasonality Template'!K29 -> 214629.95 | D11: =(C11-B11)/B11 -> -0.51799834
A12: =A11+1 -> 46301 | B12: 191197.5 | C12: ='Seasonality Template'!K30 -> 151874.5 | D12: =(C12-B12)/B12 -> -0.20566692
A13: =A12+1 -> 46302 | B13: 206303.95 | C13: ='Seasonality Template'!K31 -> 116543.95 | D13: =(C13-B13)/B13 -> -0.43508619
A14: =A13+1 -> 46303 | B14: 169083.9 | C14: ='Seasonality Template'!K32 -> 146954.5 | D14: =(C14-B14)/B14 -> -0.13087822
A15: =A14+1 -> 46304 | B15: 173091.25 | C15: ='Seasonality Template'!K33 -> 198378.74 | D15: =(C15-B15)/B15 -> 0.1460934
A16: =A15+1 -> 46305 | B16: 197428.25 | C16: ='Seasonality Template'!K34 -> 316237.04 | D16: =(C16-B16)/B16 -> 0.60178212
A17: =A16+1 -> 46306 | B17: 401911.4 | C17: ='Seasonality Template'!K35 -> 315334.4 | D17: =(C17-B17)/B17 -> -0.21541315
A18: =A17+1 -> 46307 | B18: 548017.05 | C18: ='Seasonality Template'!K36 -> 158110 | D18: =(C18-B18)/B18 -> -0.71148708
A19: =A18+1 -> 46308 | B19: 162285.5 | C19: ='Seasonality Template'!K37 -> 0 | D19: =(C19-B19)/B19 -> -1
A20: =A19+1 -> 46309 | B20: 196776 | C20: ='Seasonality Template'!K38 -> 0 | D20: =(C20-B20)/B20 -> -1
A21: =A20+1 -> 46310 | B21: 217199.4 | C21: ='Seasonality Template'!K39 -> 0 | D21: =(C21-B21)/B21 -> -1
... A37: =A36+1 -> 46326 | B37: 316509.45 | C37: ='Seasonality Template'!K55 -> 0 | D37: =(C37-B37)/B37 -> -1
A38: TOTAL | B38: =SUM(B7:B37) -> 8046155 | C38: =SUM(C7:C37) -> 2655900.6 | D38: =(C38-B38)/B38 -> -0.6699168

Sheet EOD MONITORING
B1: Z-ID NUMBER
A2: DATE | B2: POS 1 | C2: POS 2
A3: 46266
A4: =A3+1 -> 46267
A5: =A4+1 -> 46268
A6: =A5+1 -> 46269
A7: =A6+1 -> 46270
A8: =A7+1 -> 46271
A9: =A8+1 -> 46272
A10: =A9+1 -> 46273
A11: =A10+1 -> 46274
A12: =A11+1 -> 46275
A13: =A12+1 -> 46276
A14: =A13+1 -> 46277
A15: =A14+1 -> 46278
... A33: =A32+1 -> 46296

Sheet Seasonality Template WML V
D1: DAILY SALES MONITORING REPORT
N2: Interpretation:
N3: *Current seasonality %age is 62% while Sales Achievement is @ 31%. The store is short by 31% on seasonality
N4: *Staright line is 58% while Sales Achievement is @ 31%. The store is short by 27% on straight line
N5: **Seasonality percentage shows sales trend last year thus it will be great if the store is at par with the seasonality %age
N6: **Straight line shows equal distribution of sales based on the no. Of days
D12: STORE:
D13: MONTH: | E13: MAY 1-31, 2025
O14: RETAIL DRIVERS | P14: RUNNING LY | Q14: RUNNING 2025 | R14: % inc/dec | T14: RETAIL DRIVERS | U14: RUNNING LY | V14: RUNNING 2016 | W14: % inc/dec
D15: GROSS SALES TARGET | G15: 2735471.6 | H15: AVE. DAILY SALES | J15: =G16/J20 -> 91582.779 | K15: GROSS MARGIN TARGET | M15: 925000 | O15: Entering Customer | P15: =SUM(AI25:AI55) -> 6216 | Q15: =SUM(AJ25:AJ55) -> 6827 | R15: =Q15/P15-1 -> 0.098294723 | T15: Gait Request | U15: =SUM(BG25:BG55) -> 0 | V15: =BH56 -> 0 | W15: =V15/U15-1 -> #DIV/0!
D16: MONTH-TO-DATE (MTD) | G16: =K56 -> 2655900.6 | H16: TARGET GROWTH VS. LY | J16: =G15/G56-1 -> 0.1128 | K16: MONTH-TO-DATE (MTD) | M16: =AB56 -> 644162.84 | O16: Buying Customer | P16: =SUM(AL25:AL55) -> 1279 | Q16: =SUM(AM25:AM55) -> 1013 | R16: =Q16/P16-1 -> -0.20797498 | T16: Gait w/ po | U16: =SUM(BJ25:BJ55) -> 0 | V16: =BK56 -> 0 | W16: =V16/U16-1 -> #DIV/0!
D17: TOTAL VARIANCE ON TARGET | G17: =G16-G15 -> -79571.05 | H17: CURRENT SEASONALITY | J17: =SUM(H5:H51) -> 0.93258795 | K17: TOTAL VARIANCE ON TARGET | M17: =M16-M15 -> -280837.16 | O17: Average Purchase | P17: =G56/AL56 -> 1921.9609 | Q17: =G16/Q16 -> 2621.817 | R17: =Q17/P17-1 -> 0.36413645 | T17: Gait Conversion | U17: =U16/U15 -> #DIV/0! | V17: =V16/V15 -> #DIV/0! | W17: =V17-U17 -> #DIV/0!
D18: TOTAL VARIANCE ON EXPECTED SALES -DAILY | G18: =N51 -> 104832.71 | H18: STRAIGHT LINE | J18: =(100%/30)*J20 -> 0.96666667 | K18: GM ACHIEVEMENT | M18: =SUM(AC25:AC55) -> 0.69639225 | O18: Conversion Ratio | P18: =P16/P15 -> 0.20575933 | Q18: =Q16/Q15 -> 0.14838143 | R18: =Q18-P18 -> -0.057377904 | T18: Shoes Sold | U18: =BQ56 -> 267 | V18: =BR56 -> 240 | W18: =V18/U18-1 -> -0.1011236
D19: AVE. SALES NEEDED- DAILY | G19: =G17/J21 -> -79571.05 | H19: SALES ACHIEVEMENT | J19: =SUM(M25:M55) -> 0.9709114 | K19: GM ACHIEVEMENT BASED ON GROSS SALES | M19: =M16/G16 -> 0.24254027 | O19: Raquet Stringing | P19: =SUM(AY25:AY55) -> 67 | Q19: =AZ56 -> 54 | R19: =Q19/P19-1 -> -0.19402985
D20: BEST EOM PESO VALUE | G20: =J15*J21+G16 -> 2747483.4 | H20: RUNNING DAY/S | J20: 29 | O20: Shoot-out | P20: =BC56 -> 0 | Q20: =BD56 -> 0 | R20: =Q20/P20-1 -> #DIV/0!
D21: BEST EOM % | G21: =G20/G15 -> 1.0043911 | H21: REMAINING DAY/S | J21: =30-J20 -> 1 | O21: *Note: Follow execution on the sales template
D22: MONTH-TO-DATE (MTD) LY | G22: =SUM(G25:G55) -> 2458188 | H22: % LY | J22: =(K56-G22)/G22 -> 0.080430202 | T22: GROSS MARGIN COMPUTATION
D23: . | T23: CONCESSION | X23: OUTRIGHT | AB23: TOTAL GROSS MARGIN 2025 | AC23: % SEASONALITY OF ACTUAL GROSS MARGIN
D24: DATE | G24: ACTUAL 2024 | H24: % SEASONALITY | I24: TARGET SALES PER DAY | J24: DAYS (TY) | K24: ACTUAL 2025 | L24: VARIANCE ON DAILY SALES TARGET | M24: % SEASONALITY OF ACTUAL SALES | N24: Running Variance | O24: QTY. SOLD 2025 | P24: DISCOUNT 2024 | Q24: DISCOUNT 2025 | R24: % CHANGE | T24: CONCESSION SALES 2024 | U24: CONCESSION SALES 2025 | V24: % Inc/Dec | W24: CONCESSION GM 2025 | X24: OUTRIGHT SALES 2024 | Y24: OUTRIGHT SALES 2025 | Z24: % Inc/Dec | AA24: OUTRIGHT GM 2025 | AE24: CREDIT CARD SALES 2024 | AF24: CREDIT CARD SALES 2025 | AG24: % Inc/Dec | AI24: ENTERING CUSTOMER 2024 | AJ24: ENTERING CUSTOMER 2025 | AK24: % Inc/Dec | AL24: BUYING CUSTOMER 2024 | AM24: BUYING CUSTOMER 2025 | AN24: % Inc/Dec | AO24: BATTING AVE. 2024 | AP24: BATTING AVE. 2025 | AQ24: % Inc/Dec | AS24: TENNIS 2024 | AT24: TENNIS 2025 | AU24: % Inc/Dec | AV24: BADMINTON 2024 | AW24: BADMINTON 2025 | AX24: % Inc/Dec | AY24: TOTAL RACQUETS STRINGING 2024 | AZ24: TOTAL RACQUETS STRINGING 2025 | BA24: % CHANGE | BC24: SHOOT-OUT SALES 2024 | BD24: SHOOT-OUT SALES 2025 | BE24: % Inc/Dec | BG24: GAIT REQUEST 2024 | BH24: GAIT REQUEST 2025 | BI24: % Inc/Dec | BJ24: GAIT W/ PO 2024 | BK24: GAIT W/ PO 2025 | BL24: % Inc/Dec | BM24: GAIT CONVERSION 2024 | BN24: GAIT CONVERSION 2025 | BO24: % CHANGE | BQ24: SHOES SOLD 2024 | BR24: SHOES SOLD 2025 | BS24: % Inc/Dec
D25: 1 | E25: Thursday | G25: 48302.5 | H25: =G25/$G$56 -> 0.019649636 | I25: =G$15*H25 -> 53751.022 | J25: Thursday | K25: =LS_RPRO!B6+MANUAL!B6+OUTSALE!B6 -> 173242.35 | L25: =K25-I25 -> 119491.33 | M25: =K25/G15 -> 0.063331802 | N25: =L25 -> 119491.33 | O25: 167 | P25: 0 | Q25: =LS_RPRO!C6+MANUAL!C6+OUTSALE!C6 -> 0 | R25: =(Q25-P25)/P25 -> #DIV/0! | T25: 6010.5 | U25: 21842.5 | V25: =(U25-T25)/T25 -> 2.6340571 | X25: 48145 | Y25: 66074 | Z25: =(Y25-X25)/X25 -> 0.37239589 | AA25: 21128.422 | AB25: =W25+AA25 -> 21128.422 | AC25: =AB25/$M$15 -> 0.022841538 | AE25: 20581 | AF25: =LS_RPRO!O6+MANUAL!M6+OUTSALE!M6 -> 137805.35 | AG25: =(AF25-AE25)/AE25 -> 5.6957558 | AI25: 225 | AJ25: =LS_RPRO!M6 -> 359 | AK25: =AJ25/AI25-1 -> 0.59555556 | AL25: 34 | AM25: =LS_RPRO!H6+MANUAL!H6+OUTSALE!H6 -> 0 | AN25: =AM25/AL25-1 -> -1 | AO25: =AL25/AI25 -> 0.15111111 | AP25: =AM25/AJ25 -> 0 | AQ25: =AP25-AO25 -> -0.15111111 | AS25: 0 | AT25: =LS_RPRO!K6 -> 0 | AU25: =(AT25-AS25)/AS25 -> #DIV/0! | AV25: 1 | AW25: =LS_RPRO!L6 -> 0 | AX25: =(AW25-AV25)/AV25 -> -1 | AY25: =AS25+AV25 -> 1 | AZ25: =AT25+AW25 -> 0 | BA25: =(AZ25-AY25)/AY25 -> -1 | BD25: 0 | BE25: =(BD25-BC25)/BC25 -> #DIV/0! | BI25: =(BH25-BG25)/BG25 -> #DIV/0! | BL25: =(BK25-BJ25)/BJ25 -> #DIV/0! | BM25: =BJ25/BG25 -> #DIV/0! | BN25: =BK25/BH25 -> #DIV/0! | BO25: =BN25-BM25 -> #DIV/0! | BQ25: 7 | BR25: 11 | BS25: =(BR25-BQ25)/BQ25 -> 0.57142857
D26: 2 | E26: Friday | G26: 85025.5 | H26: =G26/$G$56 -> 0.034588688 | I26: =G$15*H26 -> 94616.376 | J26: Friday | K26: =LS_RPRO!B7+MANUAL!B7+OUTSALE!B7 -> 208772.5 | L26: =K26-I26 -> 114156.12 | M26: =K26/G15 -> 0.076320477 | N26: =N25+L26 -> 233647.45 | O26: 96 | P26: 318.75 | Q26: =LS_RPRO!C7+MANUAL!C7+OUTSALE!C7 -> 169.8 | R26: =(Q26-P26)/P26 -> -0.46729412 | T26: 14322 | U26: 20286.75 | V26: =(U26-T26)/T26 -> 0.41647465 | X26: 27467 | Y26: 49503 | Z26: =(Y26-X26)/X26 -> 0.80227182 | AA26: 17394.7 | AB26: =W26+AA26 -> 17394.7 | AC26: =AB26/$M$15 -> 0.018805081 | AE26: 25166.25 | AF26: =LS_RPRO!O7+MANUAL!M7+OUTSALE!M7 -> 171801.75 | AG26: =(AF26-AE26)/AE26 -> 5.8266726 | AI26: 158 | AJ26: =LS_RPRO!M7 -> 446 | AK26: =AJ26/AI26-1 -> 1.8227848 | AL26: 23 | AM26: =LS_RPRO!H7+MANUAL!H7+OUTSALE!H7 -> 101 | AN26: =AM26/AL26-1 -> 3.3913043 | AO26: =AL26/AI26 -> 0.14556962 | AP26: =AM26/AJ26 -> 0.2264574 | AQ26: =AP26-AO26 -> 0.080887779 | AS26: 0 | AT26: =LS_RPRO!K7 -> 0 | AU26: =(AT26-AS26)/AS26 -> #DIV/0! | AV26: 0 | AW26: =LS_RPRO!L7 -> 2 | AX26: =(AW26-AV26)/AV26 -> #DIV/0! | AY26: =AS26+AV26 -> 0 | AZ26: =AT26+AW26 -> 2 | BA26: =(AZ26-AY26)/AY26 -> #DIV/0! | BD26: 0 | BE26: =(BD26-BC26)/BC26 -> #DIV/0! | BI26: =(BH26-BG26)/BG26 -> #DIV/0! | BL26: =(BK26-BJ26)/BJ26 -> #DIV/0! | BM26: =BJ26/BG26 -> #DIV/0! | BN26: =BK26/BH26 -> #DIV/0! | BO26: =BN26-BM26 -> #DIV/0! | BQ26: 2 | BR26: 10 | BS26: =(BR26-BQ26)/BQ26 -> 4
D27: 3 | E27: Saturday | G27: 76585 | H27: =G27/$G$56 -> 0.031155062 | I27: =G$15*H27 -> 85223.788 | J27: Saturday | K27: =LS_RPRO!B8+MANUAL!B8+OUTSALE!B8 -> 355795.97 | L27: =K27-I27 -> 270572.18 | M27: =K27/G15 -> 0.1300675 | N27: =N26+L27 -> 504219.63 | O27: 103 | P27: 0 | Q27: =LS_RPRO!C8+MANUAL!C8+OUTSALE!C8 -> 708.96 | R27: =(Q27-P27)/P27 -> #DIV/0! | T27: 10475 | U27: 6411 | V27: =(U27-T27)/T27 -> -0.38797136 | X27: 37827.5 | Y27: 71209 | Z27: =(Y27-X27)/X27 -> 0.88246646 | AA27: 20159.531 | AB27: =W27+AA27 -> 20159.531 | AC27: =AB27/$M$15 -> 0.021794087 | AE27: 24898 | AF27: =LS_RPRO!O8+MANUAL!M8+OUTSALE!M8 -> 285580.75 | AG27: =(AF27-AE27)/AE27 -> 10.470028 | AI27: 213 | AJ27: =LS_RPRO!M8 -> 976 | AK27: =AJ27/AI27-1 -> 3.5821596 | AL27: 36 | AM27: =LS_RPRO!H8+MANUAL!H8+OUTSALE!H8 -> 138 | AN27: =AM27/AL27-1 -> 2.8333333 | AO27: =AL27/AI27 -> 0.16901408 | AP27: =AM27/AJ27 -> 0.14139344 | AQ27: =AP27-AO27 -> -0.027620642 | AS27: 1 | AT27: =LS_RPRO!K8 -> 4 | AU27: =(AT27-AS27)/AS27 -> 3 | AV27: 6 | AW27: =LS_RPRO!L8 -> 5 | AX27: =(AW27-AV27)/AV27 -> -0.16666667 | AY27: =AS27+AV27 -> 7 | AZ27: =AT27+AW27 -> 9 | BA27: =(AZ27-AY27)/AY27 -> 0.28571429 | BD27: 0 | BE27: =(BD27-BC27)/BC27 -> #DIV/0! | BI27: =(BH27-BG27)/BG27 -> #DIV/0! | BL27: =(BK27-BJ27)/BJ27 -> #DIV/0! | BM27: =BJ27/BG27 -> #DIV/0! | BN27: =BK27/BH27 -> #DIV/0! | BO27: =BN27-BM27 -> #DIV/0! | BQ27: 1 | BR27: 7 | BS27: =(BR27-BQ27)/BQ27 -> 6
D28: 4 | E28: Sunday | G28: 100788 | H28: =G28/$G$56 -> 0.041000932 | I28: =G$15*H28 -> 112156.89 | J28: Sunday | K28: =LS_RPRO!B9+MANUAL!B9+OUTSALE!B9 -> 300026.7 | L28: =K28-I28 -> 187869.81 | M28: =K28/G15 -> 0.10968006 | N28: =N27+L28 -> 692089.45 | O28: 105 | P28: 0 | Q28: =LS_RPRO!C9+MANUAL!C9+OUTSALE!C9 -> 2180.5 | R28: =(Q28-P28)/P28 -> #DIV/0! | T28: 15175 | U28: 22346 | V28: =(U28-T28)/T28 -> 0.47255354 | X28: 69850.5 | Y28: 45634.5 | Z28: =(Y28-X28)/X28 -> -0.34668327 | AA28: 14498.235 | AB28: =W28+AA28 -> 14498.235 | AC28: =AB28/$M$15 -> 0.015673768 | AE28: 61799.5 | AF28: =LS_RPRO!O9+MANUAL!M9+OUTSALE!M9 -> 243077.7 | AG28: =(AF28-AE28)/AE28 -> 2.9333279 | AI28: 178 | AJ28: =LS_RPRO!M9 -> 883 | AK28: =AJ28/AI28-1 -> 3.9606742 | AL28: 49 | AM28: =LS_RPRO!H9+MANUAL!H9+OUTSALE!H9 -> 130 | AN28: =AM28/AL28-1 -> 1.6530612 | AO28: =AL28/AI28 -> 0.2752809 | AP28: =AM28/AJ28 -> 0.14722537 | AQ28: =AP28-AO28 -> -0.12805553 | AS28: 0 | AT28: =LS_RPRO!K9 -> 0 | AU28: =(AT28-AS28)/AS28 -> #DIV/0! | AV28: 2 | AW28: =LS_RPRO!L9 -> 17 | AX28: =(AW28-AV28)/AV28 -> 7.5 | AY28: =AS28+AV28 -> 2 | AZ28: =AT28+AW28 -> 17 | BA28: =(AZ28-AY28)/AY28 -> 7.5 | BD28: 0 | BE28: =(BD28-BC28)/BC28 -> #DIV/0! | BI28: =(BH28-BG28)/BG28 -> #DIV/0! | BL28: =(BK28-BJ28)/BJ28 -> #DIV/0! | BM28: =BJ28/BG28 -> #DIV/0! | BN28: =BK28/BH28 -> #DIV/0! | BO28: =BN28-BM28 -> #DIV/0! | BQ28: 11 | BR28: 7 | BS28: =(BR28-BQ28)/BQ28 -> -0.36363636
D29: 5 | E29: Monday | G29: 160546.5 | H29: =G29/$G$56 -> 0.065310911 | I29: =G$15*H29 -> 178656.15 | J29: Monday | K29: =LS_RPRO!B10+MANUAL!B10+OUTSALE!B10 -> 214629.95 | L29: =K29-I29 -> 35973.805 | M29: =K29/G15 -> 0.078461771 | N29: =N28+L29 -> 728063.25 | O29: 139 | P29: 0 | Q29: =LS_RPRO!C10+MANUAL!C10+OUTSALE!C10 -> 1596.06 | R29: =(Q29-P29)/P29 -> #DIV/0! | T29: 12719.5 | U29: 16321.5 | V29: =(U29-T29)/T29 -> 0.28318723 | X29: 63865.5 | Y29: 70292.5 | Z29: =(Y29-X29)/X29 -> 0.10063336 | AA29: 23645.014 | AB29: =W29+AA29 -> 23645.014 | AC29: =AB29/$M$15 -> 0.025562178 | AE29: 40319.5 | AF29: =LS_RPRO!O10+MANUAL!M10+OUTSALE!M10 -> 168429.69 | AG29: =(AF29-AE29)/AE29 -> 3.1773755 | AI29: 278 | AJ29: =LS_RPRO!M10 -> 687 | AK29: =AJ29/AI29-1 -> 1.471223 | AL29: 44 | AM29: =LS_RPRO!H10+MANUAL!H10+OUTSALE!H10 -> 75 | AN29: =AM29/AL29-1 -> 0.70454545 | AO29: =AL29/AI29 -> 0.15827338 | AP29: =AM29/AJ29 -> 0.10917031 | AQ29: =AP29-AO29 -> -0.049103076 | AS29: 0 | AT29: =LS_RPRO!K10 -> 5 | AU29: =(AT29-AS29)/AS29 -> #DIV/0! | AV29: 5 | AW29: =LS_RPRO!L10 -> 1 | AX29: =(AW29-AV29)/AV29 -> -0.8 | AY29: =AS29+AV29 -> 5 | AZ29: =AT29+AW29 -> 6 | BA29: =(AZ29-AY29)/AY29 -> 0.2 | BD29: 0 | BE29: =(BD29-BC29)/BC29 -> #DIV/0! | BI29: =(BH29-BG29)/BG29 -> #DIV/0! | BL29: =(BK29-BJ29)/BJ29 -> #DIV/0! | BM29: =BJ29/BG29 -> #DIV/0! | BN29: =BK29/BH29 -> #DIV/0! | BO29: =BN29-BM29 -> #DIV/0! | BQ29: 8 | BR29: 7 | BS29: =(BR29-BQ29)/BQ29 -> -0.125
D30: 6 | E30: Tuesday | G30: 97075.5 | H30: =G30/$G$56 -> 0.039490673 | I30: =G$15*H30 -> 108025.62 | J30: Tuesday | K30: =LS_RPRO!B11+MANUAL!B11+OUTSALE!B11 -> 151874.5 | L30: =K30-I30 -> 43848.884 | M30: =K30/G15 -> 0.055520407 | N30: =N29+L30 -> 771912.14 | O30: 166 | P30: 0 | Q30: =LS_RPRO!C11+MANUAL!C11+OUTSALE!C11 -> 328.75 | R30: =(Q30-P30)/P30 -> #DIV/0! | T30: 13298.5 | U30: 35829 | V30: =(U30-T30)/T30 -> 1.6942136 | X30: 62931.5 | Y30: 69316.5 | Z30: =(Y30-X30)/X30 -> 0.10145952 | AA30: 20434.176 | AB30: =W30+AA30 -> 20434.176 | AC30: =AB30/$M$15 -> 0.022091001 | AE30: 46283.5 | AF30: =LS_RPRO!O11+MANUAL!M11+OUTSALE!M11 -> 143597.75 | AG30: =(AF30-AE30)/AE30 -> 2.102569 | AI30: 214 | AJ30: =LS_RPRO!M11 -> 333 | AK30: =AJ30/AI30-1 -> 0.55607477 | AL30: 54 | AM30: =LS_RPRO!H11+MANUAL!H11+OUTSALE!H11 -> 72 | AN30: =AM30/AL30-1 -> 0.33333333 | AO30: =AL30/AI30 -> 0.25233645 | AP30: =AM30/AJ30 -> 0.21621622 | AQ30: =AP30-AO30 -> -0.036120232 | AS30: 0 | AT30: =LS_RPRO!K11 -> 1 | AU30: =(AT30-AS30)/AS30 -> #DIV/0! | AV30: 1 | AW30: =LS_RPRO!L11 -> 1 | AX30: =(AW30-AV30)/AV30 -> 0 | AY30: =AS30+AV30 -> 1 | AZ30: =AT30+AW30 -> 2 | BA30: =(AZ30-AY30)/AY30 -> 1 | BD30: 0 | BE30: =(BD30-BC30)/BC30 -> #DIV/0! | BI30: =(BH30-BG30)/BG30 -> #DIV/0! | BL30: =(BK30-BJ30)/BJ30 -> #DIV/0! | BM30: =BJ30/BG30 -> #DIV/0! | BN30: =BK30/BH30 -> #DIV/0! | BO30: =BN30-BM30 -> #DIV/0! | BQ30: 12 | BR30: 14 | BS30: =(BR30-BQ30)/BQ30 -> 0.16666667
D31: 7 | E31: Wednesday | G31: 48751.5 | H31: =G31/$G$56 -> 0.019832291 | I31: =G$15*H31 -> 54250.669 | J31: Wednesday | K31: =LS_RPRO!B12+MANUAL!B12+OUTSALE!B12 -> 116543.95 | L31: =K31-I31 -> 62293.281 | M31: =K31/G15 -> 0.0426047 | N31: =N30+L31 -> 834205.42 | O31: 53 | P31: 0 | Q31: =LS_RPRO!C12+MANUAL!C12+OUTSALE!C12 -> 966.3 | R31: =(Q31-P31)/P31 -> #DIV/0! | T31: 18631.5 | U31: 9362.5 | V31: =(U31-T31)/T31 -> -0.49749081 | W31: 33099.81 | X31: 141915 | Y31: 38113.5 | Z31: =(Y31-X31)/X31 -> -0.73143431 | AA31: 11659.52 | AB31: =W31+AA31 -> 44759.33 | AC31: =AB31/$M$15 -> 0.048388465 | AE31: 87498 | AF31: =LS_RPRO!O12+MANUAL!M12+OUTSALE!M12 -> 81910.4 | AG31: =(AF31-AE31)/AE31 -> -0.063859745 | AI31: 249 | AJ31: =LS_RPRO!M12 -> 316 | AK31: =AJ31/AI31-1 -> 0.26907631 | AL31: 65 | AM31: =LS_RPRO!H12+MANUAL!H12+OUTSALE!H12 -> 50 | AN31: =AM31/AL31-1 -> -0.23076923 | AO31: =AL31/AI31 -> 0.26104418 | AP31: =AM31/AJ31 -> 0.15822785 | AQ31: =AP31-AO31 -> -0.10281633 | AS31: 0 | AT31: =LS_RPRO!K12 -> 0 | AU31: =(AT31-AS31)/AS31 -> #DIV/0! | AV31: 2 | AW31: =LS_RPRO!L12 -> 0 | AX31: =(AW31-AV31)/AV31 -> -1 | AY31: =AS31+AV31 -> 2 | AZ31: =AT31+AW31 -> 0 | BA31: =(AZ31-AY31)/AY31 -> -1 | BD31: 0 | BE31: =(BD31-BC31)/BC31 -> #DIV/0! | BI31: =(BH31-BG31)/BG31 -> #DIV/0! | BL31: =(BK31-BJ31)/BJ31 -> #DIV/0! | BM31: =BJ31/BG31 -> #DIV/0! | BN31: =BK31/BH31 -> #DIV/0! | BO31: =BN31-BM31 -> #DIV/0! | BQ31: 19 | BR31: 7 | BS31: =(BR31-BQ31)/BQ31 -> -0.63157895
D32: 8 | E32: Thursday | G32: 100935 | H32: =G32/$G$56 -> 0.041060732 | I32: =G$15*H32 -> 112320.47 | J32: Thursday | K32: =LS_RPRO!B13+MANUAL!B13+OUTSALE!B13 -> 146954.5 | L32: =K32-I32 -> 34634.032 | M32: =K32/G15 -> 0.053721814 | N32: =N31+L32 -> 868839.45 | O32: 105 | P32: 0 | Q32: =LS_RPRO!C13+MANUAL!C13+OUTSALE!C13 -> 1268.25 | R32: =(Q32-P32)/P32 -> #DIV/0! | T32: 11501 | U32: 15962.75 | V32: =(U32-T32)/T32 -> 0.38794453 | X32: 85574.5 | Y32: 46137.5 | Z32: =(Y32-X32)/X32 -> -0.4608499 | AA32: 14565.026 | AB32: =W32+AA32 -> 14565.026 | AC32: =AB32/$M$15 -> 0.015745974 | AE32: 64274.5 | AF32: =LS_RPRO!O13+MANUAL!M13+OUTSALE!M13 -> 120065.25 | AG32: =(AF32-AE32)/AE32 -> 0.86800753 | AI32: 124 | AJ32: =LS_RPRO!M13 -> 478 | AK32: =AJ32/AI32-1 -> 2.8548387 | AL32: 37 | AM32: =LS_RPRO!H13+MANUAL!H13+OUTSALE!H13 -> 67 | AN32: =AM32/AL32-1 -> 0.81081081 | AO32: =AL32/AI32 -> 0.2983871 | AP32: =AM32/AJ32 -> 0.14016736 | AQ32: =AP32-AO32 -> -0.15821973 | AS32: 0 | AT32: =LS_RPRO!K13 -> 0 | AU32: =(AT32-AS32)/AS32 -> #DIV/0! | AV32: 1 | AW32: =LS_RPRO!L13 -> 0 | AX32: =(AW32-AV32)/AV32 -> -1 | AY32: =AS32+AV32 -> 1 | AZ32: =AT32+AW32 -> 0 | BA32: =(AZ32-AY32)/AY32 -> -1 | BD32: 0 | BE32: =(BD32-BC32)/BC32 -> #DIV/0! | BI32: =(BH32-BG32)/BG32 -> #DIV/0! | BL32: =(BK32-BJ32)/BJ32 -> #DIV/0! | BM32: =BJ32/BG32 -> #DIV/0! | BN32: =BK32/BH32 -> #DIV/0! | BO32: =BN32-BM32 -> #DIV/0! | BQ32: 7 | BR32: 5 | BS32: =(BR32-BQ32)/BQ32 -> -0.28571429
D33: 9 | E33: Friday | G33: 79330 | H33: =G33/$G$56 -> 0.032271738 | I33: =G$15*H33 -> 88278.424 | J33: Friday | K33: =LS_RPRO!B14+MANUAL!B14+OUTSALE!B14 -> 198378.74 | L33: =K33-I33 -> 110100.32 | M33: =K33/G15 -> 0.072520854 | N33: =N32+L33 -> 978939.76 | O33: 203 | P33: 0 | Q33: =LS_RPRO!C14+MANUAL!C14+OUTSALE!C14 -> 1337.3 | R33: =(Q33-P33)/P33 -> #DIV/0! | T33: 14879 | U33: 26206.5 | V33: =(U33-T33)/T33 -> 0.76130788 | X33: 33872.5 | Y33: 95411.5 | Z33: =(Y33-X33)/X33 -> 1.8167835 | AA33: 32588.821 | AB33: =W33+AA33 -> 32588.821 | AC33: =AB33/$M$15 -> 0.035231158 | AE33: 23752 | AF33: =LS_RPRO!O14+MANUAL!M14+OUTSALE!M14 -> 169130.25 | AG33: =(AF33-AE33)/AE33 -> 6.120674 | AI33: 141 | AJ33: =LS_RPRO!M14 -> 531 | AK33: =AJ33/AI33-1 -> 2.7659574 | AL33: 36 | AM33: =LS_RPRO!H14+MANUAL!H14+OUTSALE!H14 -> 81 | AN33: =AM33/AL33-1 -> 1.25 | AO33: =AL33/AI33 -> 0.25531915 | AP33: =AM33/AJ33 -> 0.15254237 | AQ33: =AP33-AO33 -> -0.10277678 | AS33: 0 | AT33: =LS_RPRO!K14 -> 1 | AU33: =(AT33-AS33)/AS33 -> #DIV/0! | AV33: 3 | AW33: =LS_RPRO!L14 -> 6 | AX33: =(AW33-AV33)/AV33 -> 1 | AY33: =AS33+AV33 -> 3 | AZ33: =AT33+AW33 -> 7 | BA33: =(AZ33-AY33)/AY33 -> 1.3333333 | BD33: 0 | BE33: =(BD33-BC33)/BC33 -> #DIV/0! | BI33: =(BH33-BG33)/BG33 -> #DIV/0! | BL33: =(BK33-BJ33)/BJ33 -> #DIV/0! | BM33: =BJ33/BG33 -> #DIV/0! | BN33: =BK33/BH33 -> #DIV/0! | BO33: =BN33-BM33 -> #DIV/0! | BQ33: 5 | BR33: 11 | BS33: =(BR33-BQ33)/BQ33 -> 1.2
D34: 10 | E34: Saturday | G34: 83591.5 | H34: =G34/$G$56 -> 0.034005332 | I34: =G$15*H34 -> 93020.621 | J34: Saturday | K34: =LS_RPRO!B15+MANUAL!B15+OUTSALE!B15 -> 316237.04 | L34: =K34-I34 -> 223216.42 | M34: =K34/G15 -> 0.11560604 | N34: =N33+L34 -> 1202156.2 | O34: 100 | P34: 0 | Q34: =LS_RPRO!C15+MANUAL!C15+OUTSALE!C15 -> 3966.11 | R34: =(Q34-P34)/P34 -> #DIV/0! | T34: 10708 | U34: 14014 | V34: =(U34-T34)/T34 -> 0.30874113 | X34: 90227 | Y34: 105662.5 | Z34: =(Y34-X34)/X34 -> 0.17107407 | AA34: 44097.695 | AB34: =W34+AA34 -> 44097.695 | AC34: =AB34/$M$15 -> 0.047673184 | AE34: 75065 | AF34: =LS_RPRO!O15+MANUAL!M15+OUTSALE!M15 -> 246123.73 | AG34: =(AF34-AE34)/AE34 -> 2.2788081 | AI34: 217 | AJ34: =LS_RPRO!M15 -> 887 | AK34: =AJ34/AI34-1 -> 3.0875576 | AL34: 55 | AM34: =LS_RPRO!H15+MANUAL!H15+OUTSALE!H15 -> 142 | AN34: =AM34/AL34-1 -> 1.5818182 | AO34: =AL34/AI34 -> 0.25345622 | AP34: =AM34/AJ34 -> 0.16009019 | AQ34: =AP34-AO34 -> -0.09336603 | AS34: 0 | AT34: =LS_RPRO!K15 -> 5 | AU34: =(AT34-AS34)/AS34 -> #DIV/0! | AV34: 3 | AW34: =LS_RPRO!L15 -> 4 | AX34: =(AW34-AV34)/AV34 -> 0.33333333 | AY34: =AS34+AV34 -> 3 | AZ34: =AT34+AW34 -> 9 | BA34: =(AZ34-AY34)/AY34 -> 2 | BD34: 0 | BE34: =(BD34-BC34)/BC34 -> #DIV/0! | BI34: =(BH34-BG34)/BG34 -> #DIV/0! | BL34: =(BK34-BJ34)/BJ34 -> #DIV/0! | BM34: =BJ34/BG34 -> #DIV/0! | BN34: =BK34/BH34 -> #DIV/0! | BO34: =BN34-BM34 -> #DIV/0! | BQ34: 22 | BR34: 11 | BS34: =(BR34-BQ34)/BQ34 -> -0.5
D35: 11 | E35: Sunday | G35: 101294.5 | H35: =G35/$G$56 -> 0.041206978 | I35: =G$15*H35 -> 112720.52 | J35: Sunday | K35: =LS_RPRO!B16+MANUAL!B16+OUTSALE!B16 -> 315334.4 | L35: =K35-I35 -> 202613.88 | M35: =K35/G15 -> 0.11527606 | N35: =N34+L35 -> 1404770.1 | O35: 180 | P35: 149.7 | Q35: =LS_RPRO!C16+MANUAL!C16+OUTSALE!C16 -> 3289.55 | R35: =(Q35-P35)/P35 -> 20.974282 | T35: 12067.5 | U35: 31410.5 | V35: =(U35-T35)/T35 -> 1.6029004 | X35: 67262.5 | Y35: 69196 | Z35: =(Y35-X35)/X35 -> 0.028745586 | AA35: 22573.569 | AB35: =W35+AA35 -> 22573.569 | AC35: =AB35/$M$15 -> 0.024403859 | AE35: 29840.8 | AF35: =LS_RPRO!O16+MANUAL!M16+OUTSALE!M16 -> 263154.2 | AG35: =(AF35-AE35)/AE35 -> 7.8186041 | AI35: 129 | AJ35: =LS_RPRO!M16 -> 595 | AK35: =AJ35/AI35-1 -> 3.6124031 | AL35: 39 | AM35: =LS_RPRO!H16+MANUAL!H16+OUTSALE!H16 -> 133 | AN35: =AM35/AL35-1 -> 2.4102564 | AO35: =AL35/AI35 -> 0.30232558 | AP35: =AM35/AJ35 -> 0.22352941 | AQ35: =AP35-AO35 -> -0.07879617 | AS35: 0 | AT35: =LS_RPRO!K16 -> 0 | AU35: =(AT35-AS35)/AS35 -> #DIV/0! | AV35: 0 | AW35: =LS_RPRO!L16 -> 0 | AX35: =(AW35-AV35)/AV35 -> #DIV/0! | AY35: =AS35+AV35 -> 0 | AZ35: =AT35+AW35 -> 0 | BA35: =(AZ35-AY35)/AY35 -> #DIV/0! | BD35: 0 | BE35: =(BD35-BC35)/BC35 -> #DIV/0! | BI35: =(BH35-BG35)/BG35 -> #DIV/0! | BL35: =(BK35-BJ35)/BJ35 -> #DIV/0! | BM35: =BJ35/BG35 -> #DIV/0! | BN35: =BK35/BH35 -> #DIV/0! | BO35: =BN35-BM35 -> #DIV/0! | BQ35: 7 | BR35: 11 | BS35: =(BR35-BQ35)/BQ35 -> 0.57142857
D36: 12 | E36: Monday | G36: 96241.5 | H36: =G36/$G$56 -> 0.039151399 | I36: =G$15*H36 -> 107097.54 | J36: Monday | K36: =LS_RPRO!B17+MANUAL!B17+OUTSALE!B17 -> 158110 | L36: =K36-I36 -> 51012.459 | M36: =K36/G15 -> 0.057799904 | N36: =N35+L36 -> 1455782.5 | O36: 167 | P36: 0 | Q36: =LS_RPRO!C17+MANUAL!C17+OUTSALE!C17 -> 658.3 | R36: =(Q36-P36)/P36 -> #DIV/0! | T36: 18115 | U36: 34912.5 | V36: =(U36-T36)/T36 -> 0.92727022 | X36: 65476.5 | Y36: 66206.5 | Z36: =(Y36-X36)/X36 -> 0.011149038 | AA36: 18039.772 | AB36: =W36+AA36 -> 18039.772 | AC36: =AB36/$M$15 -> 0.019502456 | AE36: 43473 | AF36: =LS_RPRO!O17+MANUAL!M17+OUTSALE!M17 -> 119603.7 | AG36: =(AF36-AE36)/AE36 -> 1.751218 | AI36: 184 | AJ36: =LS_RPRO!M17 -> 336 | AK36: =AJ36/AI36-1 -> 0.82608696 | AL36: 46 | AM36: =LS_RPRO!H17+MANUAL!H17+OUTSALE!H17 -> 24 | AN36: =AM36/AL36-1 -> -0.47826087 | AO36: =AL36/AI36 -> 0.25 | AP36: =AM36/AJ36 -> 0.071428571 | AQ36: =AP36-AO36 -> -0.17857143 | AS36: 0 | AT36: =LS_RPRO!K17 -> 0 | AU36: =(AT36-AS36)/AS36 -> #DIV/0! | AV36: 8 | AW36: =LS_RPRO!L17 -> 2 | AX36: =(AW36-AV36)/AV36 -> -0.75 | AY36: =AS36+AV36 -> 8 | AZ36: =AT36+AW36 -> 2 | BA36: =(AZ36-AY36)/AY36 -> -0.75 | BD36: 0 | BE36: =(BD36-BC36)/BC36 -> #DIV/0! | BI36: =(BH36-BG36)/BG36 -> #DIV/0! | BL36: =(BK36-BJ36)/BJ36 -> #DIV/0! | BM36: =BJ36/BG36 -> #DIV/0! | BN36: =BK36/BH36 -> #DIV/0! | BO36: =BN36-BM36 -> #DIV/0! | BQ36: 7 | BR36: 13 | BS36: =(BR36-BQ36)/BQ36 -> 0.85714286
